Workbook

Sheet Summary
B2: 설화수 JP QA Result
C3: 1차 | D3: 2차
B4: QA Date | C4: 2026.04.16 | D4: 2026.04.24
B5: Overall Pass Rate | C5: 0.67 | D5: =1-AVERAGE(D9:D15) -> 0.75824176
B8: QA Elements | C8: Total | D8: Error Rate | E8: Pass | F8: Issue | G8: 비고 | H8: To-Be
B9: Status/Indexability | C9: =COUNTA(TOBE!A:A)-1 -> 26 | D9: =IFERROR(F9/C9,0) -> 0.19230769 | E9: =COUNTIF(TOBE!F:F,"Pass") -> 16 | F9: =COUNTIF(TOBE!F:F,"Fail") -> 5 | G9: NoIndex 처리 필요 | H9: TOBE 참고
B10: Title | C10: =COUNTA(TOBE!A:A)-1 -> 26 | D10: =IFERROR(F10/C10,0) -> 0 | E10: =COUNTIF(TOBE!H:H,"Pass") -> 16 | F10: =COUNTIF(TOBE!H:H,"Fail") -> 0 | G10: 브랜드명 수정 필요 | H10: N/A
B11: Meta Description | C11: =COUNTA(TOBE!A:A)-1 -> 26 | D11: =IFERROR(F11/C11,0) -> 0.26923077 | E11: =COUNTIF(TOBE!K:K,"Pass") -> 9 | F11: =COUNTIF(TOBE!K:K,"Fail") -> 7 | G11: 일부 권장 길이 미달/중복 | H11: TOBE 참고
B12: H1 | C12: =COUNTA(TOBE!A:A)-1 -> 26 | D12: =IFERROR(F12/C12,0) -> 0.038461538 | E12: =COUNTIF(TOBE!O:O,"Pass") -> 15 | F12: =COUNTIF(TOBE!O:O,"Fail") -> 1 | G12: H1 태그 중복 | H12: TOBE 참고
B13: Canonical | C13: =COUNTA(TOBE!A:A)-1 -> 26 | D13: =IFERROR(F13/C13,0) -> 0 | E13: =COUNTIF(TOBE!Q:Q,"Pass") -> 16 | F13: =COUNTIF(TOBE!Q:Q,"Fail") -> 0 | G13: N/A | H13: N/A
B14: Social Tag | C14: =COUNTA(TOBE!A:A)-1 -> 26 | D14: =IFERROR(F14/C14,0) -> 0.61538462 | E14: =COUNTIF(TOBE!AB:AB,"Pass") -> 0 | F14: =COUNTIF(TOBE!AB:AB,"Fail") -> 16 | G14: 일부 권장 길이 미달/중복/누락 | H14: TOBE 참고
B15: Schema | C15: =COUNTA(TOBE!A:A)-1 -> 26 | D15: =IFERROR(F15/C15,0) -> 0.57692308 | E15: =COUNTIF(TOBE!AI:AI,"Pass") -> 1 | F15: =COUNTIF(TOBE!AI:AI,"Fail") -> 15 | G15: 알맞지 않은 스키마 적용 (추후 작업 필요) | H15: TOBE 참고
B16: URL | C16: =COUNTA(TOBE!A:A)-1 -> 26 | D16: =IFERROR(F16/C16,0) -> 0 | E16: =COUNTIF(TOBE!C:C,"Pass") -> 16 | F16: =COUNTIF(TOBE!C:C,"Fail") -> 0 | G16: N/A | H16: N/A

Sheet TOBE
A1: Address | B1: 비고 | C1: Address QA | D1: Indexability | E1: Status Code | F1: Status/Indexability QA | G1: Title 1 | H1: Title QA | I1: Title to-be | J1: Meta Description 1 | K1: Meta Description QA | L1: Meta Description to-be | M1: H1-1 | N1: H1-2 | O1: H1 QA | P1: Canonical Link Element 1 | Q1: Canonical QA | R1: OG Title 1 | S1: OG Description 1 | T1: OG Type 1 | U1: OG Site Name 1 | V1: OG image 1 | W1: OG url 1 | X1: Twitter Card 1 | Y1: Twitter Title 1 | Z1: Twitter Site 1 | AA1: Twitter URL 1 | AB1: Social Tag QA | AC1: Type-1 | AD1: Updated | AE1: Type-2 | AF1: Type-3 | AG1: Type-4 | AH1: Type-5 | AI1: Schema QA
A2: https://sulwhasoo-jp.myshopify.com/pages/store-locator | C2: N/A | D2: Non-Indexable | E2: 404 | F2: N/A | G2: Store Locator | Sulwhasoo Japan | H2: N/A | J2: Store Locator is loading from Storemapper plugin... | K2: N/A | L2: This is the Sulwhasoo store locator page. Check the locations and information of nearby stores. | O2: N/A | P2: https://sulwhasoo-jp.myshopify.com/pages/store-locator | Q2: N/A | R2: Store Locator | Sulwhasoo Japan | S2: Meta Description to-be 내용 넣기 | T2: website | U2: Sulwhasoo Japan | V2: 설화수 로고 및 대표 이미지 넣기 - KR참고 | W2: https://sulwhasoo-jp.myshopify.com/pages/store-locator | X2: summary_large_image | Y2: Store Locator | Sulwhasoo Japan | AA2: url 채우기 | AB2: N/A | AC2: Organization | AI2: N/A
A3: https://sulwhasoo-jp.myshopify.com/pages/site-map | C3: Pass | D3: Indexable | E3: 200 | F3: Pass | G3: Site Map | Sulwhasoo Japan | H3: Pass | K3: Pass | L3: Sulwhasoo Sitemap. You can view the entire menu and key content of the Sulwhasoo website at a glance. | M3: Site Map | O3: Pass | P3: https://sulwhasoo-jp.myshopify.com/pages/site-map | Q3: Pass | R3: Site Map | Sulwhasoo Japan | S3: Sulwhasoo Sitemap. You can view the entire menu and key content of the Sulwhasoo website at a glance. | T3: website | U3: Sulwhasoo Japan | V3: http://sulwhasoo-jp.myshopify.com/cdn/shop/articles/Sulwhasoo_JP.webp?v=1776042225 | W3: https://sulwhasoo-jp.myshopify.com/pages/site-map | X3: summary_large_image | Y3: Site Map | Sulwhasoo Japan | AA3: url 채우기 | AB3: Fail | AC3: Organization | AI3: Fail
A4: https://sulwhasoo-jp.myshopify.com/pages/shopping-guide | C4: Pass | D4: Indexable | E4: 200 | F4: Pass | G4: Shopping Guide | Sulwhasoo Japan | H4: Pass | K4: Fail | L4: Shop Sulwhasoo Japan with ease. Free shipping on orders over ¥6,000. We support PayPay, Rakuten Pay & credit cards. See our guide for ordering & delivery info. | M4: ご注文について | O4: Pass | P4: https://sulwhasoo-jp.myshopify.com/pages/shopping-guide | Q4: Pass | R4: Shopping Guide | Sulwhasoo Japan | S4: Meta Description to-be 내용 넣기 | T4: website | U4: Sulwhasoo Japan | V4: http://sulwhasoo-jp.myshopify.com/cdn/shop/articles/Sulwhasoo_JP.webp?v=1776042225 | W4: https://sulwhasoo-jp.myshopify.com/pages/shopping-guide | X4: summary_large_image | Y4: Shopping Guide | Sulwhasoo Japan | AA4: url 채우기 | AB4: Fail | AC4: Organization | AI4: Fail
A5: https://sulwhasoo-jp.myshopify.com/pages/shop-info | C5: N/A | D5: Non-Indexable | E5: 404 | F5: N/A | G5: Shop Info | Sulwhasoo Japan | H5: N/A | K5: N/A | L5: Discover the heritage of Sulwhasoo Japan. View official store information, brand philosophy, and legal notices for our online and offline presence. | M5: Shop Info | O5: N/A | P5: https://sulwhasoo-jp.myshopify.com/pages/shop-info | Q5: N/A | R5: Shop Info | Sulwhasoo Japan | S5: Meta Description to-be 내용 넣기 | T5: website | U5: Sulwhasoo Japan | V5: 설화수 로고 및 대표 이미지 넣기 - KR참고 | W5: https://sulwhasoo-jp.myshopify.com/pages/shop-info | X5: summary_large_image | Y5: Shop Info | Sulwhasoo Japan | AA5: url 채우기 | AB5: N/A | AC5: Organization | AI5: N/A
A6: https://sulwhasoo-jp.myshopify.com/pages/point-list | C6: N/A | D6: Indexable | E6: 200 | F6: Fail | G6: Point List | Sulwhasoo Japan | H6: N/A | K6: N/A | M6: ポイント情報 | O6: N/A | P6: https://sulwhasoo-jp.myshopify.com/pages/point-list | Q6: N/A | R6: Point List | Sulwhasoo Japan | S6: Sulwhasoo Japan | T6: website | U6: Sulwhasoo Japan | W6: https://sulwhasoo-jp.myshopify.com/pages/point-list | X6: summary_large_image | Y6: Point List | Sulwhasoo Japan | AB6: N/A | AC6: Organization | AI6: N/A
A7: https://sulwhasoo-jp.myshopify.com/pages/order-list | C7: N/A | D7: Indexable | E7: 200 | F7: Fail | G7: Order List | Sulwhasoo Japan | H7: N/A | K7: N/A | M7: ご注文管理 | O7: N/A | P7: https://sulwhasoo-jp.myshopify.com/pages/order-list | Q7: N/A | R7: Order List | Sulwhasoo Japan | S7: Sulwhasoo Japan | T7: website | U7: Sulwhasoo Japan | W7: https://sulwhasoo-jp.myshopify.com/pages/order-list | X7: summary_large_image | Y7: Order List | Sulwhasoo Japan | AB7: N/A | AC7: Organization | AI7: N/A
A8: https://sulwhasoo-jp.myshopify.com/pages/mypage | C8: N/A | D8: Indexable | E8: 200 | F8: Fail | G8: mypage | Sulwhasoo Japan | H8: N/A | K8: N/A | M8: マイページ | O8: N/A | P8: https://sulwhasoo-jp.myshopify.com/pages/mypage | Q8: N/A | R8: mypage | Sulwhasoo Japan | S8: Sulwhasoo Japan | T8: website | U8: Sulwhasoo Japan | W8: https://sulwhasoo-jp.myshopify.com/pages/mypage | X8: summary_large_image | Y8: mypage | Sulwhasoo Japan | AB8: N/A | AC8: Organization | AI8: N/A
A9: https://sulwhasoo-jp.myshopify.com/pages/my-address | C9: N/A | D9: Indexable | E9: 200 | F9: Fail | G9: my-address | Sulwhasoo Japan | H9: N/A | K9: N/A | M9: My Page | O9: N/A | P9: https://sulwhasoo-jp.myshopify.com/pages/my-address | Q9: N/A | R9: my-address | Sulwhasoo Japan | S9: Sulwhasoo Japan | T9: website | U9: Sulwhasoo Japan | W9: https://sulwhasoo-jp.myshopify.com/pages/my-address | X9: summary_large_image | Y9: my-address | Sulwhasoo Japan | AB9: N/A | AC9: Organization | AI9: N/A
A10: https://sulwhasoo-jp.myshopify.com/pages/membership | C10: Pass | D10: Indexable | E10: 200 | F10: Pass | G10: Membership | Sulwhasoo Japan | H10: Pass | K10: Fail | L10: Bergabung dengan keanggotaan Sulwhasoo dan dapatkan beragam keistimewaan. | M10: メンバーシップ | O10: Pass | P10: https://sulwhasoo-jp.myshopify.com/pages/membership | Q10: Pass | R10: Membership | Sulwhasoo Japan | S10: Meta Description to-be 내용 넣기 | T10: website | U10: Sulwhasoo Japan | V10: http://sulwhasoo-jp.myshopify.com/cdn/shop/articles/Sulwhasoo_JP.webp?v=1776042225 | W10: https://sulwhasoo-jp.myshopify.com/pages/membership | X10: summary_large_image | Y10: Membership | Sulwhasoo Japan | AA10: url 채우기 | AB10: Fail | AC10: Organization | AI10: Fail
A11: https://sulwhasoo-jp.myshopify.com/pages/legal-notice | C11: N/A | D11: Non-Indexable | E11: 404 | F11: N/A | G11: 特定商取引法に基づく表記 | Sulwhasoo Japan | H11: N/A | J11: 事業者名 アモーレパシフィックジャパン株式会社 所在地 〒150-0012 東京都渋谷区広尾１－１３－７ 恵比寿イーストビル2階 代表者 代表 松井 理奈 お問い合わせ Sulwhasoo カスタマーサポート TEL：0120-929-744 受付時間： 月~金 10:00 ~ 18:00＜祝祭日、年末年始・夏期休暇を除く＞ フォームでのお問い合わせはこちら URL https://jp.sulwhasoo.com/ 販売価格 各商品詳細ページに表示された価格に基づきます。表示価格は本体価格に消費税額を加えた「お支払い総額（税込価格）」となっております。 商品代金以外の必要料金 ■送料：通常配送料金は、550円（税込）※沖縄、北海 | K11: N/A | O11: N/A | P11: https://sulwhasoo-jp.myshopify.com/pages/legal-notice | Q11: N/A | R11: 特定商取引法に基づく表記 | Sulwhasoo Japan | S11: 事業者名 アモーレパシフィックジャパン株式会社 所在地 〒150-0012 東京都渋谷区広尾１－１３－７ 恵比寿イーストビル2階 代表者 代表 松井 理奈 お問い合わせ Sulwhasoo カスタマーサポート TEL：0120-929-744 受付時間： 月~金 10:00 ~ 18:00＜祝祭日、年末年始・夏期休暇を除く＞ フォームでのお問い合わせはこちら URL https://jp.sulwhasoo.com/ 販売価格 各商品詳細ページに表示された価格に基づきます。表示価格は本体価格に消費税額を加えた「お支払い総額（税込価格）」となっております。 商品代金以外の必要料金 ■送料：通常配送料金は、550円（税込）※沖縄、北海 | T11: website | U11: Sulwhasoo Japan | V11: 설화수 로고 및 대표 이미지 넣기 - KR참고 | W11: https://sulwhasoo-jp.myshopify.com/pages/legal-notice | X11: summary_large_image | Y11: 特定商取引法に基づく表記 | Sulwhasoo Japan | AA11: url 채우기 | AB11: N/A | AC11: Organization | AI11: N/A
A12: https://sulwhasoo-jp.myshopify.com/pages/faq | C12: Pass | D12: Indexable | E12: 200 | F12: Pass | G12: FAQ | Sulwhasoo Japan | H12: Pass | K12: Fail | L12: Sulwhasoo FAQ. Find quick answers to your questions about order status, payment methods, shipping tracking, and product inquiries in one place. | M12: よくあるご質問 | O12: Pass | P12: https://sulwhasoo-jp.myshopify.com/pages/faq | Q12: Pass | R12: FAQ | Sulwhasoo Japan | S12: Meta Description to-be 내용 넣기 | T12: website | U12: Sulwhasoo Japan | V12: http://sulwhasoo-jp.myshopify.com/cdn/shop/articles/Sulwhasoo_JP.webp?v=1776042225 | W12: https://sulwhasoo-jp.myshopify.com/pages/faq | X12: summary_large_image | Y12: FAQ | Sulwhasoo Japan | AA12: url 채우기 | AB12: Fail | AC12: Organization | AI12: Fail
A13: https://sulwhasoo-jp.myshopify.com/pages/exchange-return | C13: Pass | D13: Indexable | E13: 200 | F13: Pass | G13: Exchange Return | Sulwhasoo Japan | H13: Pass | K13: Fail | L13: Sulwhasoo Exchange & Return. Guide for returning damaged or incorrect items. Contact our support team to request an exchange or refund under our policy. | M13: 交換・返品について | O13: Pass | P13: https://sulwhasoo-jp.myshopify.com/pages/exchange-return | Q13: Pass | R13: Exchange Return | Sulwhasoo Japan | S13: Meta Description to-be 내용 넣기 | T13: website | U13: Sulwhasoo Japan | V13: http://sulwhasoo-jp.myshopify.com/cdn/shop/articles/Sulwhasoo_JP.webp?v=1776042225 | W13: https://sulwhasoo-jp.myshopify.com/pages/exchange-return | X13: summary_large_image | Y13: Exchange Return | Sulwhasoo Japan | AA13: url 채우기 | AB13: Fail | AC13: Organization | AI13: Fail
A14: https://sulwhasoo-jp.myshopify.com/pages/edit-account | C14: N/A | D14: Indexable | E14: 200 | F14: Fail | G14: Edit Account | Sulwhasoo Japan | H14: N/A | K14: N/A | M14: 個人情報の修正 | O14: N/A | P14: https://sulwhasoo-jp.myshopify.com/pages/edit-account | Q14: N/A | R14: Edit Account | Sulwhasoo Japan | S14: Sulwhasoo Japan | T14: website | U14: Sulwhasoo Japan | W14: https://sulwhasoo-jp.myshopify.com/pages/edit-account | X14: summary_large_image | Y14: Edit Account | Sulwhasoo Japan | AB14: N/A | AC14: Organization | AI14: N/A
A15: https://sulwhasoo-jp.myshopify.com/pages/contact | C15: Pass | D15: Indexable | E15: 200 | F15: Pass | G15: Contact | Sulwhasoo Japan | H15: Pass | K15: Fail | L15: Contact Sulwhasoo for inquiries on products, orders, or shipping. Please fill out the form below for assistance. | M15: お問い合わせ | O15: Pass | P15: https://sulwhasoo-jp.myshopify.com/pages/contact | Q15: Pass | R15: Contact | Sulwhasoo Japan | S15: Meta Description to-be 내용 넣기 | T15: website | U15: Sulwhasoo Japan | V15: http://sulwhasoo-jp.myshopify.com/cdn/shop/articles/Sulwhasoo_JP.webp?v=1776042225 | W15: https://sulwhasoo-jp.myshopify.com/pages/contact | X15: summary_large_image | Y15: Contact | Sulwhasoo Japan | AA15: url 채우기 | AB15: Fail | AC15: Organization | AI15: Fail
A16: https://sulwhasoo-jp.myshopify.com/pages/brand-sustainability | C16: Pass | D16: Indexable | E16: 200 | F16: Pass | G16: Brand Sustainability – Earth & Culture | Sulwhasoo Japan | H16: Pass | J16: Sulwhasoo’s sustainable beauty is built on Ginseng Science, Environmental Care, and Cultural Heritage to shape a better future. | K16: Pass | M16: Brand Sustainability | Sulwhasoo Japan | N16: 持続可能な未来のための約束 | O16: Fail | P16: https://sulwhasoo-jp.myshopify.com/pages/brand-sustainability | Q16: Pass | R16: Brand Sustainability – Earth & Culture | Sulwhasoo Japan | S16: Sulwhasoo’s sustainable beauty is built on Ginseng Science, Environmental Care, and Cultural Heritage to shape a better future. | T16: website | U16: Sulwhasoo Japan | V16: http://sulwhasoo-jp.myshopify.com/cdn/shop/articles/Sulwhasoo_JP.webp?v=1776042225 | W16: https://sulwhasoo-jp.myshopify.com/pages/brand-sustainability | X16: summary_large_image | Y16: Brand Sustainability – Earth & Culture | Sulwhasoo Japan | AA16: url 채우기 | AB16: Fail | AC16: Organization | AI16: Fail
A17: https://sulwhasoo-jp.myshopify.com/pages/brand-story | C17: Pass | D17: Indexable | E17: 200 | F17: Pass | G17: Brand Story | Sulwhasoo Japan | H17: Pass | J17: Sulwhasoo fuses Korean tradition with cutting-edge science, using JAUM Activator® and ginseng research for youthful, radiant skin | K17: Pass | M17: Brand Story | Sulwhasoo Japan | N17: 時の流れにゆるがない美しさへの旅 | O17: Pass | P17: https://sulwhasoo-jp.myshopify.com/pages/brand-story | Q17: Pass | R17: Brand Story | Sulwhasoo Japan | S17: Sulwhasoo fuses Korean tradition with cutting-edge science, using JAUM Activator® and ginseng research for youthful, radiant skin | T17: website | U17: Sulwhasoo Japan | V17: http://sulwhasoo-jp.myshopify.com/cdn/shop/articles/Sulwhasoo_JP.webp?v=1776042225 | W17: https://sulwhasoo-jp.myshopify.com/pages/brand-story | X17: summary_large_image | Y17: Brand Story | Sulwhasoo Japan | AA17: url 채우기 | AB17: Fail | AC17: Organization | AI17: Fail
A18: https://sulwhasoo-jp.myshopify.com/pages/activate-account-form | C18: N/A | D18: Non-Indexable | E18: 404 | F18: N/A | G18: Activate Account Form | Sulwhasoo Japan | H18: N/A | K18: N/A | O18: N/A | P18: https://sulwhasoo-jp.myshopify.com/pages/activate-account-form | Q18: N/A | R18: Activate Account Form | Sulwhasoo Japan | S18: Sulwhasoo Japan | T18: website | U18: Sulwhasoo Japan | W18: https://sulwhasoo-jp.myshopify.com/pages/activate-account-form | X18: summary_large_image | Y18: Activate Account Form | Sulwhasoo Japan | AB18: N/A | AC18: Organization | AI18: N/A
A19: https://sulwhasoo-jp.myshopify.com/blogs/sulwhasoo-post/journey-to-holistic-beauty-時の流れに揺るがない美しさへの旅 | C19: Pass | D19: Indexable | E19: 200 | F19: Pass | G19: 「Journey to Holistic Beauty」時の流れに揺るがない美しさへの旅 | Sulwhasoo Japan | H19: Pass | J19: 時を超えて愛される韓国発ラグジュアリービューティーブランド、Sulwhasoo（雪花秀／ソルファス）。その世界観と高麗人参サイエンスを体験できる「Sulwhasoo Lounge（ソルファスラウンジ）」が、5月6日（水）より@cosme TOKYOにて1週間限定オープン。 アモーレパシフィックジャパン株式会社（所在地：東京都渋谷区 代表：羅政均）が展開する、韓国発ラグジュアリービューティーブランド『Sulwhasoo（雪花秀/ソルファス）』は、5月6日（水）から12日（火）までの1週間、@cosme TOKYO ポップアップストア1階にて「Sulwhasoo Lounge（ソルファスラウンジ）」を開催します。 長年にわたり韓国ビュー | K19: Pass | O19: Pass | P19: https://sulwhasoo-jp.myshopify.com/blogs/sulwhasoo-post/journey-to-holistic-beauty-時の流れに揺るがない美しさへの旅 | Q19: Pass | R19: 「Journey to Holistic Beauty」時の流れに揺るがない美しさへの旅 | Sulwhasoo Japan | S19: 時を超えて愛される韓国発ラグジュアリービューティーブランド、Sulwhasoo（雪花秀／ソルファス）。その世界観と高麗人参サイエンスを体験できる「Sulwhasoo Lounge（ソルファスラウンジ）」が、5月6日（水）より@cosme TOKYOにて1週間限定オープン。 アモーレパシフィックジャパン株式会社（所在地：東京都渋谷区 代表：羅政均）が展開する、韓国発ラグジュアリービューティーブランド『Sulwhasoo（雪花秀/ソルファス）』は、5月6日（水）から12日（火）までの1週間、@cosme TOKYO ポップアップストア1階にて「Sulwhasoo Lounge（ソルファスラウンジ）」を開催します。 長年にわたり韓国ビュー | T19: article | U19: Sulwhasoo Japan | V19: http://sulwhasoo-jp.myshopify.com/cdn/shop/articles/Sulwhasoo_JP.webp?v=1776042225 | W19: https://sulwhasoo-jp.myshopify.com/blogs/sulwhasoo-post/journey-to-holistic-beauty-%e6%99%82%e3%81%ae%e6%b5%81%e3%82%8c%e3%81%ab%e6%8f%ba%e3%82%8b%e3%81%8c%e3%81%aa%e3%81%84%e7%be%8e%e3%81%97%e3%81%95%e3%81%b8%e3%81%ae%e6%97%85 | X19: summary_large_image | Y19: 「Journey to Holistic Beauty」時の流れに揺るがない美しさへの旅 | Sulwhasoo Japan | AA19: url 채우기 | AB19: Fail | AC19: Organization | AE19: Article | AF19: WebPage | AG19: Person | AH19: Organization | AI19: Fail
A20: https://sulwhasoo-jp.myshopify.com/blogs/sulwhasoo-post/concentrated-ginseng-rejuvenating-cream | C20: Pass | D20: Indexable | E20: 200 | F20: Pass | G20: Concentrated Ginseng Rejuvenating Cream | Sulwhasoo Japan | H20: Pass | J20: Discover 60 years of Ginseng science with Sulwhasoo’s Concentrated Ginseng Rejuvenating Cream, boosting elasticity for a youthful glow. | K20: Pass | M20: Concentrated Ginseng Rejuvenating Cream | O20: Pass | P20: https://sulwhasoo-jp.myshopify.com/blogs/sulwhasoo-post/concentrated-ginseng-rejuvenating-cream | Q20: Pass | R20: Concentrated Ginseng Rejuvenating Cream | Sulwhasoo Japan | S20: Discover 60 years of Ginseng science with Sulwhasoo’s Concentrated Ginseng Rejuvenating Cream, boosting elasticity for a youthful glow. | T20: article | U20: Sulwhasoo Japan | V20: http://sulwhasoo-jp.myshopify.com/cdn/shop/articles/Sulwhasoo_JP.webp?v=1776042225 | W20: https://sulwhasoo-jp.myshopify.com/blogs/sulwhasoo-post/concentrated-ginseng-rejuvenating-cream | X20: summary_large_image | Y20: Concentrated Ginseng Rejuvenating Cream | Sulwhasoo Japan | AA20: url 채우기 | AB20: Fail | AC20: Organization | AE20: Article | AF20: WebPage | AG20: Person | AH20: Organization | AI20: Fail
A21: https://sulwhasoo-jp.myshopify.com/blogs/sulwhasoo-post/2025-first-care-activating-serum-introduction | C21: Pass | D21: Indexable | E21: 200 | F21: Pass | G21: FIRST CARE ACTIVATING SERUM – Sulwhasoo Japan | H21: Pass | I21: FIRST CARE ACTIVATING SERUM | Sulwhasoo Japan | J21: REVITALIZE YOUR SKIN FOR A HEALTHY, YOUTHFUL COMPLEXION | K21: Pass | M21: 2025 FIRST CARE ACTIVATING SERUM | N21: 潤燥ユンジョ ファーストケア アクティブセラム VI | O21: Pass | P21: https://sulwhasoo-jp.myshopify.com/blogs/sulwhasoo-post/2025-first-care-activating-serum-introduction | Q21: Pass | R21: FIRST CARE ACTIVATING SERUM – Sulwhasoo Japan | S21: REVITALIZE YOUR SKIN FOR A HEALTHY, YOUTHFUL COMPLEXION | T21: article | U21: Sulwhasoo Japan | V21: http://sulwhasoo-jp.myshopify.com/cdn/shop/articles/Sulwhasoo_JP.webp?v=1776042225 | W21: https://sulwhasoo-jp.myshopify.com/blogs/sulwhasoo-post/2025-first-care-activating-serum-introduction | X21: summary_large_image | Y21: FIRST CARE ACTIVATING SERUM – Sulwhasoo Japan | AA21: url 채우기 | AB21: Fail | AC21: Organization | AE21: Article | AF21: WebPage | AG21: Person | AH21: Organization | AI21: Fail
A22: https://sulwhasoo-jp.myshopify.com/blogs/sulwhasoo-post | C22: Pass | D22: Indexable | E22: 200 | F22: Pass | G22: Brand News | Heritage-Inspired Luxury | Sulwhasoo Japan | H22: Pass | J22: Sulwhasoo, an iconic luxury beauty brand, dates back to 1932. Known for its pioneering spirit, it was the first to create products infused with ginseng. | K22: Pass | M22: BRAND NEWS | O22: Pass | P22: https://sulwhasoo-jp.myshopify.com/blogs/sulwhasoo-post | Q22: Pass | R22: Brand News | Heritage-Inspired Luxury | Sulwhasoo Japan | S22: Sulwhasoo, an iconic luxury beauty brand, dates back to 1932. Known for its pioneering spirit, it was the first to create products infused with ginseng. | T22: website | U22: Sulwhasoo Japan | V22: http://sulwhasoo-jp.myshopify.com/cdn/shop/articles/Sulwhasoo_JP.webp?v=1776042225 | W22: https://sulwhasoo-jp.myshopify.com/blogs/sulwhasoo-post | X22: summary_large_image | Y22: Brand News | Heritage-Inspired Luxury | Sulwhasoo Japan | AA22: url 채우기 | AB22: Fail | AC22: Organization | AI22: Fail
A23: https://sulwhasoo-jp.myshopify.com/blogs/notice | C23: Pass | D23: Indexable | E23: 200 | F23: Pass | G23: Notice | Sulwhasoo Japan | H23: Pass | K23: Fail | L23: Sulwhasoo Notice. Stay updated with the latest news, service announcements, and shipping schedules from our official store. | M23: お知らせ | O23: Pass | P23: https://sulwhasoo-jp.myshopify.com/blogs/notice | Q23: Pass | R23: Notice | Sulwhasoo Japan | S23: Meta Description to-be 내용 넣기 | T23: website | U23: Sulwhasoo Japan | V23: http://sulwhasoo-jp.myshopify.com/cdn/shop/articles/Sulwhasoo_JP.webp?v=1776042225 | W23: https://sulwhasoo-jp.myshopify.com/blogs/notice | X23: summary_large_image | Y23: Notice | Sulwhasoo Japan | AA23: url 채우기 | AB23: Fail | AC23: Organization | AI23: Fail
A24: https://sulwhasoo-jp.myshopify.com/blogs/event/公式ストアオープン記念-レビューキャンペーン | C24: Pass | D24: Indexable | E24: 200 | F24: Pass | G24: 公式ストアオープン記念 レビューキャンペーン | Sulwhasoo Japan | H24: Pass | J24: 公式ストアオープン記念レビューキャンペーン。 キャンペーン期間は2026年4月28日から6月30日までです。 対象商品レビュー投稿者の中から抽選で5名様にスペシャルギフトをプレゼントします。 | K24: Pass | O24: Pass | P24: https://sulwhasoo-jp.myshopify.com/blogs/event/公式ストアオープン記念-レビューキャンペーン | Q24: Pass | R24: 公式ストアオープン記念 レビューキャンペーン | Sulwhasoo Japan | S24: 公式ストアオープン記念レビューキャンペーン。 キャンペーン期間は2026年4月28日から6月30日までです。 対象商品レビュー投稿者の中から抽選で5名様にスペシャルギフトをプレゼントします。 | T24: article | U24: Sulwhasoo Japan | V24: http://sulwhasoo-jp.myshopify.com/cdn/shop/articles/Sulwhasoo_JP.webp?v=1776042225 | W24: https://sulwhasoo-jp.myshopify.com/blogs/event/%e5%85%ac%e5%bc%8f%e3%82%b9%e3%83%88%e3%82%a2%e3%82%aa%e3%83%bc%e3%83%97%e3%83%b3%e8%a8%98%e5%bf%b5-%e3%83%ac%e3%83%93%e3%83%a5%e3%83%bc%e3%82%ad%e3%83%a3%e3%83%b3%e3%83%9a%e3%83%bc%e3%83%b3 | X24: summary_large_image | Y24: 公式ストアオープン記念 レビューキャンペーン | Sulwhasoo Japan | AA24: url 채우기 | AB24: Fail | AC24: Organization | AE24: Article | AF24: WebPage | AG24: Person | AH24: Organization | AI24: Fail
A25: https://sulwhasoo-jp.myshopify.com/blogs/event/cosme-store-tokyoにてpopupstore開催 | C25: N/A | D25: Non-Indexable | E25: 404 | F25: N/A | G25: @cosme store TOKYOにてPOPUPSTORE開催 | Sulwhasoo Japan | H25: N/A | J25: 韓国発ラグジュアリースキンケアブランド「Sulwhasoo（ソルファス）」は、2026年5月6日から5月12日までの期間、＠cosme storeにてPOPUPSTOREを開催いたします【POPUP STORE開催概要】 期間：2026年5月6日～2026年5月12日 開催時間：11:00～21:00 場所：@cosme TOKYO 住所：東京都渋谷区神宮前1-14-27 | K25: N/A | M25: @cosme store TOKYOにてPOPUPSTORE開催 | O25: N/A | P25: https://sulwhasoo-jp.myshopify.com/blogs/event/cosme-store-tokyoにてpopupstore開催 | Q25: N/A | R25: @cosme store TOKYOにてPOPUPSTORE開催 | Sulwhasoo Japan | S25: 韓国発ラグジュアリースキンケアブランド「Sulwhasoo（ソルファス）」は、2026年5月6日から5月12日までの期間、＠cosme storeにてPOPUPSTOREを開催いたします【POPUP STORE開催概要】 期間：2026年5月6日～2026年5月12日 開催時間：11:00～21:00 場所：@cosme TOKYO 住所：東京都渋谷区神宮前1-14-27 | T25: article | U25: Sulwhasoo Japan | V25: http://sulwhasoo-jp.myshopify.com/cdn/shop/articles/111170002325_01_d50df340-e78c-4d41-ae4f-ea577d47fb7b.jpg?v=1776047739 | W25: https://sulwhasoo-jp.myshopify.com/blogs/event/cosme-store-tokyo%e3%81%ab%e3%81%a6popupstore%e9%96%8b%e5%82%ac | X25: summary_large_image | Y25: @cosme store TOKYOにてPOPUPSTORE開催 | Sulwhasoo Japan | AA25: url 채우기 | AB25: N/A | AC25: Organization | AE25: Article | AF25: WebPage | AG25: Person | AH25: Organization | AI25: N/A
A26: https://sulwhasoo-jp.myshopify.com/blogs/event | C26: Pass | D26: Indexable | E26: 200 | F26: Pass | G26: Event | Sulwhasoo Japan | H26: Pass | K26: Fail | L26: Sulwhasoo Events. Discover exclusive promotions, gift-with-purchase offers, and seasonal specials for our members. Check out our current events now. | M26: イベント | O26: Pass | P26: https://sulwhasoo-jp.myshopify.com/blogs/event | Q26: Pass | R26: Event | Sulwhasoo Japan | S26: Meta Description to-be 내용 넣기 | T26: website | U26: Sulwhasoo Japan | V26: http://sulwhasoo-jp.myshopify.com/cdn/shop/articles/Sulwhasoo_JP.webp?v=1776042225 | W26: https://sulwhasoo-jp.myshopify.com/blogs/event | X26: summary_large_image | Y26: Event | Sulwhasoo Japan | AA26: url 채우기 | AB26: Fail | AC26: Organization | AI26: Fail
A27: https://sulwhasoo-jp.myshopify.com/ | C27: Pass | D27: Indexable | E27: 200 | F27: Pass | G27: Sulwhasoo Japan | H27: Pass | K27: Pass | L27: Sulwhasoo Japan Official Website. Experience our luxury skincare line featuring First Care Activating Serum. Shop now for radiant beauty. | M27: Sulwhasoo Japan | O27: Pass | P27: https://sulwhasoo-jp.myshopify.com/ | Q27: Pass | R27: Sulwhasoo Japan | S27: Sulwhasoo（ソルファス）Japan公式オンラインストア。韓国伝統の知恵と最先端の現代技術を融合させたスキンケアブランド「雪花秀」公式ストアです | T27: website | U27: Sulwhasoo Japan | V27: http://sulwhasoo-jp.myshopify.com/cdn/shop/articles/Sulwhasoo_JP.webp?v=1776042225 | W27: https://sulwhasoo-jp.myshopify.com/ | X27: summary_large_image | Y27: Sulwhasoo Japan | AA27: url 채우기 | AB27: Fail | AC27: Organization | AE27: WebSite | AF27: SearchAction | AI27: Pass

Sheet TOBE-1차
A1: Address | B1: 비고 | C1: Address QA | D1: Indexability | E1: Updated | F1: Status Code | G1: Status/Indexability QA | H1: Title 1 | I1: Title QA | J1: Title to-be | K1: Meta Description 1 | L1: Meta Description QA | M1: Meta Description to-be | N1: H1-1 | O1: H1-2 | P1: H1 QA | Q1: Canonical Link Element 1 | R1: Canonical QA | S1: OG Title 1 | T1: OG Description 1 | U1: OG Type 1 | V1: OG Site Name 1 | W1: OG image 1 | X1: OG url 1 | Y1: Twitter Card 1 | Z1: Twitter Title 1 | AA1: Twitter Site 1 | AB1: Twitter URL 1 | AC1: Social Tag QA | AD1: Type-1 | AE1: Type-2 | AF1: Type-3 | AG1: Type-4 | AH1: Type-5 | AI1: Schema QA
A2: https://sulwhasoo-jp.myshopify.com/pages/store-locator | C2: Pass | D2: Indexable | E2: 확인 불가 | F2: 200 | G2: Pass | H2: Store Locator | Sulwhasoo Japan | I2: Pass | K2: Store Locator is loading from Storemapper plugin... | L2: Fail | M2: This is the Sulwhasoo store locator page. Check the locations and information of nearby stores. | P2: Pass | Q2: https://sulwhasoo-jp.myshopify.com/pages/store-locator | R2: Pass | S2: Store Locator | Sulwhasoo Japan | T2: Meta Description to-be 내용 넣기 | U2: website | V2: Sulwhasoo Japan | W2: 설화수 로고 및 대표 이미지 넣기 - KR참고 | X2: https://sulwhasoo-jp.myshopify.com/pages/store-locator | Y2: summary_large_image | Z2: Store Locator | Sulwhasoo Japan | AB2: url 채우기 | AC2: Fail | AD2: Organization | AI2: Fail
A3: https://sulwhasoo-jp.myshopify.com/pages/site-map | C3: Pass | D3: Indexable | E3: O | F3: 200 | G3: Pass | H3: Site Map | Sulwhasoo Japan | I3: Pass | L3: Fail | M3: Sulwhasoo Sitemap. You can view the entire menu and key content of the Sulwhasoo website at a glance. | N3: Site Map | P3: Pass | Q3: https://sulwhasoo-jp.myshopify.com/pages/site-map | R3: Pass | S3: Site Map | Sulwhasoo Japan | T3: Meta Description to-be 내용 넣기 | U3: website | V3: Sulwhasoo Japan | W3: 설화수 로고 및 대표 이미지 넣기 - KR참고 | X3: https://sulwhasoo-jp.myshopify.com/pages/site-map | Y3: summary_large_image | Z3: Site Map | Sulwhasoo Japan | AB3: url 채우기 | AC3: Fail | AD3: Organization | AI3: Fail
A4: https://sulwhasoo-jp.myshopify.com/pages/shopping-guide | C4: Pass | D4: Indexable | E4: O | F4: 200 | G4: Pass | H4: Shopping Guide | Sulwhasoo Japan | I4: Pass | L4: Fail | M4: Shop Sulwhasoo Japan with ease. Free shipping on orders over ¥6,000. We support PayPay, Rakuten Pay & credit cards. See our guide for ordering & delivery info. | N4: ご注文について | P4: Pass | Q4: https://sulwhasoo-jp.myshopify.com/pages/shopping-guide | R4: Pass | S4: Shopping Guide | Sulwhasoo Japan | T4: Meta Description to-be 내용 넣기 | U4: website | V4: Sulwhasoo Japan | W4: 설화수 로고 및 대표 이미지 넣기 - KR참고 | X4: https://sulwhasoo-jp.myshopify.com/pages/shopping-guide | Y4: summary_large_image | Z4: Shopping Guide | Sulwhasoo Japan | AB4: url 채우기 | AC4: Fail | AD4: Organization | AI4: Fail
A5: https://sulwhasoo-jp.myshopify.com/pages/shop-info | C5: Pass | D5: Indexable | E5: O | F5: 200 | G5: Pass | H5: Shop Info | Sulwhasoo Japan | I5: Pass | L5: Fail | M5: Discover the heritage of Sulwhasoo Japan. View official store information, brand philosophy, and legal notices for our online and offline presence. | N5: Shop Info | P5: Pass | Q5: https://sulwhasoo-jp.myshopify.com/pages/shop-info | R5: Pass | S5: Shop Info | Sulwhasoo Japan | T5: Meta Description to-be 내용 넣기 | U5: website | V5: Sulwhasoo Japan | W5: 설화수 로고 및 대표 이미지 넣기 - KR참고 | X5: https://sulwhasoo-jp.myshopify.com/pages/shop-info | Y5: summary_large_image | Z5: Shop Info | Sulwhasoo Japan | AB5: url 채우기 | AC5: Fail | AD5: Organization | AI5: Fail
A6: https://sulwhasoo-jp.myshopify.com/pages/point-list | C6: N/A | D6: Indexable | E6: O | F6: 200 | G6: Fail | H6: Point List | Sulwhasoo Japan | I6: N/A | L6: N/A | N6: ポイント情報 | P6: N/A | Q6: https://sulwhasoo-jp.myshopify.com/pages/point-list | R6: N/A | S6: Point List | Sulwhasoo Japan | T6: Sulwhasoo Japan | U6: website | V6: Sulwhasoo Japan | X6: https://sulwhasoo-jp.myshopify.com/pages/point-list | Y6: summary_large_image | Z6: Point List | Sulwhasoo Japan | AC6: N/A | AD6: Organization | AI6: N/A
A7: https://sulwhasoo-jp.myshopify.com/pages/order-list | C7: N/A | D7: Indexable | E7: O | F7: 200 | G7: Fail | H7: Order List | Sulwhasoo Japan | I7: N/A | L7: N/A | N7: ご注文管理 | P7: N/A | Q7: https://sulwhasoo-jp.myshopify.com/pages/order-list | R7: N/A | S7: Order List | Sulwhasoo Japan | T7: Sulwhasoo Japan | U7: website | V7: Sulwhasoo Japan | X7: https://sulwhasoo-jp.myshopify.com/pages/order-list | Y7: summary_large_image | Z7: Order List | Sulwhasoo Japan | AC7: N/A | AD7: Organization | AI7: N/A
A8: https://sulwhasoo-jp.myshopify.com/pages/mypage | C8: N/A | D8: Indexable | E8: O | F8: 200 | G8: Fail | H8: mypage | Sulwhasoo Japan | I8: N/A | L8: N/A | N8: マイページ | P8: N/A | Q8: https://sulwhasoo-jp.myshopify.com/pages/mypage | R8: N/A | S8: mypage | Sulwhasoo Japan | T8: Sulwhasoo Japan | U8: website | V8: Sulwhasoo Japan | X8: https://sulwhasoo-jp.myshopify.com/pages/mypage | Y8: summary_large_image | Z8: mypage | Sulwhasoo Japan | AC8: N/A | AD8: Organization | AI8: N/A
A9: https://sulwhasoo-jp.myshopify.com/pages/my-address | C9: N/A | D9: Indexable | E9: O | F9: 200 | G9: Fail | H9: my-address | Sulwhasoo Japan | I9: N/A | L9: N/A | N9: My Page | P9: N/A | Q9: https://sulwhasoo-jp.myshopify.com/pages/my-address | R9: N/A | S9: my-address | Sulwhasoo Japan | T9: Sulwhasoo Japan | U9: website | V9: Sulwhasoo Japan | X9: https://sulwhasoo-jp.myshopify.com/pages/my-address | Y9: summary_large_image | Z9: my-address | Sulwhasoo Japan | AC9: N/A | AD9: Organization | AI9: N/A
A10: https://sulwhasoo-jp.myshopify.com/pages/membership | C10: Pass | D10: Indexable | E10: O | F10: 200 | G10: Pass | H10: Membership | Sulwhasoo Japan | I10: Pass | L10: Fail | M10: Bergabung dengan keanggotaan Sulwhasoo dan dapatkan beragam keistimewaan. | N10: メンバーシップ | P10: Pass | Q10: https://sulwhasoo-jp.myshopify.com/pages/membership | R10: Pass | S10: Membership | Sulwhasoo Japan | T10: Meta Description to-be 내용 넣기 | U10: website | V10: Sulwhasoo Japan | W10: 설화수 로고 및 대표 이미지 넣기 - KR참고 | X10: https://sulwhasoo-jp.myshopify.com/pages/membership | Y10: summary_large_image | Z10: Membership | Sulwhasoo Japan | AB10: url 채우기 | AC10: Fail | AD10: Organization | AI10: Fail
A11: https://sulwhasoo-jp.myshopify.com/pages/legal-notice | C11: Pass | D11: Indexable | E11: 확인 불가 | F11: 200 | G11: Pass | H11: 特定商取引法に基づく表記 | Sulwhasoo Japan | I11: Pass | K11: 事業者名 アモーレパシフィックジャパン株式会社 所在地 〒150-0012 東京都渋谷区広尾１－１３－７ 恵比寿イーストビル2階 代表者 代表 松井 理奈 お問い合わせ Sulwhasoo カスタマーサポート TEL：0120-929-744 受付時間： 月~金 10:00 ~ 18:00＜祝祭日、年末年始・夏期休暇を除く＞ フォームでのお問い合わせはこちら URL https://jp.sulwhasoo.com/ 販売価格 各商品詳細ページに表示された価格に基づきます。表示価格は本体価格に消費税額を加えた「お支払い総額（税込価格）」となっております。 商品代金以外の必要料金 ■送料：通常配送料金は、550円（税込）※沖縄、北海 | L11: Pass | P11: Pass | Q11: https://sulwhasoo-jp.myshopify.com/pages/legal-notice | R11: Pass | S11: 特定商取引法に基づく表記 | Sulwhasoo Japan | T11: 事業者名 アモーレパシフィックジャパン株式会社 所在地 〒150-0012 東京都渋谷区広尾１－１３－７ 恵比寿イーストビル2階 代表者 代表 松井 理奈 お問い合わせ Sulwhasoo カスタマーサポート TEL：0120-929-744 受付時間： 月~金 10:00 ~ 18:00＜祝祭日、年末年始・夏期休暇を除く＞ フォームでのお問い合わせはこちら URL https://jp.sulwhasoo.com/ 販売価格 各商品詳細ページに表示された価格に基づきます。表示価格は本体価格に消費税額を加えた「お支払い総額（税込価格）」となっております。 商品代金以外の必要料金 ■送料：通常配送料金は、550円（税込）※沖縄、北海 | U11: website | V11: Sulwhasoo Japan | W11: 설화수 로고 및 대표 이미지 넣기 - KR참고 | X11: https://sulwhasoo-jp.myshopify.com/pages/legal-notice | Y11: summary_large_image | Z11: 特定商取引法に基づく表記 | Sulwhasoo Japan | AB11: url 채우기 | AC11: Fail | AD11: Organization | AI11: Fail
A12: https://sulwhasoo-jp.myshopify.com/pages/faq | C12: Pass | D12: Indexable | E12: O | F12: 200 | G12: Pass | H12: FAQ | Sulwhasoo Japan | I12: Pass | L12: Fail | M12: Sulwhasoo FAQ. Find quick answers to your questions about order status, payment methods, shipping tracking, and product inquiries in one place. | N12: よくあるご質問 | P12: Pass | Q12: https://sulwhasoo-jp.myshopify.com/pages/faq | R12: Pass | S12: FAQ | Sulwhasoo Japan | T12: Meta Description to-be 내용 넣기 | U12: website | V12: Sulwhasoo Japan | W12: 설화수 로고 및 대표 이미지 넣기 - KR참고 | X12: https://sulwhasoo-jp.myshopify.com/pages/faq | Y12: summary_large_image | Z12: FAQ | Sulwhasoo Japan | AB12: url 채우기 | AC12: Fail | AD12: Organization | AI12: Fail
A13: https://sulwhasoo-jp.myshopify.com/pages/exchange-return | C13: Pass | D13: Indexable | E13: O | F13: 200 | G13: Pass | H13: Exchange Return | Sulwhasoo Japan | I13: Pass | L13: Fail | M13: Sulwhasoo Exchange & Return. Guide for returning damaged or incorrect items. Contact our support team to request an exchange or refund under our policy. | N13: 交換・返品について | P13: Pass | Q13: https://sulwhasoo-jp.myshopify.com/pages/exchange-return | R13: Pass | S13: Exchange Return | Sulwhasoo Japan | T13: Meta Description to-be 내용 넣기 | U13: website | V13: Sulwhasoo Japan | W13: 설화수 로고 및 대표 이미지 넣기 - KR참고 | X13: https://sulwhasoo-jp.myshopify.com/pages/exchange-return | Y13: summary_large_image | Z13: Exchange Return | Sulwhasoo Japan | AB13: url 채우기 | AC13: Fail | AD13: Organization | AI13: Fail
A14: https://sulwhasoo-jp.myshopify.com/pages/edit-account | C14: N/A | D14: Indexable | E14: O | F14: 200 | G14: Fail | H14: Edit Account | Sulwhasoo Japan | I14: N/A | L14: N/A | N14: 個人情報の修正 | P14: N/A | Q14: https://sulwhasoo-jp.myshopify.com/pages/edit-account | R14: N/A | S14: Edit Account | Sulwhasoo Japan | T14: Sulwhasoo Japan | U14: website | V14: Sulwhasoo Japan | X14: https://sulwhasoo-jp.myshopify.com/pages/edit-account | Y14: summary_large_image | Z14: Edit Account | Sulwhasoo Japan | AC14: N/A | AD14: Organization | AI14: N/A
A15: https://sulwhasoo-jp.myshopify.com/pages/contact | C15: Pass | D15: Indexable | E15: O | F15: 200 | G15: Pass | H15: Contact | Sulwhasoo Japan | I15: Pass | L15: Fail | M15: Contact Sulwhasoo for inquiries on products, orders, or shipping. Please fill out the form below for assistance. | N15: お問い合わせ | P15: Pass | Q15: https://sulwhasoo-jp.myshopify.com/pages/contact | R15: Pass | S15: Contact | Sulwhasoo Japan | T15: Meta Description to-be 내용 넣기 | U15: website | V15: Sulwhasoo Japan | W15: 설화수 로고 및 대표 이미지 넣기 - KR참고 | X15: https://sulwhasoo-jp.myshopify.com/pages/contact | Y15: summary_large_image | Z15: Contact | Sulwhasoo Japan | AB15: url 채우기 | AC15: Fail | AD15: Organization | AI15: Fail
A16: https://sulwhasoo-jp.myshopify.com/pages/brand-sustainability | C16: Pass | D16: Indexable | E16: O | F16: 200 | G16: Pass | H16: Brand Sustainability – Earth & Culture | Sulwhasoo Japan | I16: Pass | K16: Sulwhasoo’s sustainable beauty is built on Ginseng Science, Environmental Care, and Cultural Heritage to shape a better future. | L16: Pass | N16: Brand Sustainability | Sulwhasoo Japan | O16: 持続可能な未来のための約束 | P16: Fail | Q16: https://sulwhasoo-jp.myshopify.com/pages/brand-sustainability | R16: Pass | S16: Brand Sustainability – Earth & Culture | Sulwhasoo Japan | T16: Sulwhasoo’s sustainable beauty is built on Ginseng Science, Environmental Care, and Cultural Heritage to shape a better future. | U16: website | V16: Sulwhasoo Japan | W16: 설화수 로고 및 대표 이미지 넣기 - KR참고 | X16: https://sulwhasoo-jp.myshopify.com/pages/brand-sustainability | Y16: summary_large_image | Z16: Brand Sustainability – Earth & Culture | Sulwhasoo Japan | AB16: url 채우기 | AC16: Fail | AD16: Organization | AI16: Fail
A17: https://sulwhasoo-jp.myshopify.com/pages/brand-story | C17: Pass | D17: Indexable | E17: O | F17: 200 | G17: Pass | H17: Brand Story | Sulwhasoo Japan | I17: Pass | K17: Sulwhasoo fuses Korean tradition with cutting-edge science, using JAUM Activator® and ginseng research for youthful, radiant skin | L17: Pass | N17: Brand Story | Sulwhasoo Japan | O17: 時の流れにゆるがない美しさへの旅 | P17: Fail | Q17: https://sulwhasoo-jp.myshopify.com/pages/brand-story | R17: Pass | S17: Brand Story | Sulwhasoo Japan | T17: Sulwhasoo fuses Korean tradition with cutting-edge science, using JAUM Activator® and ginseng research for youthful, radiant skin | U17: website | V17: Sulwhasoo Japan | W17: 설화수 로고 및 대표 이미지 넣기 - KR참고 | X17: https://sulwhasoo-jp.myshopify.com/pages/brand-story | Y17: summary_large_image | Z17: Brand Story | Sulwhasoo Japan | AB17: url 채우기 | AC17: Fail | AD17: Organization | AI17: Fail
A18: https://sulwhasoo-jp.myshopify.com/pages/activate-account-form | C18: N/A | D18: Indexable | E18: 확인 불가 | F18: 200 | G18: Fail | H18: Activate Account Form | Sulwhasoo Japan | I18: N/A | L18: N/A | P18: N/A | Q18: https://sulwhasoo-jp.myshopify.com/pages/activate-account-form | R18: N/A | S18: Activate Account Form | Sulwhasoo Japan | T18: Sulwhasoo Japan | U18: website | V18: Sulwhasoo Japan | X18: https://sulwhasoo-jp.myshopify.com/pages/activate-account-form | Y18: summary_large_image | Z18: Activate Account Form | Sulwhasoo Japan | AC18: N/A | AD18: Organization | AI18: N/A
A19: https://sulwhasoo-jp.myshopify.com/blogs/sulwhasoo-post/journey-to-holistic-beauty-時の流れに揺るがない美しさへの旅 | C19: Pass | D19: Indexable | E19: O | F19: 200 | G19: Pass | H19: 「Journey to Holistic Beauty」時の流れに揺るがない美しさへの旅 | Sulwhasoo Japan | I19: Pass | K19: 時を超えて愛される韓国発ラグジュアリービューティーブランド、Sulwhasoo（雪花秀／ソルファス）。その世界観と高麗人参サイエンスを体験できる「Sulwhasoo Lounge（ソルファスラウンジ）」が、5月6日（水）より@cosme TOKYOにて1週間限定オープン。 アモーレパシフィックジャパン株式会社（所在地：東京都渋谷区 代表：羅政均）が展開する、韓国発ラグジュアリービューティーブランド『Sulwhasoo（雪花秀/ソルファス）』は、5月6日（水）から12日（火）までの1週間、@cosme TOKYO ポップアップストア1階にて「Sulwhasoo Lounge（ソルファスラウンジ）」を開催します。 長年にわたり韓国ビュー | L19: Pass | P19: Pass | Q19: https://sulwhasoo-jp.myshopify.com/blogs/sulwhasoo-post/journey-to-holistic-beauty-時の流れに揺るがない美しさへの旅 | R19: Pass | S19: 「Journey to Holistic Beauty」時の流れに揺るがない美しさへの旅 | Sulwhasoo Japan | T19: 時を超えて愛される韓国発ラグジュアリービューティーブランド、Sulwhasoo（雪花秀／ソルファス）。その世界観と高麗人参サイエンスを体験できる「Sulwhasoo Lounge（ソルファスラウンジ）」が、5月6日（水）より@cosme TOKYOにて1週間限定オープン。 アモーレパシフィックジャパン株式会社（所在地：東京都渋谷区 代表：羅政均）が展開する、韓国発ラグジュアリービューティーブランド『Sulwhasoo（雪花秀/ソルファス）』は、5月6日（水）から12日（火）までの1週間、@cosme TOKYO ポップアップストア1階にて「Sulwhasoo Lounge（ソルファスラウンジ）」を開催します。 長年にわたり韓国ビュー | U19: article | V19: Sulwhasoo Japan | W19: http://sulwhasoo-jp.myshopify.com/cdn/shop/articles/Sulwhasoo_JP.webp?v=1776042225 | X19: https://sulwhasoo-jp.myshopify.com/blogs/sulwhasoo-post/journey-to-holistic-beauty-%e6%99%82%e3%81%ae%e6%b5%81%e3%82%8c%e3%81%ab%e6%8f%ba%e3%82%8b%e3%81%8c%e3%81%aa%e3%81%84%e7%be%8e%e3%81%97%e3%81%95%e3%81%b8%e3%81%ae%e6%97%85 | Y19: summary_large_image | Z19: 「Journey to Holistic Beauty」時の流れに揺るがない美しさへの旅 | Sulwhasoo Japan | AB19: url 채우기 | AC19: Fail | AD19: Organization | AE19: Article | AF19: WebPage | AG19: Person | AH19: Organization | AI19: Fail
A20: https://sulwhasoo-jp.myshopify.com/blogs/sulwhasoo-post/concentrated-ginseng-rejuvenating-cream | C20: Pass | D20: Indexable | E20: O | F20: 200 | G20: Pass | H20: Concentrated Ginseng Rejuvenating Cream | Sulwhasoo Japan | I20: Pass | K20: Discover 60 years of Ginseng science with Sulwhasoo’s Concentrated Ginseng Rejuvenating Cream, boosting elasticity for a youthful glow. | L20: Pass | N20: Concentrated Ginseng Rejuvenating Cream | P20: Pass | Q20: https://sulwhasoo-jp.myshopify.com/blogs/sulwhasoo-post/concentrated-ginseng-rejuvenating-cream | R20: Pass | S20: Concentrated Ginseng Rejuvenating Cream | Sulwhasoo Japan | T20: Discover 60 years of Ginseng science with Sulwhasoo’s Concentrated Ginseng Rejuvenating Cream, boosting elasticity for a youthful glow. | U20: article | V20: Sulwhasoo Japan | W20: http://sulwhasoo-jp.myshopify.com/cdn/shop/articles/240816_final_SG_concentrated-ginseng-rejuvenating-cream-cover_500x500_360x_83aa104d-76f3-4112-8d3b-ba15e6385f17.webp?v=1776072597 | X20: https://sulwhasoo-jp.myshopify.com/blogs/sulwhasoo-post/concentrated-ginseng-rejuvenating-cream | Y20: summary_large_image | Z20: Concentrated Ginseng Rejuvenating Cream | Sulwhasoo Japan | AB20: url 채우기 | AC20: Fail | AD20: Organization | AE20: Article | AF20: WebPage | AG20: Person | AH20: Organization | AI20: Fail
A21: https://sulwhasoo-jp.myshopify.com/blogs/sulwhasoo-post/2025-first-care-activating-serum-introduction | C21: Pass | D21: Indexable | E21: O | F21: 200 | G21: Pass | H21: FIRST CARE ACTIVATING SERUM – Sulwhasoo Japan | I21: Fail | J21: FIRST CARE ACTIVATING SERUM | Sulwhasoo Japan | K21: REVITALIZE YOUR SKIN FOR A HEALTHY, YOUTHFUL COMPLEXION | L21: Pass | N21: 2025 FIRST CARE ACTIVATING SERUM | O21: 潤燥ユンジョ ファーストケア アクティブセラム VI | P21: Fail | Q21: https://sulwhasoo-jp.myshopify.com/blogs/sulwhasoo-post/2025-first-care-activating-serum-introduction | R21: Pass | S21: FIRST CARE ACTIVATING SERUM – Sulwhasoo Japan | T21: REVITALIZE YOUR SKIN FOR A HEALTHY, YOUTHFUL COMPLEXION | U21: article | V21: Sulwhasoo Japan | W21: http://sulwhasoo-jp.myshopify.com/cdn/shop/articles/251120_final_TH_brand-news_thumbnail_720x_9f9a8857-59ec-48da-9861-5472e1a130e3.webp?v=1776043398 | X21: https://sulwhasoo-jp.myshopify.com/blogs/sulwhasoo-post/2025-first-care-activating-serum-introduction | Y21: summary_large_image | Z21: FIRST CARE ACTIVATING SERUM – Sulwhasoo Japan | AB21: url 채우기 | AC21: Fail | AD21: Organization | AE21: Article | AF21: WebPage | AG21: Person | AH21: Organization | AI21: Fail
A22: https://sulwhasoo-jp.myshopify.com/blogs/sulwhasoo-post | C22: Pass | D22: Indexable | E22: O | F22: 200 | G22: Pass | H22: Brand News | Heritage-Inspired Luxury | Sulwhasoo Japan | I22: Pass | K22: Sulwhasoo, an iconic luxury beauty brand, dates back to 1932. Known for its pioneering spirit, it was the first to create products infused with ginseng. | L22: Pass | N22: BRAND NEWS | P22: Pass | Q22: https://sulwhasoo-jp.myshopify.com/blogs/sulwhasoo-post | R22: Pass | S22: Brand News | Heritage-Inspired Luxury | Sulwhasoo Japan | T22: Sulwhasoo, an iconic luxury beauty brand, dates back to 1932. Known for its pioneering spirit, it was the first to create products infused with ginseng. | U22: website | V22: Sulwhasoo Japan | W22: 설화수 로고 및 대표 이미지 넣기 - KR참고 | X22: https://sulwhasoo-jp.myshopify.com/blogs/sulwhasoo-post | Y22: summary_large_image | Z22: Brand News | Heritage-Inspired Luxury | Sulwhasoo Japan | AB22: url 채우기 | AC22: Fail | AD22: Organization | AI22: Fail
A23: https://sulwhasoo-jp.myshopify.com/blogs/notice | C23: Pass | D23: Indexable | E23: O | F23: 200 | G23: Pass | H23: Notice | Sulwhasoo Japan | I23: Pass | L23: Fail | M23: Sulwhasoo Notice. Stay updated with the latest news, service announcements, and shipping schedules from our official store. | N23: お知らせ | P23: Pass | Q23: https://sulwhasoo-jp.myshopify.com/blogs/notice | R23: Pass | S23: Notice | Sulwhasoo Japan | T23: Meta Description to-be 내용 넣기 | U23: website | V23: Sulwhasoo Japan | W23: 설화수 로고 및 대표 이미지 넣기 - KR참고 | X23: https://sulwhasoo-jp.myshopify.com/blogs/notice | Y23: summary_large_image | Z23: Notice | Sulwhasoo Japan | AB23: url 채우기 | AC23: Fail | AD23: Organization | AI23: Fail
A24: https://sulwhasoo-jp.myshopify.com/blogs/event/公式ストアオープン記念-レビューキャンペーン | C24: Pass | D24: Indexable | E24: O | F24: 200 | G24: Pass | H24: 公式ストアオープン記念 レビューキャンペーン | Sulwhasoo Japan | I24: Pass | K24: 公式ストアオープン記念レビューキャンペーン。 キャンペーン期間は2026年4月28日から6月30日までです。 対象商品レビュー投稿者の中から抽選で5名様にスペシャルギフトをプレゼントします。 | L24: Pass | P24: Pass | Q24: https://sulwhasoo-jp.myshopify.com/blogs/event/公式ストアオープン記念-レビューキャンペーン | R24: Pass | S24: 公式ストアオープン記念 レビューキャンペーン | Sulwhasoo Japan | T24: 公式ストアオープン記念レビューキャンペーン。 キャンペーン期間は2026年4月28日から6月30日までです。 対象商品レビュー投稿者の中から抽選で5名様にスペシャルギフトをプレゼントします。 | U24: article | V24: Sulwhasoo Japan | X24: https://sulwhasoo-jp.myshopify.com/blogs/event/%e5%85%ac%e5%bc%8f%e3%82%b9%e3%83%88%e3%82%a2%e3%82%aa%e3%83%bc%e3%83%97%e3%83%b3%e8%a8%98%e5%bf%b5-%e3%83%ac%e3%83%93%e3%83%a5%e3%83%bc%e3%82%ad%e3%83%a3%e3%83%b3%e3%83%9a%e3%83%bc%e3%83%b3 | Y24: summary_large_image | Z24: 公式ストアオープン記念 レビューキャンペーン | Sulwhasoo Japan | AB24: url 채우기 | AC24: Fail | AD24: Organization | AE24: Article | AF24: WebPage | AG24: Person | AH24: Organization | AI24: Fail
A25: https://sulwhasoo-jp.myshopify.com/blogs/event/cosme-store-tokyoにてpopupstore開催 | C25: Pass | D25: Indexable | E25: O | F25: 200 | G25: Pass | H25: @cosme store TOKYOにてPOPUPSTORE開催 | Sulwhasoo Japan | I25: Pass | K25: 韓国発ラグジュアリースキンケアブランド「Sulwhasoo（ソルファス）」は、2026年5月6日から5月12日までの期間、＠cosme storeにてPOPUPSTOREを開催いたします【POPUP STORE開催概要】 期間：2026年5月6日～2026年5月12日 開催時間：11:00～21:00 場所：@cosme TOKYO 住所：東京都渋谷区神宮前1-14-27 | L25: Pass | N25: @cosme store TOKYOにてPOPUPSTORE開催 | P25: Pass | Q25: https://sulwhasoo-jp.myshopify.com/blogs/event/cosme-store-tokyoにてpopupstore開催 | R25: Pass | S25: @cosme store TOKYOにてPOPUPSTORE開催 | Sulwhasoo Japan | T25: 韓国発ラグジュアリースキンケアブランド「Sulwhasoo（ソルファス）」は、2026年5月6日から5月12日までの期間、＠cosme storeにてPOPUPSTOREを開催いたします【POPUP STORE開催概要】 期間：2026年5月6日～2026年5月12日 開催時間：11:00～21:00 場所：@cosme TOKYO 住所：東京都渋谷区神宮前1-14-27 | U25: article | V25: Sulwhasoo Japan | W25: http://sulwhasoo-jp.myshopify.com/cdn/shop/articles/111170002325_01_d50df340-e78c-4d41-ae4f-ea577d47fb7b.jpg?v=1776047739 | X25: https://sulwhasoo-jp.myshopify.com/blogs/event/cosme-store-tokyo%e3%81%ab%e3%81%a6popupstore%e9%96%8b%e5%82%ac | Y25: summary_large_image | Z25: @cosme store TOKYOにてPOPUPSTORE開催 | Sulwhasoo Japan | AB25: url 채우기 | AC25: Fail | AD25: Organization | AE25: Article | AF25: WebPage | AG25: Person | AH25: Organization | AI25: Fail
A26: https://sulwhasoo-jp.myshopify.com/blogs/event | C26: Pass | D26: Indexable | E26: O | F26: 200 | G26: Pass | H26: Event | Sulwhasoo Japan | I26: Pass | L26: Fail | M26: Sulwhasoo Events. Discover exclusive promotions, gift-with-purchase offers, and seasonal specials for our members. Check out our current events now. | N26: イベント | P26: Pass | Q26: https://sulwhasoo-jp.myshopify.com/blogs/event | R26: Pass | S26: Event | Sulwhasoo Japan | T26: Meta Description to-be 내용 넣기 | U26: website | V26: Sulwhasoo Japan | W26: 설화수 로고 및 대표 이미지 넣기 - KR참고 | X26: https://sulwhasoo-jp.myshopify.com/blogs/event | Y26: summary_large_image | Z26: Event | Sulwhasoo Japan | AB26: url 채우기 | AC26: Fail | AD26: Organization | AI26: Fail
A27: https://sulwhasoo-jp.myshopify.com/ | C27: Pass | D27: Indexable | E27: O | F27: 200 | G27: Pass | H27: Sulwhasoo Japan | I27: Pass | L27: Fail | M27: Sulwhasoo Japan Official Website. Experience our luxury skincare line featuring First Care Activating Serum. Shop now for radiant beauty. | N27: Sulwhasoo Japan | P27: Pass | Q27: https://sulwhasoo-jp.myshopify.com/ | R27: Pass | S27: Sulwhasoo Japan | T27: Meta Description to-be 내용 넣기 | U27: website | V27: Sulwhasoo Japan | W27: 설화수 로고 및 대표 이미지 넣기 - KR참고 | X27: https://sulwhasoo-jp.myshopify.com/ | Y27: summary_large_image | Z27: Sulwhasoo Japan | AB27: url 채우기 | AC27: Fail | AD27: Organization | AE27: WebSite | AF27: SearchAction | AI27: Pass

Sheet data
A1: Address | B1: Content Type | C1: Status Code | D1: Status | E1: Indexability | F1: Indexability Status | G1: Title 1 | H1: Title 1 Length | I1: Title 1 Pixel Width | J1: Meta Description 1 | K1: Meta Description 1 Length | L1: Meta Description 1 Pixel Width | M1: Meta Keywords 1 | N1: Meta Keywords 1 Length | O1: H1-1 | P1: H1-1 Length | Q1: H1-2 | R1: H1-2 Length | S1: H2-1 | T1: H2-1 Length | U1: H2-2 | V1: H2-2 Length | W1: Meta Robots 1 | X1: X-Robots-Tag 1 | Y1: Meta Refresh 1 | Z1: Canonical Link Element 1 | AA1: rel="next" 1 | AB1: rel="prev" 1 | AC1: HTTP rel="next" 1 | AD1: HTTP rel="prev" 1 | AE1: amphtml Link Element | AF1: Size (bytes) | AG1: Transferred (bytes) | AH1: Word Count | AI1: Sentence Count | AJ1: Average Words Per Sentence | AK1: Flesch Reading Ease Score | AL1: Readability | AM1: Text Ratio | AN1: Crawl Depth | AO1: Folder Depth | AP1: Link Score | AQ1: Inlinks | AR1: Unique Inlinks | AS1: Unique JS Inlinks | AT1: % of Total | AU1: Outlinks | AV1: Unique Outlinks | AW1: Unique JS Outlinks | AX1: External Outlinks | AY1: Unique External Outlinks | AZ1: Unique External JS Outlinks | BA1: Closest Similarity Match | BB1: No. Near Duplicates | BC1: Spelling Errors | BD1: Grammar Errors | BE1: Hash | BF1: Response Time | BG1: Last Modified | BH1: Redirect URL | BI1: Redirect Type | BJ1: Cookies | BK1: HTTP Version | BL1: OG Title 1 | BM1: OG Description 1 | BN1: OG Type 1 | BO1: OG Site Name 1 | BP1: OG image 1 | BQ1: OG url 1 | BR1: Twitter Card 1 | BS1: Twitter Title 1 | BT1: Twitter Site 1 | BU1: Twitter URL 1 | BV1: type 1 | BW1: alternate 1 | BX1: URL Encoded Address | BY1: Crawl Timestamp | BZ1: type 2 | CA1: type 3 | CB1: type 4 | CC1: type 5
A2: https://sulwhasoo-jp.myshopify.com/ | B2: text/html; charset=utf-8 | C2: 200 | D2: OK | E2: Indexable | G2: Sulwhasoo Japan | H2: 15 | I2: 157 | K2: 0 | L2: 0 | N2: 0 | O2: Sulwhasoo Japan | P2: 15 | R2: 0 | S2: カート0 | T2: 4 | U2: おすすめのキーワード | V2: 10 | Z2: https://sulwhasoo-jp.myshopify.com/ | AF2: 697593 | AG2: 124600 | AH2: 333 | AI2: 195 | AJ2: 1.708 | AK2: 100 | AL2: Very Easy | AM2: 0.497 | AN2: 0 | AO2: 0 | AQ2: 94 | AR2: 30 | AS2: 0 | AT2: 93.75 | AU2: 148 | AV2: 60 | AW2: 0 | BE2: fc66ae26996816501e3132b0408658e0 | BF2: 0.207 | BK2: 1.1 | BL2: Sulwhasoo Japan | BM2: Sulwhasoo Japan | BN2: website | BO2: Sulwhasoo Japan | BQ2: https://sulwhasoo-jp.myshopify.com/ | BR2: summary_large_image | BS2: Sulwhasoo Japan | BV2: Organization | BX2: https://sulwhasoo-jp.myshopify.com/ | BY2: 46128.603 | BZ2: WebSite | CA2: SearchAction
A3: https://sulwhasoo-jp.myshopify.com/pages/contact | B3: text/html; charset=utf-8 | C3: 200 | D3: OK | E3: Indexable | G3: Contact | Sulwhasoo Japan | H3: 26 | I3: 242 | K3: 0 | L3: 0 | N3: 0 | O3: お問い合わせ | P3: 6 | R3: 0 | S3: カート0 | T3: 4 | U3: おすすめのキーワード | V3: 10 | Z3: https://sulwhasoo-jp.myshopify.com/pages/contact | AF3: 532180 | AG3: 115111 | AH3: 149 | AI3: 79 | AJ3: 1.886 | AK3: 100 | AL3: Very Easy | AM3: 0.436 | AN3: 0 | AO3: 1 | AQ3: 52 | AR3: 30 | AS3: 0 | AT3: 93.75 | AU3: 118 | AV3: 51 | AW3: 0 | BE3: 31fe67b129cc962dea2844bc8e615e86 | BF3: 0.52 | BK3: 1.1 | BL3: Contact | Sulwhasoo Japan | BM3: Sulwhasoo Japan | BN3: website | BO3: Sulwhasoo Japan | BQ3: https://sulwhasoo-jp.myshopify.com/pages/contact | BR3: summary_large_image | BS3: Contact | Sulwhasoo Japan | BV3: Organization | BX3: https://sulwhasoo-jp.myshopify.com/pages/contact | BY3: 46128.603
A4: https://sulwhasoo-jp.myshopify.com/pages/site-map | B4: text/html; charset=utf-8 | C4: 200 | D4: OK | E4: Indexable | G4: Site Map | Sulwhasoo Japan | H4: 27 | I4: 251 | K4: 0 | L4: 0 | N4: 0 | O4: Site Map | P4: 8 | R4: 0 | S4: カート0 | T4: 4 | U4: おすすめのキーワード | V4: 10 | Z4: https://sulwhasoo-jp.myshopify.com/pages/site-map | AF4: 530986 | AG4: 113301 | AH4: 263 | AI4: 129 | AJ4: 2.039 | AK4: 100 | AL4: Very Easy | AM4: 0.468 | AN4: 0 | AO4: 1 | AQ4: 37 | AR4: 30 | AS4: 0 | AT4: 93.75 | AU4: 154 | AV4: 52 | AW4: 0 | BE4: ddb9f201e6491401344e72e84eea542e | BF4: 0.355 | BK4: 1.1 | BL4: Site Map | Sulwhasoo Japan | BM4: Sulwhasoo Japan | BN4: website | BO4: Sulwhasoo Japan | BQ4: https://sulwhasoo-jp.myshopify.com/pages/site-map | BR4: summary_large_image | BS4: Site Map | Sulwhasoo Japan | BV4: Organization | BX4: https://sulwhasoo-jp.myshopify.com/pages/site-map | BY4: 46128.603
A5: https://sulwhasoo-jp.myshopify.com/pages/order-list | B5: text/html; charset=utf-8 | C5: 200 | D5: OK | E5: Indexable | G5: Order List | Sulwhasoo Japan | H5: 29 | I5: 260 | K5: 0 | L5: 0 | N5: 0 | O5: ご注文管理 | P5: 5 | R5: 0 | S5: カート0 | T5: 4 | U5: おすすめのキーワード | V5: 10 | Z5: https://sulwhasoo-jp.myshopify.com/pages/order-list | AF5: 519000 | AG5: 111802 | AH5: 148 | AI5: 72 | AJ5: 2.056 | AK5: 100 | AL5: Very Easy | AM5: 0.414 | AN5: 0 | AO5: 1 | AQ5: 15 | AR5: 4 | AS5: 0 | AT5: 12.5 | AU5: 116 | AV5: 57 | AW5: 0 | BE5: d1929f20a52521d5e5d23860752a0c2b | BF5: 0.366 | BK5: 1.1 | BL5: Order List | Sulwhasoo Japan | BM5: Sulwhasoo Japan | BN5: website | BO5: Sulwhasoo Japan | BQ5: https://sulwhasoo-jp.myshopify.com/pages/order-list | BR5: summary_large_image | BS5: Order List | Sulwhasoo Japan | BV5: Organization | BX5: https://sulwhasoo-jp.myshopify.com/pages/order-list | BY5: 46128.603
A6: https://sulwhasoo-jp.myshopify.com/pages/point-list | B6: text/html; charset=utf-8 | C6: 200 | D6: OK | E6: Indexable | G6: Point List | Sulwhasoo Japan | H6: 29 | I6: 257 | K6: 0 | L6: 0 | N6: 0 | O6: ポイント情報 | P6: 6 | R6: 0 | S6: カート0 | T6: 4 | U6: おすすめのキーワード | V6: 10 | Z6: https://sulwhasoo-jp.myshopify.com/pages/point-list | AF6: 519540 | AG6: 112778 | AH6: 138 | AI6: 68 | AJ6: 2.029 | AK6: 100 | AL6: Very Easy | AM6: 0.393 | AN6: 0 | AO6: 1 | AQ6: 16 | AR6: 4 | AS6: 0 | AT6: 12.5 | AU6: 116 | AV6: 57 | AW6: 0 | BE6: 1dfc1b48630cd8026fe7f2aca10f4aa8 | BF6: 0.366 | BK6: 1.1 | BL6: Point List | Sulwhasoo Japan | BM6: Sulwhasoo Japan | BN6: website | BO6: Sulwhasoo Japan | BQ6: https://sulwhasoo-jp.myshopify.com/pages/point-list | BR6: summary_large_image | BS6: Point List | Sulwhasoo Japan | BV6: Organization | BX6: https://sulwhasoo-jp.myshopify.com/pages/point-list | BY6: 46128.603
A7: https://sulwhasoo-jp.myshopify.com/pages/faq | B7: text/html; charset=utf-8 | C7: 200 | D7: OK | E7: Indexable | G7: FAQ | Sulwhasoo Japan | H7: 22 | I7: 210 | K7: 0 | L7: 0 | N7: 0 | O7: よくあるご質問 | P7: 7 | R7: 0 | S7: カート0 | T7: 4 | U7: おすすめのキーワード | V7: 10 | Z7: https://sulwhasoo-jp.myshopify.com/pages/faq | AF7: 567771 | AG7: 115641 | AH7: 223 | AI7: 153 | AJ7: 1.458 | AK7: 100 | AL7: Very Easy | AM7: 0.75 | AN7: 0 | AO7: 1 | AQ7: 52 | AR7: 30 | AS7: 0 | AT7: 93.75 | AU7: 118 | AV7: 51 | AW7: 0 | BE7: 26143999126c2e43eaf649f024566bec | BF7: 0.34 | BK7: 1.1 | BL7: FAQ | Sulwhasoo Japan | BM7: Sulwhasoo Japan | BN7: website | BO7: Sulwhasoo Japan | BQ7: https://sulwhasoo-jp.myshopify.com/pages/faq | BR7: summary_large_image | BS7: FAQ | Sulwhasoo Japan | BV7: Organization | BX7: https://sulwhasoo-jp.myshopify.com/pages/faq | BY7: 46128.603
A8: https://sulwhasoo-jp.myshopify.com/pages/exchange-return | B8: text/html; charset=utf-8 | C8: 200 | D8: OK | E8: Indexable | G8: Exchange Return | Sulwhasoo Japan | H8: 34 | I8: 322 | K8: 0 | L8: 0 | N8: 0 | O8: 交換・返品について | P8: 9 | R8: 0 | S8: カート0 | T8: 4 | U8: おすすめのキーワード | V8: 10 | Z8: https://sulwhasoo-jp.myshopify.com/pages/exchange-return | AF8: 527405 | AG8: 114240 | AH8: 180 | AI8: 93 | AJ8: 1.935 | AK8: 100 | AL8: Very Easy | AM8: 0.611 | AN8: 0 | AO8: 1 | AQ8: 52 | AR8: 30 | AS8: 0 | AT8: 93.75 | AU8: 119 | AV8: 51 | AW8: 0 | BE8: ecdca370c527ebd2c44cc47fc05447a5 | BF8: 0.753 | BK8: 1.1 | BL8: Exchange Return | Sulwhasoo Japan | BM8: Sulwhasoo Japan | BN8: website | BO8: Sulwhasoo Japan | BQ8: https://sulwhasoo-jp.myshopify.com/pages/exchange-return | BR8: summary_large_image | BS8: Exchange Return | Sulwhasoo Japan | BV8: Organization | BX8: https://sulwhasoo-jp.myshopify.com/pages/exchange-return | BY8: 46128.603
A9: https://sulwhasoo-jp.myshopify.com/pages/membership | B9: text/html; charset=utf-8 | C9: 200 | D9: OK | E9: Indexable | G9: Membership | Sulwhasoo Japan | H9: 29 | I9: 284 | K9: 0 | L9: 0 | N9: 0 | O9: メンバーシップ | P9: 7 | R9: 0 | S9: カート0 | T9: 4 | U9: おすすめのキーワード | V9: 10 | Z9: https://sulwhasoo-jp.myshopify.com/pages/membership | AF9: 529474 | AG9: 114847 | AH9: 211 | AI9: 103 | AJ9: 2.049 | AK9: 100 | AL9: Very Easy | AM9: 0.636 | AN9: 0 | AO9: 1 | AQ9: 155 | AR9: 30 | AS9: 0 | AT9: 93.75 | AU9: 119 | AV9: 51 | AW9: 0 | BE9: 2902fd37c8f205946caf414c4c97685d | BF9: 0.46 | BK9: 1.1 | BL9: Membership | Sulwhasoo Japan | BM9: Sulwhasoo Japan | BN9: website | BO9: Sulwhasoo Japan | BQ9: https://sulwhasoo-jp.myshopify.com/pages/membership | BR9: summary_large_image | BS9: Membership | Sulwhasoo Japan | BV9: Organization | BX9: https://sulwhasoo-jp.myshopify.com/pages/membership | BY9: 46128.603
A10: https://sulwhasoo-jp.myshopify.com/pages/edit-account | B10: text/html; charset=utf-8 | C10: 200 | D10: OK | E10: Indexable | G10: Edit Account | Sulwhasoo Japan | H10: 31 | I10: 284 | K10: 0 | L10: 0 | N10: 0 | O10: 個人情報の修正 | P10: 7 | R10: 0 | S10: カート0 | T10: 4 | U10: おすすめのキーワード | V10: 10 | Z10: https://sulwhasoo-jp.myshopify.com/pages/edit-account | AF10: 523711 | AG10: 113662 | AH10: 138 | AI10: 68 | AJ10: 2.029 | AK10: 100 | AL10: Very Easy | AM10: 0.391 | AN10: 0 | AO10: 1 | AQ10: 15 | AR10: 4 | AS10: 0 | AT10: 12.5 | AU10: 116 | AV10: 57 | AW10: 0 | BE10: eef09dc9509699f825109fbf1d5e892 | BF10: 0.323 | BK10: 1.1 | BL10: Edit Account | Sulwhasoo Japan | BM10: Sulwhasoo Japan | BN10: website | BO10: Sulwhasoo Japan | BQ10: https://sulwhasoo-jp.myshopify.com/pages/edit-account | BR10: summary_large_image | BS10: Edit Account | Sulwhasoo Japan | BV10: Organization | BX10: https://sulwhasoo-jp.myshopify.com/pages/edit-account | BY10: 46128.603
A11: https://sulwhasoo-jp.myshopify.com/pages/shopping-guide | B11: text/html; charset=utf-8 | C11: 200 | D11: OK | E11: Indexable | G11: Shopping Guide | Sulwhasoo Japan | H11: 33 | I11: 312 | K11: 0 | L11: 0 | N11: 0 | O11: ご注文について | P11: 7 | R11: 0 | S11: カート0 | T11: 4 | U11: おすすめのキーワード | V11: 10 | Z11: https://sulwhasoo-jp.myshopify.com/pages/shopping-guide | AF11: 529563 | AG11: 114714 | AH11: 242 | AI11: 126 | AJ11: 1.921 | AK11: 100 | AL11: Very Easy | AM11: 0.695 | AN11: 0 | AO11: 1 | AQ11: 52 | AR11: 30 | AS11: 0 | AT11: 93.75 | AU11: 119 | AV11: 51 | AW11: 0 | BE11: bea393938a3e1768f21a1b5887468e6f | BF11: 0.331 | BK11: 1.1 | BL11: Shopping Guide | Sulwhasoo Japan | BM11: Sulwhasoo Japan | BN11: website | BO11: Sulwhasoo Japan | BQ11: https://sulwhasoo-jp.myshopify.com/pages/shopping-guide | BR11: summary_large_image | BS11: Shopping Guide | Sulwhasoo Japan | BV11: Organization | BX11: https://sulwhasoo-jp.myshopify.com/pages/shopping-guide | BY11: 46128.603
A12: https://sulwhasoo-jp.myshopify.com/pages/activate-account-form | B12: text/html; charset=utf-8 | C12: 200 | D12: OK | E12: Indexable | G12: Activate Account Form | Sulwhasoo Japan | H12: 40 | I12: 376 | K12: 0 | L12: 0 | N12: 0 | P12: 0 | R12: 0 | S12: カート0 | T12: 4 | U12: おすすめのキーワード | V12: 10 | Z12: https://sulwhasoo-jp.myshopify.com/pages/activate-account-form | AF12: 512305 | AG12: 112066 | AH12: 136 | AI12: 66 | AJ12: 2.061 | AK12: 100 | AL12: Very Easy | AM12: 0.374 | AN12: 0 | AO12: 1 | AQ12: 7 | AR12: 1 | AS12: 0 | AT12: 3.13 | AU12: 104 | AV12: 52 | AW12: 0 | BE12: 705301e5d37e8f8f939b0b5e779f5851 | BF12: 0.324 | BK12: 1.1 | BL12: Activate Account Form | Sulwhasoo Japan | BM12: Sulwhasoo Japan | BN12: website | BO12: Sulwhasoo Japan | BQ12: https://sulwhasoo-jp.myshopify.com/pages/activate-account-form | BR12: summary_large_image | BS12: Activate Account Form | Sulwhasoo Japan | BV12: Organization | BX12: https://sulwhasoo-jp.myshopify.com/pages/activate-account-form | BY12: 46128.603
A13: https://sulwhasoo-jp.myshopify.com/pages/pub-test | B13: text/html; charset=utf-8 | C13: 200 | D13: OK | E13: Indexable | G13: (퍼블) 퍼블리싱 테스트 | Sulwhasoo Japan | H13: 32 | I13: 277 | J13: Font test Font test Font test Font test Font test Font test | K13: 59 | L13: 351 | N13: 0 | O13: Sulwhasoo | P13: 9 | R13: 0 | T13: 0 | V13: 0 | Z13: https://sulwhasoo-jp.myshopify.com/pages/pub-test | AF13: 447666 | AG13: 109380 | AH13: 82 | AI13: 13 | AJ13: 6.308 | AK13: 100 | AL13: Very Easy | AM13: 0.084 | AN13: 0 | AO13: 1 | AQ13: 0 | AR13: 0 | AS13: 0 | AT13: 0 | AU13: 0 | AV13: 0 | AW13: 0 | BE13: 21f53dcc7b67eb4e38028957ae13b926 | BF13: 0.313 | BK13: 1.1 | BL13: (퍼블) 퍼블리싱 테스트 | Sulwhasoo Japan | BM13: Font test Font test Font test Font test Font test Font test | BN13: website | BO13: Sulwhasoo Japan | BQ13: https://sulwhasoo-jp.myshopify.com/pages/pub-test | BR13: summary_large_image | BS13: (퍼블) 퍼블리싱 테스트 | Sulwhasoo Japan | BX13: https://sulwhasoo-jp.myshopify.com/pages/pub-test | BY13: 46128.603
A14: https://sulwhasoo-jp.myshopify.com/pages/brand-story | B14: text/html; charset=utf-8 | C14: 200 | D14: OK | E14: Indexable | G14: Brand Story | Sulwhasoo Japan | H14: 29 | I14: 275 | J14: Sulwhasoo fuses Korean tradition with cutting-edge science, using JAUM Activator® and ginseng research for youthful, radiant skin | K14: 129 | L14: 813 | N14: 0 | O14: Brand Story | Sulwhasoo Japan | P14: 29 | Q14: 時の流れにゆるがない美しさへの旅 | R14: 16 | S14: カート0 | T14: 4 | U14: おすすめのキーワード | V14: 10 | Z14: https://sulwhasoo-jp.myshopify.com/pages/brand-story | AF14: 570849 | AG14: 123432 | AH14: 256 | AI14: 134 | AJ14: 1.91 | AK14: 100 | AL14: Very Easy | AM14: 0.671 | AN14: 0 | AO14: 1 | AQ14: 133 | AR14: 30 | AS14: 0 | AT14: 93.75 | AU14: 107 | AV14: 51 | AW14: 0 | BE14: f783b21f2e47b7901aaf57a8718bfd5 | BF14: 0.455 | BK14: 1.1 | BL14: Brand Story | Sulwhasoo Japan | BM14: Sulwhasoo fuses Korean tradition with cutting-edge science, using JAUM Activator® and ginseng research for youthful, radiant skin | BN14: website | BO14: Sulwhasoo Japan | BQ14: https://sulwhasoo-jp.myshopify.com/pages/brand-story | BR14: summary_large_image | BS14: Brand Story | Sulwhasoo Japan | BV14: Organization | BX14: https://sulwhasoo-jp.myshopify.com/pages/brand-story | BY14: 46128.603
A15: https://sulwhasoo-jp.myshopify.com/pages/brand-sustainability | B15: text/html; charset=utf-8 | C15: 200 | D15: OK | E15: Indexable | G15: Brand Sustainability – Earth & Culture | Sulwhasoo Japan | H15: 56 | I15: 506 | J15: Sulwhasoo’s sustainable beauty is built on Ginseng Science, Environmental Care, and Cultural Heritage to shape a better future. | K15: 127 | L15: 785 | N15: 0 | O15: Brand Sustainability | Sulwhasoo Japan | P15: 38 | Q15: 持続可能な未来のための約束 | R15: 13 | S15: カート0 | T15: 4 | U15: おすすめのキーワード | V15: 10 | Z15: https://sulwhasoo-jp.myshopify.com/pages/brand-sustainability | AF15: 571548 | AG15: 121669 | AH15: 277 | AI15: 154 | AJ15: 1.799 | AK15: 100 | AL15: Very Easy | AM15: 0.727 | AN15: 0 | AO15: 1 | AQ15: 102 | AR15: 30 | AS15: 0 | AT15: 93.75 | AU15: 107 | AV15: 51 | AW15: 0 | BE15: 8693d5ae3cf681ce807cc3b66e0a7a05 | BF15: 0.284 | BK15: 1.1 | BL15: Brand Sustainability – Earth & Culture | Sulwhasoo Japan | BM15: Sulwhasoo’s sustainable beauty is built on Ginseng Science, Environmental Care, and Cultural Heritage to shape a better future. | BN15: website | BO15: Sulwhasoo Japan | BQ15: https://sulwhasoo-jp.myshopify.com/pages/brand-sustainability | BR15: summary_large_image | BS15: Brand Sustainability – Earth & Culture | Sulwhasoo Japan | BV15: Organization | BX15: https://sulwhasoo-jp.myshopify.com/pages/brand-sustainability | BY15: 46128.603
A16: https://sulwhasoo-jp.myshopify.com/pages/store-locator | B16: text/html; charset=utf-8 | C16: 200 | D16: OK | E16: Indexable | G16: Store Locator | Sulwhasoo Japan | H16: 32 | I16: 293 | J16: Store Locator is loading from Storemapper plugin... | K16: 51 | L16: 317 | N16: 0 | P16: 0 | R16: 0 | S16: カート0 | T16: 4 | U16: おすすめのキーワード | V16: 10 | Z16: https://sulwhasoo-jp.myshopify.com/pages/store-locator | AF16: 522179 | AG16: 112638 | AH16: 136 | AI16: 66 | AJ16: 2.061 | AK16: 100 | AL16: Very Easy | AM16: 0.404 | AN16: 0 | AO16: 1 | AQ16: 7 | AR16: 1 | AS16: 0 | AT16: 3.13 | AU16: 118 | AV16: 52 | AW16: 0 | BE16: abc16ff67ef4dc3d996147e31fae9740 | BF16: 0.348 | BK16: 1.1 | BL16: Store Locator | Sulwhasoo Japan | BM16: Store Locator is loading from Storemapper plugin... | BN16: website | BO16: Sulwhasoo Japan | BQ16: https://sulwhasoo-jp.myshopify.com/pages/store-locator | BR16: summary_large_image | BS16: Store Locator | Sulwhasoo Japan | BV16: Organization | BX16: https://sulwhasoo-jp.myshopify.com/pages/store-locator | BY16: 46128.603
A17: https://sulwhasoo-jp.myshopify.com/pages/mypage | B17: text/html; charset=utf-8 | C17: 200 | D17: OK | E17: Indexable | G17: mypage | Sulwhasoo Japan | H17: 25 | I17: 243 | K17: 0 | L17: 0 | N17: 0 | O17: マイページ | P17: 5 | R17: 0 | S17: カート0 | T17: 4 | U17: おすすめのキーワード | V17: 10 | Z17: https://sulwhasoo-jp.myshopify.com/pages/mypage | AF17: 521981 | AG17: 113310 | AH17: 146 | AI17: 74 | AJ17: 1.973 | AK17: 100 | AL17: Very Easy | AM17: 0.407 | AN17: 0 | AO17: 1 | AQ17: 15 | AR17: 4 | AS17: 0 | AT17: 12.5 | AU17: 118 | AV17: 57 | AW17: 0 | BE17: bcb5705dd62caabfcd15e59ded3791f5 | BF17: 0.375 | BK17: 1.1 | BL17: mypage | Sulwhasoo Japan | BM17: Sulwhasoo Japan | BN17: website | BO17: Sulwhasoo Japan | BQ17: https://sulwhasoo-jp.myshopify.com/pages/mypage | BR17: summary_large_image | BS17: mypage | Sulwhasoo Japan | BV17: Organization | BX17: https://sulwhasoo-jp.myshopify.com/pages/mypage | BY17: 46128.603
A18: https://sulwhasoo-jp.myshopify.com/pages/pub-wsg | B18: text/html; charset=utf-8 | C18: 200 | D18: OK | E18: Indexable | G18: (퍼블) 퍼블리싱 WSG | Sulwhasoo Japan | H18: 32 | I18: 294 | K18: 0 | L18: 0 | N18: 0 | O18: Theme Style Guide | P18: 17 | R18: 0 | S18: Shopify 작업 규칙 가이드 | T18: 17 | U18: 1. 네이밍 규칙 | V18: 9 | Z18: https://sulwhasoo-jp.myshopify.com/pages/pub-wsg | AF18: 606008 | AG18: 143560 | AH18: 3325 | AI18: 1507 | AJ18: 2.206 | AK18: 47.15 | AL18: Hard | AM18: 7.702 | AN18: 0 | AO18: 1 | AQ18: 31 | AR18: 1 | AS18: 0 | AT18: 3.13 | AU18: 31 | AV18: 1 | AW18: 0 | BE18: 25ad1e59bb3b437eff92ba9303b757ab | BF18: 2.897 | BK18: 1.1 | BL18: (퍼블) 퍼블리싱 WSG | Sulwhasoo Japan | BM18: Sulwhasoo Japan | BN18: website | BO18: Sulwhasoo Japan | BQ18: https://sulwhasoo-jp.myshopify.com/pages/pub-wsg | BR18: summary_large_image | BS18: (퍼블) 퍼블리싱 WSG | Sulwhasoo Japan | BX18: https://sulwhasoo-jp.myshopify.com/pages/pub-wsg | BY18: 46128.603
A19: https://sulwhasoo-jp.myshopify.com/pages/legal-notice | B19: text/html; charset=utf-8 | C19: 200 | D19: OK | E19: Indexable | G19: 特定商取引法に基づく表記 | Sulwhasoo Japan | H19: 31 | I19: 413 | J19: 事業者名 アモーレパシフィックジャパン株式会社 所在地 〒150-0012 東京都渋谷区広尾１－１３－７ 恵比寿イーストビル2階 代表者 代表 松井 理奈 お問い合わせ Sulwhasoo カスタマーサポート TEL：0120-929-744 受付時間： 月~金 10:00 ~ 18:00＜祝祭日、年末年始・夏期休暇を除く＞ フォームでのお問い合わせはこちら URL https://jp.sulwhasoo.com/ 販売価格 各商品詳細ページに表示された価格に基づきます。表示価格は本体価格に消費税額を加えた「お支払い総額（税込価格）」となっております。 商品代金以外の必要料金 ■送料：通常配送料金は、550円（税込）※沖縄、北海 | K19: 320 | L19: 3782 | N19: 0 | P19: 0 | R19: 0 | S19: カート0 | T19: 4 | U19: おすすめのキーワード | V19: 10 | Z19: https://sulwhasoo-jp.myshopify.com/pages/legal-notice | AF19: 517038 | AG19: 113724 | AH19: 146 | AI19: 70 | AJ19: 2.086 | AK19: 100 | AL19: Very Easy | AM19: 0.394 | AN19: 0 | AO19: 1 | AQ19: 7 | AR19: 1 | AS19: 0 | AT19: 3.13 | AU19: 104 | AV19: 52 | AW19: 0 | BE19: ec156ada5d185315784c390a8e061f5e | BF19: 0.336 | BK19: 1.1 | BL19: 特定商取引法に基づく表記 | Sulwhasoo Japan | BM19: 事業者名 アモーレパシフィックジャパン株式会社 所在地 〒150-0012 東京都渋谷区広尾１－１３－７ 恵比寿イーストビル2階 代表者 代表 松井 理奈 お問い合わせ Sulwhasoo カスタマーサポート TEL：0120-929-744 受付時間： 月~金 10:00 ~ 18:00＜祝祭日、年末年始・夏期休暇を除く＞ フォームでのお問い合わせはこちら URL https://jp.sulwhasoo.com/ 販売価格 各商品詳細ページに表示された価格に基づきます。表示価格は本体価格に消費税額を加えた「お支払い総額（税込価格）」となっております。 商品代金以外の必要料金 ■送料：通常配送料金は、550円（税込）※沖縄、北海 | BN19: website | BO19: Sulwhasoo Japan | BQ19: https://sulwhasoo-jp.myshopify.com/pages/legal-notice | BR19: summary_large_image | BS19: 特定商取引法に基づく表記 | Sulwhasoo Japan | BV19: Organization | BX19: https://sulwhasoo-jp.myshopify.com/pages/legal-notice | BY19: 46128.603
A20: https://sulwhasoo-jp.myshopify.com/pages/shop-info | B20: text/html; charset=utf-8 | C20: 200 | D20: OK | E20: Indexable | G20: Shop Info | Sulwhasoo Japan | H20: 28 | I20: 256 | K20: 0 | L20: 0 | N20: 0 | O20: Shop Info | P20: 9 | R20: 0 | S20: カート0 | T20: 4 | U20: おすすめのキーワード | V20: 10 | Z20: https://sulwhasoo-jp.myshopify.com/pages/shop-info | AF20: 525736 | AG20: 112767 | AH20: 187 | AI20: 89 | AJ20: 2.101 | AK20: 100 | AL20: Very Easy | AM20: 0.449 | AN20: 0 | AO20: 1 | AQ20: 68 | AR20: 30 | AS20: 0 | AT20: 93.75 | AU20: 112 | AV20: 51 | AW20: 0 | BE20: deeb7ded7da74142cfb4d0a1ac56b45a | BF20: 0.373 | BK20: 1.1 | BL20: Shop Info | Sulwhasoo Japan | BM20: Sulwhasoo Japan | BN20: website | BO20: Sulwhasoo Japan | BQ20: https://sulwhasoo-jp.myshopify.com/pages/shop-info | BR20: summary_large_image | BS20: Shop Info | Sulwhasoo Japan | BV20: Organization | BX20: https://sulwhasoo-jp.myshopify.com/pages/shop-info | BY20: 46128.603
A21: https://sulwhasoo-jp.myshopify.com/pages/my-address | B21: text/html; charset=utf-8 | C21: 200 | D21: OK | E21: Indexable | G21: my-address | Sulwhasoo Japan | H21: 29 | I21: 276 | K21: 0 | L21: 0 | N21: 0 | O21: My Page | P21: 7 | R21: 0 | S21: カート0 | T21: 4 | U21: おすすめのキーワード | V21: 10 | Z21: https://sulwhasoo-jp.myshopify.com/pages/my-address | AF21: 516170 | AG21: 112223 | AH21: 148 | AI21: 71 | AJ21: 2.085 | AK21: 100 | AL21: Very Easy | AM21: 0.399 | AN21: 0 | AO21: 1 | AQ21: 15 | AR21: 5 | AS21: 0 | AT21: 15.63 | AU21: 106 | AV21: 53 | AW21: 0 | BE21: 229c01a04c4976566bd7aa950bb40949 | BF21: 0.386 | BK21: 1.1 | BL21: my-address | Sulwhasoo Japan | BM21: Sulwhasoo Japan | BN21: website | BO21: Sulwhasoo Japan | BQ21: https://sulwhasoo-jp.myshopify.com/pages/my-address | BR21: summary_large_image | BS21: my-address | Sulwhasoo Japan | BV21: Organization | BX21: https://sulwhasoo-jp.myshopify.com/pages/my-address | BY21: 46128.603
A22: https://sulwhasoo-jp.myshopify.com/pages/pub-blog | B22: text/html; charset=utf-8 | C22: 200 | D22: OK | E22: Indexable | G22: pub-blog | Sulwhasoo Japan | H22: 27 | I22: 249 | K22: 0 | L22: 0 | N22: 0 | O22: pub-blog | P22: 8 | R22: 0 | S22: カート0 | T22: 4 | U22: おすすめのキーワード | V22: 10 | Z22: https://sulwhasoo-jp.myshopify.com/pages/pub-blog | AF22: 514548 | AG22: 112304 | AH22: 146 | AI22: 70 | AJ22: 2.086 | AK22: 100 | AL22: Very Easy | AM22: 0.385 | AN22: 0 | AO22: 1 | AQ22: 7 | AR22: 1 | AS22: 0 | AT22: 3.13 | AU22: 107 | AV22: 52 | AW22: 0 | BE22: 657177f235099f5c483e2772d1da4aca | BF22: 0.345 | BK22: 1.1 | BL22: pub-blog | Sulwhasoo Japan | BM22: Sulwhasoo Japan | BN22: website | BO22: Sulwhasoo Japan | BQ22: https://sulwhasoo-jp.myshopify.com/pages/pub-blog | BR22: summary_large_image | BS22: pub-blog | Sulwhasoo Japan | BV22: Organization | BX22: https://sulwhasoo-jp.myshopify.com/pages/pub-blog | BY22: 46128.603
A23: https://sulwhasoo-jp.myshopify.com/blogs/notice | B23: text/html; charset=utf-8 | C23: 200 | D23: OK | E23: Indexable | G23: Notice | Sulwhasoo Japan | H23: 25 | I23: 230 | K23: 0 | L23: 0 | N23: 0 | O23: お知らせ | P23: 4 | R23: 0 | S23: カート0 | T23: 4 | U23: おすすめのキーワード | V23: 10 | Z23: https://sulwhasoo-jp.myshopify.com/blogs/notice | AF23: 523935 | AG23: 113164 | AH23: 141 | AI23: 70 | AJ23: 2.014 | AK23: 100 | AL23: Very Easy | AM23: 0.408 | AN23: 0 | AO23: 1 | AQ23: 52 | AR23: 30 | AS23: 0 | AT23: 93.75 | AU23: 118 | AV23: 51 | AW23: 0 | BE23: 1591e481d90d30bea83e93d285aee3d2 | BF23: 0.369 | BK23: 1.1 | BL23: Notice | Sulwhasoo Japan | BM23: Sulwhasoo Japan | BN23: website | BO23: Sulwhasoo Japan | BQ23: https://sulwhasoo-jp.myshopify.com/blogs/notice | BR23: summary_large_image | BS23: Notice | Sulwhasoo Japan | BV23: Organization | BW23: /blogs/notice.atom | BX23: https://sulwhasoo-jp.myshopify.com/blogs/notice | BY23: 46128.603
A24: https://sulwhasoo-jp.myshopify.com/blogs/event | B24: text/html; charset=utf-8 | C24: 200 | D24: OK | E24: Indexable | G24: Event | Sulwhasoo Japan | H24: 24 | I24: 222 | K24: 0 | L24: 0 | N24: 0 | O24: イベント | P24: 4 | R24: 0 | S24: カート0 | T24: 4 | U24: おすすめのキーワード | V24: 10 | Z24: https://sulwhasoo-jp.myshopify.com/blogs/event | AF24: 525641 | AG24: 113524 | AH24: 177 | AI24: 83 | AJ24: 2.133 | AK24: 100 | AL24: Very Easy | AM24: 0.483 | AN24: 0 | AO24: 1 | AQ24: 7 | AR24: 1 | AS24: 0 | AT24: 3.13 | AU24: 112 | AV24: 58 | AW24: 0 | BE24: d84c77d18f15a3a9916ee94e591c77b | BF24: 0.396 | BK24: 1.1 | BL24: Event | Sulwhasoo Japan | BM24: Sulwhasoo Japan | BN24: website | BO24: Sulwhasoo Japan | BQ24: https://sulwhasoo-jp.myshopify.com/blogs/event | BR24: summary_large_image | BS24: Event | Sulwhasoo Japan | BV24: Organization | BW24: /blogs/event.atom | BX24: https://sulwhasoo-jp.myshopify.com/blogs/event | BY24: 46128.603
A25: https://sulwhasoo-jp.myshopify.com/blogs/sulwhasoo-post | B25: text/html; charset=utf-8 | C25: 200 | D25: OK | E25: Indexable | G25: Brand News | Heritage-Inspired Luxury | Sulwhasoo Japan | H25: 56 | I25: 512 | J25: Sulwhasoo, an iconic luxury beauty brand, dates back to 1932. Known for its pioneering spirit, it was the first to create products infused with ginseng. | K25: 152 | L25: 920 | N25: 0 | O25: BRAND NEWS | P25: 10 | R25: 0 | S25: カート0 | T25: 4 | U25: おすすめのキーワード | V25: 10 | Z25: https://sulwhasoo-jp.myshopify.com/blogs/sulwhasoo-post | AF25: 525317 | AG25: 114781 | AH25: 210 | AI25: 101 | AJ25: 2.079 | AK25: 100 | AL25: Very Easy | AM25: 0.712 | AN25: 0 | AO25: 1 | AQ25: 102 | AR25: 30 | AS25: 0 | AT25: 93.75 | AU25: 112 | AV25: 54 | AW25: 0 | BE25: 27334f52028bec548b4b641d67d210a7 | BF25: 0.359 | BK25: 1.1 | BL25: Brand News | Heritage-Inspired Luxury | Sulwhasoo Japan | BM25: Sulwhasoo, an iconic luxury beauty brand, dates back to 1932. Known for its pioneering spirit, it was the first to create products infused with ginseng. | BN25: website | BO25: Sulwhasoo Japan | BQ25: https://sulwhasoo-jp.myshopify.com/blogs/sulwhasoo-post | BR25: summary_large_image | BS25: Brand News | Heritage-Inspired Luxury | Sulwhasoo Japan | BV25: Organization | BW25: /blogs/sulwhasoo-post.atom | BX25: https://sulwhasoo-jp.myshopify.com/blogs/sulwhasoo-post | BY25: 46128.603
A26: https://sulwhasoo-jp.myshopify.com/blogs/event/dev-test-event-active | B26: text/html; charset=utf-8 | C26: 200 | D26: OK | E26: Indexable | G26: [DEV TEST] event-active | Sulwhasoo Japan | H26: 42 | I26: 386 | K26: 0 | L26: 0 | N26: 0 | O26: [DEV TEST] event-active | P26: 23 | R26: 0 | S26: カート0 | T26: 4 | U26: おすすめのキーワード | V26: 10 | Z26: https://sulwhasoo-jp.myshopify.com/blogs/event/dev-test-event-active | AF26: 521957 | AG26: 114229 | AH26: 145 | AI26: 71 | AJ26: 2.042 | AK26: 100 | AL26: Very Easy | AM26: 0.385 | AN26: 0 | AO26: 2 | AQ26: 8 | AR26: 2 | AS26: 0 | AT26: 6.25 | AU26: 107 | AV26: 52 | AW26: 0 | BE26: e70247a3a008e9e4813c5170b0f47374 | BF26: 0.302 | BK26: 1.1 | BL26: [DEV TEST] event-active | Sulwhasoo Japan | BM26: Sulwhasoo Japan | BN26: article | BO26: Sulwhasoo Japan | BP26: http://sulwhasoo-jp.myshopify.com/cdn/shop/articles/palm-trees-sky.jpg?v=1775914429 | BQ26: https://sulwhasoo-jp.myshopify.com/blogs/event/dev-test-event-active | BR26: summary_large_image | BS26: [DEV TEST] event-active | Sulwhasoo Japan | BV26: Organization | BW26: /blogs/event.atom | BX26: https://sulwhasoo-jp.myshopify.com/blogs/event/dev-test-event-active | BY26: 46128.603 | BZ26: Article | CA26: WebPage | CB26: Person | CC26: Organization
A27: https://sulwhasoo-jp.myshopify.com/blogs/event/dev-test-event-inactive | B27: text/html; charset=utf-8 | C27: 200 | D27: OK | E27: Indexable | G27: [DEV TEST] event-inactive | Sulwhasoo Japan | H27: 44 | I27: 402 | K27: 0 | L27: 0 | N27: 0 | O27: [DEV TEST] event-inactive | P27: 25 | R27: 0 | S27: カート0 | T27: 4 | U27: おすすめのキーワード | V27: 10 | Z27: https://sulwhasoo-jp.myshopify.com/blogs/event/dev-test-event-inactive | AF27: 521515 | AG27: 114458 | AH27: 145 | AI27: 71 | AJ27: 2.042 | AK27: 100 | AL27: Very Easy | AM27: 0.386 | AN27: 0 | AO27: 2 | AQ27: 8 | AR27: 2 | AS27: 0 | AT27: 6.25 | AU27: 107 | AV27: 53 | AW27: 0 | BE27: 69588078958fedb4371a108967ea7ae6 | BF27: 0.36 | BK27: 1.1 | BL27: [DEV TEST] event-inactive | Sulwhasoo Japan | BM27: Sulwhasoo Japan | BN27: article | BO27: Sulwhasoo Japan | BQ27: https://sulwhasoo-jp.myshopify.com/blogs/event/dev-test-event-inactive | BR27: summary_large_image | BS27: [DEV TEST] event-inactive | Sulwhasoo Japan | BV27: Organization | BW27: /blogs/event.atom | BX27: https://sulwhasoo-jp.myshopify.com/blogs/event/dev-test-event-inactive | BY27: 46128.603 | BZ27: Article | CA27: WebPage | CB27: Person | CC27: Organization
A28: https://sulwhasoo-jp.myshopify.com/blogs/event/dev-test-event-active2 | B28: text/html; charset=utf-8 | C28: 200 | D28: OK | E28: Indexable | G28: [DEV TEST] event-active2 | Sulwhasoo Japan | H28: 43 | I28: 397 | J28: 大人気「くまのプーさん」コラボアイテム登場。 爽やかな夏を楽しもう！ 大人気「くまのプーさん」コラボアイテム登場。 爽やかな夏を楽しもう！ 大人気「くまのプーさん」コラボアイテム登場。 爽やかな夏を楽しもう！ | K28: 104 | L28: 1411 | N28: 0 | O28: [DEV TEST] event-active2 | P28: 24 | R28: 0 | S28: カート0 | T28: 4 | U28: おすすめのキーワード | V28: 10 | Z28: https://sulwhasoo-jp.myshopify.com/blogs/event/dev-test-event-active2 | AF28: 524115 | AG28: 115287 | AH28: 157 | AI28: 76 | AJ28: 2.066 | AK28: 100 | AL28: Very Easy | AM28: 0.432 | AN28: 0 | AO28: 2 | AQ28: 8 | AR28: 2 | AS28: 0 | AT28: 6.25 | AU28: 107 | AV28: 52 | AW28: 0 | BE28: c38799ebfec0aaef30d9768ffbced344 | BF28: 0.427 | BK28: 1.1 | BL28: [DEV TEST] event-active2 | Sulwhasoo Japan | BM28: 大人気「くまのプーさん」コラボアイテム登場。 爽やかな夏を楽しもう！ 大人気「くまのプーさん」コラボアイテム登場。 爽やかな夏を楽しもう！ 大人気「くまのプーさん」コラボアイテム登場。 爽やかな夏を楽しもう！ | BN28: article | BO28: Sulwhasoo Japan | BP28: http://sulwhasoo-jp.myshopify.com/cdn/shop/articles/palm-trees-sky_a0dad88b-cd13-4099-b5e2-5dfea9fb50e1.jpg?v=1775914415 | BQ28: https://sulwhasoo-jp.myshopify.com/blogs/event/dev-test-event-active2 | BR28: summary_large_image | BS28: [DEV TEST] event-active2 | Sulwhasoo Japan | BV28: Organization | BW28: /blogs/event.atom | BX28: https://sulwhasoo-jp.myshopify.com/blogs/event/dev-test-event-active2 | BY28: 46128.603 | BZ28: Article | CA28: WebPage | CB28: Person | CC28: Organization
A29: https://sulwhasoo-jp.myshopify.com/blogs/sulwhasoo-post/2025-first-care-activating-serum-introduction | B29: text/html; charset=utf-8 | C29: 200 | D29: OK | E29: Indexable | G29: FIRST CARE ACTIVATING SERUM – Sulwhasoo Japan | H29: 45 | I29: 475 | J29: REVITALIZE YOUR SKIN FOR A HEALTHY, YOUTHFUL COMPLEXION | K29: 55 | L29: 422 | N29: 0 | O29: 2025 FIRST CARE ACTIVATING SERUM | P29: 32 | Q29: 潤燥ユンジョ ファーストケア アクティブセラム VI | R29: 26 | S29: カート0 | T29: 4 | U29: おすすめのキーワード | V29: 10 | Z29: https://sulwhasoo-jp.myshopify.com/blogs/sulwhasoo-post/2025-first-care-activating-serum-introduction | AF29: 561878 | AG29: 119734 | AH29: 342 | AI29: 169 | AJ29: 2.024 | AK29: 100 | AL29: Very Easy | AM29: 0.695 | AN29: 0 | AO29: 2 | AQ29: 8 | AR29: 2 | AS29: 0 | AT29: 6.25 | AU29: 105 | AV29: 53 | AW29: 0 | BE29: 5a226eed7b9344309c3206e493d5f119 | BF29: 0.348 | BK29: 1.1 | BL29: FIRST CARE ACTIVATING SERUM – Sulwhasoo Japan | BM29: REVITALIZE YOUR SKIN FOR A HEALTHY, YOUTHFUL COMPLEXION | BN29: article | BO29: Sulwhasoo Japan | BP29: http://sulwhasoo-jp.myshopify.com/cdn/shop/articles/251120_final_TH_brand-news_thumbnail_720x_9f9a8857-59ec-48da-9861-5472e1a130e3.webp?v=1776043398 | BQ29: https://sulwhasoo-jp.myshopify.com/blogs/sulwhasoo-post/2025-first-care-activating-serum-introduction | BR29: summary_large_image | BS29: FIRST CARE ACTIVATING SERUM – Sulwhasoo Japan | BV29: Organization | BW29: /blogs/sulwhasoo-post.atom | BX29: https://sulwhasoo-jp.myshopify.com/blogs/sulwhasoo-post/2025-first-care-activating-serum-introduction | BY29: 46128.603 | BZ29: Article | CA29: WebPage | CB29: Person | CC29: Organization
A30: https://sulwhasoo-jp.myshopify.com/blogs/sulwhasoo-post/concentrated-ginseng-rejuvenating-cream | B30: text/html; charset=utf-8 | C30: 200 | D30: OK | E30: Indexable | G30: Concentrated Ginseng Rejuvenating Cream | Sulwhasoo Japan | H30: 57 | I30: 557 | J30: Discover 60 years of Ginseng science with Sulwhasoo’s Concentrated Ginseng Rejuvenating Cream, boosting elasticity for a youthful glow. | K30: 135 | L30: 853 | N30: 0 | O30: Concentrated Ginseng Rejuvenating Cream | P30: 39 | R30: 0 | S30: カート0 | T30: 4 | U30: おすすめのキーワード | V30: 10 | Z30: https://sulwhasoo-jp.myshopify.com/blogs/sulwhasoo-post/concentrated-ginseng-rejuvenating-cream | AF30: 600964 | AG30: 124122 | AH30: 369 | AI30: 185 | AJ30: 1.995 | AK30: 100 | AL30: Very Easy | AM30: 0.677 | AN30: 0 | AO30: 2 | AQ30: 8 | AR30: 2 | AS30: 0 | AT30: 6.25 | AU30: 111 | AV30: 58 | AW30: 0 | BE30: 7100dfc86bdae1b799a98047c2a54ef0 | BF30: 0.358 | BK30: 1.1 | BL30: Concentrated Ginseng Rejuvenating Cream | Sulwhasoo Japan | BM30: Discover 60 years of Ginseng science with Sulwhasoo’s Concentrated Ginseng Rejuvenating Cream, boosting elasticity for a youthful glow. | BN30: article | BO30: Sulwhasoo Japan | BP30: http://sulwhasoo-jp.myshopify.com/cdn/shop/articles/240816_final_SG_concentrated-ginseng-rejuvenating-cream-cover_500x500_360x_83aa104d-76f3-4112-8d3b-ba15e6385f17.webp?v=1776072597 | BQ30: https://sulwhasoo-jp.myshopify.com/blogs/sulwhasoo-post/concentrated-ginseng-rejuvenating-cream | BR30: summary_large_image | BS30: Concentrated Ginseng Rejuvenating Cream | Sulwhasoo Japan | BV30: Organization | BW30: /blogs/sulwhasoo-post.atom | BX30: https://sulwhasoo-jp.myshopify.com/blogs/sulwhasoo-post/concentrated-ginseng-rejuvenating-cream | BY30: 46128.603 | BZ30: Article | CA30: WebPage | CB30: Person | CC30: Organization
A31: https://sulwhasoo-jp.myshopify.com/blogs/event/cosme-store-tokyoにてpopupstore開催 | B31: text/html; charset=utf-8 | C31: 200 | D31: OK | E31: Indexable | G31: @cosme store TOKYOにてPOPUPSTORE開催 | Sulwhasoo Japan | H31: 51 | I31: 580 | J31: 韓国発ラグジュアリースキンケアブランド「Sulwhasoo（ソルファス）」は、2026年5月6日から5月12日までの期間、＠cosme storeにてPOPUPSTOREを開催いたします【POPUP STORE開催概要】 期間：2026年5月6日～2026年5月12日 開催時間：11:00～21:00 場所：@cosme TOKYO 住所：東京都渋谷区神宮前1-14-27 | K31: 187 | L31: 2072 | N31: 0 | O31: @cosme store TOKYOにてPOPUPSTORE開催 | P31: 32 | R31: 0 | S31: カート0 | T31: 4 | U31: おすすめのキーワード | V31: 10 | Z31: https://sulwhasoo-jp.myshopify.com/blogs/event/cosme-store-tokyoにてpopupstore開催 | AF31: 524851 | AG31: 115824 | AH31: 158 | AI31: 82 | AJ31: 1.927 | AK31: 100 | AL31: Very Easy | AM31: 0.451 | AN31: 0 | AO31: 2 | AQ31: 9 | AR31: 3 | AS31: 0 | AT31: 9.38 | AU31: 107 | AV31: 52 | AW31: 0 | BE31: 30a59be4bb6342fa46eedc873f5b573b | BF31: 0.309 | BK31: 1.1 | BL31: @cosme store TOKYOにてPOPUPSTORE開催 | Sulwhasoo Japan | BM31: 韓国発ラグジュアリースキンケアブランド「Sulwhasoo（ソルファス）」は、2026年5月6日から5月12日までの期間、＠cosme storeにてPOPUPSTOREを開催いたします【POPUP STORE開催概要】 期間：2026年5月6日～2026年5月12日 開催時間：11:00～21:00 場所：@cosme TOKYO 住所：東京都渋谷区神宮前1-14-27 | BN31: article | BO31: Sulwhasoo Japan | BP31: http://sulwhasoo-jp.myshopify.com/cdn/shop/articles/111170002325_01_d50df340-e78c-4d41-ae4f-ea577d47fb7b.jpg?v=1776047739 | BQ31: https://sulwhasoo-jp.myshopify.com/blogs/event/cosme-store-tokyo%e3%81%ab%e3%81%a6popupstore%e9%96%8b%e5%82%ac | BR31: summary_large_image | BS31: @cosme store TOKYOにてPOPUPSTORE開催 | Sulwhasoo Japan | BV31: Organization | BW31: /blogs/event.atom | BX31: https://sulwhasoo-jp.myshopify.com/blogs/event/cosme-store-tokyo%E3%81%AB%E3%81%A6popupstore%E9%96%8B%E5%82%AC | BY31: 46128.603 | BZ31: Article | CA31: WebPage | CB31: Person | CC31: Organization
A32: https://sulwhasoo-jp.myshopify.com/blogs/sulwhasoo-post/journey-to-holistic-beauty-時の流れに揺るがない美しさへの旅 | B32: text/html; charset=utf-8 | C32: 200 | D32: OK | E32: Indexable | G32: 「Journey to Holistic Beauty」時の流れに揺るがない美しさへの旅 | Sulwhasoo Japan | H32: 63 | I32: 755 | J32: 時を超えて愛される韓国発ラグジュアリービューティーブランド、Sulwhasoo（雪花秀／ソルファス）。その世界観と高麗人参サイエンスを体験できる「Sulwhasoo Lounge（ソルファスラウンジ）」が、5月6日（水）より@cosme TOKYOにて1週間限定オープン。 アモーレパシフィックジャパン株式会社（所在地：東京都渋谷区 代表：羅政均）が展開する、韓国発ラグジュアリービューティーブランド『Sulwhasoo（雪花秀/ソルファス）』は、5月6日（水）から12日（火）までの1週間、@cosme TOKYO ポップアップストア1階にて「Sulwhasoo Lounge（ソルファスラウンジ）」を開催します。 長年にわたり韓国ビュー | K32: 320 | L32: 3966 | N32: 0 | P32: 0 | R32: 0 | S32: カート0 | T32: 4 | U32: おすすめのキーワード | V32: 10 | Z32: https://sulwhasoo-jp.myshopify.com/blogs/sulwhasoo-post/journey-to-holistic-beauty-時の流れに揺るがない美しさへの旅 | AF32: 534439 | AG32: 117566 | AH32: 213 | AI32: 110 | AJ32: 1.936 | AK32: 100 | AL32: Very Easy | AM32: 0.842 | AN32: 0 | AO32: 2 | AQ32: 8 | AR32: 2 | AS32: 0 | AT32: 6.25 | AU32: 104 | AV32: 52 | AW32: 0 | BE32: d7ded963fd1dfecb9c68efb9c7a5367e | BF32: 0.496 | BK32: 1.1 | BL32: 「Journey to Holistic Beauty」時の流れに揺るがない美しさへの旅 | Sulwhasoo Japan | BM32: 時を超えて愛される韓国発ラグジュアリービューティーブランド、Sulwhasoo（雪花秀／ソルファス）。その世界観と高麗人参サイエンスを体験できる「Sulwhasoo Lounge（ソルファスラウンジ）」が、5月6日（水）より@cosme TOKYOにて1週間限定オープン。 アモーレパシフィックジャパン株式会社（所在地：東京都渋谷区 代表：羅政均）が展開する、韓国発ラグジュアリービューティーブランド『Sulwhasoo（雪花秀/ソルファス）』は、5月6日（水）から12日（火）までの1週間、@cosme TOKYO ポップアップストア1階にて「Sulwhasoo Lounge（ソルファスラウンジ）」を開催します。 長年にわたり韓国ビュー | BN32: article | BO32: Sulwhasoo Japan | BP32: http://sulwhasoo-jp.myshopify.com/cdn/shop/articles/Sulwhasoo_JP.webp?v=1776042225 | BQ32: https://sulwhasoo-jp.myshopify.com/blogs/sulwhasoo-post/journey-to-holistic-beauty-%e6%99%82%e3%81%ae%e6%b5%81%e3%82%8c%e3%81%ab%e6%8f%ba%e3%82%8b%e3%81%8c%e3%81%aa%e3%81%84%e7%be%8e%e3%81%97%e3%81%95%e3%81%b8%e3%81%ae%e6%97%85 | BR32: summary_large_image | BS32: 「Journey to Holistic Beauty」時の流れに揺るがない美しさへの旅 | Sulwhasoo Japan | BV32: Organization | BW32: /blogs/sulwhasoo-post.atom | BX32: https://sulwhasoo-jp.myshopify.com/blogs/sulwhasoo-post/journey-to-holistic-beauty-%E6%99%82%E3%81%AE%E6%B5%81%E3%82%8C%E3%81%AB%E6%8F%BA%E3%82%8B%E3%81%8C%E3%81%AA%E3%81%84%E7%BE%8E%E3%81%97%E3%81%95%E3%81%B8%E3%81%AE%E6%97%85 | BY32: 46128.603 | BZ32: Article | CA32: WebPage | CB32: Person | CC32: Organization
A33: https://sulwhasoo-jp.myshopify.com/blogs/event/公式ストアオープン記念-レビューキャンペーン | B33: text/html; charset=utf-8 | C33: 200 | D33: OK | E33: Indexable | G33: 公式ストアオープン記念 レビューキャンペーン | Sulwhasoo Japan | H33: 41 | I33: 600 | J33: 公式ストアオープン記念レビューキャンペーン。 キャンペーン期間は2026年4月28日から6月30日までです。 対象商品レビュー投稿者の中から抽選で5名様にスペシャルギフトをプレゼントします。 | K33: 95 | L33: 1246 | N33: 0 | P33: 0 | R33: 0 | S33: カート0 | T33: 4 | U33: おすすめのキーワード | V33: 10 | Z33: https://sulwhasoo-jp.myshopify.com/blogs/event/公式ストアオープン記念-レビューキャンペーン | AF33: 525417 | AG33: 115175 | AH33: 145 | AI33: 72 | AJ33: 2.014 | AK33: 100 | AL33: Very Easy | AM33: 0.401 | AN33: 0 | AO33: 2 | AQ33: 8 | AR33: 2 | AS33: 0 | AT33: 6.25 | AU33: 113 | AV33: 55 | AW33: 0 | BE33: 9e5d7ff5aa5dca88050b8d314fee164f | BF33: 0.333 | BK33: 1.1 | BL33: 公式ストアオープン記念 レビューキャンペーン | Sulwhasoo Japan | BM33: 公式ストアオープン記念レビューキャンペーン。 キャンペーン期間は2026年4月28日から6月30日までです。 対象商品レビュー投稿者の中から抽選で5名様にスペシャルギフトをプレゼントします。 | BN33: article | BO33: Sulwhasoo Japan | BQ33: https://sulwhasoo-jp.myshopify.com/blogs/event/%e5%85%ac%e5%bc%8f%e3%82%b9%e3%83%88%e3%82%a2%e3%82%aa%e3%83%bc%e3%83%97%e3%83%b3%e8%a8%98%e5%bf%b5-%e3%83%ac%e3%83%93%e3%83%a5%e3%83%bc%e3%82%ad%e3%83%a3%e3%83%b3%e3%83%9a%e3%83%bc%e3%83%b3 | BR33: summary_large_image | BS33: 公式ストアオープン記念 レビューキャンペーン | Sulwhasoo Japan | BV33: Organization | BW33: /blogs/event.atom | BX33: https://sulwhasoo-jp.myshopify.com/blogs/event/%E5%85%AC%E5%BC%8F%E3%82%B9%E3%83%88%E3%82%A2%E3%82%AA%E3%83%BC%E3%83%97%E3%83%B3%E8%A8%98%E5%BF%B5-%E3%83%AC%E3%83%93%E3%83%A5%E3%83%BC%E3%82%AD%E3%83%A3%E3%83%B3%E3%83%9A%E3%83%BC%E3%83%B3 | BY33: 46128.603 | BZ33: Article | CA33: WebPage | CB33: Person | CC33: Organization

Sheet raw-sheet
A1: Address | B1: Content Type | C1: Status Code | D1: Status | E1: Indexability | F1: Indexability Status | G1: Title 1 | H1: Title 1 Length | I1: Title 1 Pixel Width | J1: Meta Description 1 | K1: Meta Description 1 Length | L1: Meta Description 1 Pixel Width | M1: Meta Keywords 1 | N1: Meta Keywords 1 Length | O1: H1-1 | P1: H1-1 Length | Q1: H1-2 | R1: H1-2 Length | S1: H2-1 | T1: H2-1 Length | U1: H2-2 | V1: H2-2 Length | W1: Meta Robots 1 | X1: X-Robots-Tag 1 | Y1: Meta Refresh 1 | Z1: Canonical Link Element 1 | AA1: rel="next" 1 | AB1: rel="prev" 1 | AC1: HTTP rel="next" 1 | AD1: HTTP rel="prev" 1 | AE1: amphtml Link Element | AF1: Size (bytes) | AG1: Transferred (bytes) | AH1: Total Transferred (bytes) | AI1: CO2 (mg) | AJ1: Carbon Rating | AK1: Word Count | AL1: Sentence Count | AM1: Average Words Per Sentence | AN1: Flesch Reading Ease Score | AO1: Readability | AP1: Text Ratio | AQ1: Crawl Depth | AR1: Folder Depth | AS1: Link Score | AT1: Inlinks | AU1: Unique Inlinks | AV1: Unique JS Inlinks | AW1: % of Total | AX1: Outlinks | AY1: Unique Outlinks | AZ1: Unique JS Outlinks | BA1: External Outlinks | BB1: Unique External Outlinks | BC1: Unique External JS Outlinks | BD1: Closest Near Duplicate Match | BE1: No. Near Duplicates | BF1: Spelling Errors | BG1: Grammar Errors | BH1: Hash | BI1: Response Time | BJ1: Last Modified | BK1: Redirect URL | BL1: Redirect Type | BM1: Cookies | BN1: Language | BO1: HTTP Version | BP1: OG Title 1 | BQ1: OG Description 1 | BR1: OG Type 1 | BS1: OG Site Name 1 | BT1: OG image 1 | BU1: OG url 1 | BV1: Twitter Card 1 | BW1: Twitter Title 1 | BX1: Twitter Site 1 | BY1: Twitter URL 1 | BZ1: schema 1 | CA1: schema 2 | CB1: schema 3 | CC1: alternate 1 | CD1: schema_type 1 | CE1: schema_type 2 | CF1: schema_type 3 | CG1: Mobile Alternate Link | CH1: Closest Semantically Similar Address | CI1: Semantic Similarity Score | CJ1: No. Semantically Similar | CK1: Semantic Relevance Score | CL1: URL Encoded Address | CM1: Crawl Timestamp
A2: https://www.sulwhasoo.com/kr/ko/about-sulwhasoo/brand-news/archive/2024-first-care-activating-serum-vi-introduction.html | B2: text/html | C2: 200 | D2: OK | E2: Indexable | G2: 윤조에센스 6세대 | 설화수 | H2: 15 | I2: 121 | J2: 피부 속건조부터 모공, 주름, 탄력까지 매일 차오르는 윤빛 피부 | K2: 35 | L2: 180 | N2: 0 | O2: 설화수 윤조에센스 6세대 소개 | P2: 16 | R2: 0 | S2: 설화수 윤조에센스 6세대 FIRST CARE ACTIVATING SERUM VI | T2: 44 | U2: 전 세계에서 사랑받는 베스트 셀러 설화수 윤조에센스 6세대 | V2: 32 | Z2: https://www.sulwhasoo.com/kr/ko/about-sulwhasoo/brand-news/archive/2024-first-care-activating-serum-vi-introduction.html | AF2: 51366 | AG2: 12322 | AH2: 12322 | AI2: 4.8016739 | AK2: 382 | AL2: 133 | AM2: 2.8721805 | AN2: 100 | AO2: Very Easy | AP2: 4.0589595 | AQ2: 0 | AR2: 5 | AT2: 4 | AU2: 1 | AV2: 0 | AW2: 0.61 | AX2: 18 | AY2: 13 | AZ2: 0 | BA2: 4 | BB2: 3 | BC2: 0 | BH2: 20e4e7af04d23b73a65445c7fac7e82a | BI2: 0.006 | BJ2: Thu, 05 Feb 2026 01:01:36 GMT | BN2: ko | BO2: 1.1 | BP2: 윤조에센스 6세대 | 설화수 | BQ2: 피부 속건조부터 모공, 주름, 탄력까지 매일 차오르는 윤빛 피부 | BR2: website | BS2: 설화수 | BT2: https://www.sulwhasoo.com/kr/ko/about-sulwhasoo/brand-news/archive/__icsFiles/afieldfile/2024/03/20/240319_final_KR_BRAND-NEWS_thumbnail_07_1.jpg | BU2: https://www.sulwhasoo.com/kr/ko/about-sulwhasoo/brand-news/archive/2024-first-care-activating-serum-vi-introduction.html | BV2: summary_large_image | BW2: 윤조에센스 6세대 | 설화수 | BY2: https://www.sulwhasoo.com/kr/ko/about-sulwhasoo/brand-news/archive/2024-first-care-activating-serum-vi-introduction.html | BZ2: schema.org | CD2: BreadcrumbList | CL2: https://www.sulwhasoo.com/kr/ko/about-sulwhasoo/brand-news/archive/2024-first-care-activating-serum-vi-introduction.html | CM2: 2026-02-05 15:35:55
A3: https://www.sulwhasoo.com/kr/ko/about-sulwhasoo/brand-news/archive/2024-lunar-new-year-limited-edition.html | B3: text/html | C3: 200 | D3: OK | E3: Indexable | G3: 윤조에센스 용의 해 에디션 | 설화수 | H3: 20 | I3: 156 | J3: 용의 해를 맞아 리미티드로 탄생한 설화수의 NO.1 에센스 | K3: 32 | L3: 179 | N3: 0 | O3: 윤조에센스 용의 해 에디션 소개 | P3: 17 | R3: 0 | S3: HAPPY NEW YEAR FROM SULWHASOO 윤조에센스 용의 해 에디션 | T3: 44 | U3: 윤조에센스 용의 해 에디션 | V3: 14 | Z3: https://www.sulwhasoo.com/kr/ko/about-sulwhasoo/brand-news/archive/2024-lunar-new-year-limited-edition.html | AF3: 49869 | AG3: 11814 | AH3: 11814 | AI3: 4.603715 | AK3: 360 | AL3: 110 | AM3: 3.2727273 | AN3: 100 | AO3: Very Easy | AP3: 3.7907693 | AQ3: 0 | AR3: 5 | AT3: 4 | AU3: 1 | AV3: 0 | AW3: 0.61 | AX3: 16 | AY3: 11 | AZ3: 0 | BA3: 2 | BB3: 2 | BC3: 0 | BH3: d051d294bfca1b92101cd08db64bd24 | BI3: 0.007 | BJ3: Thu, 05 Feb 2026 01:01:36 GMT | BN3: ko | BO3: 1.1 | BP3: 윤조에센스 용의 해 에디션 | 설화수 | BQ3: 용의 해를 맞아 리미티드로 탄생한 설화수의 NO.1 에센스 | BR3: website | BS3: 설화수 | BT3: https://www.sulwhasoo.com/kr/ko/about-sulwhasoo/brand-news/archive/__icsFiles/afieldfile/2024/03/07/240307_final_KR_BRAND-NEWS_thumbnail_01_2024-lunar-new-year-limited-edition_1.jpg | BU3: https://www.sulwhasoo.com/kr/ko/about-sulwhasoo/brand-news/archive/2024-lunar-new-year-limited-edition.html | BV3: summary_large_image | BW3: 윤조에센스 용의 해 에디션 | 설화수 | BY3: https://www.sulwhasoo.com/kr/ko/about-sulwhasoo/brand-news/archive/2024-lunar-new-year-limited-edition.html | BZ3: schema.org | CD3: BreadcrumbList | CL3: https://www.sulwhasoo.com/kr/ko/about-sulwhasoo/brand-news/archive/2024-lunar-new-year-limited-edition.html | CM3: 2026-02-05 15:35:42
A4: https://www.sulwhasoo.com/kr/ko/about-sulwhasoo/brand-news/archive/2025-concentrated-ginseng-rejuvenating-cream.html | B4: text/html | C4: 200 | D4: OK | E4: Indexable | G4: 2025 자음생크림 | 설화수 | H4: 16 | I4: 136 | J4: 10년 연속 안티에이징 크림 1위. 60년간 끊임없는 진화를 거듭해온 자음생크림은 한 순간의 에이징 케어를 넘어 피부의 장수를 바라봅니다. | K4: 77 | L4: 417 | N4: 0 | O4: 설화수 자음생크림 | P4: 9 | R4: 0 | S4: 설화수 자음생크림 소개 영상 | T4: 15 | U4: 10년 연속 안티에이징 크림 1위* 자음생크림 | V4: 25 | Z4: https://www.sulwhasoo.com/kr/ko/about-sulwhasoo/brand-news/archive/2025-concentrated-ginseng-rejuvenating-cream.html | AF4: 72205 | AG4: 12796 | AH4: 12796 | AI4: 4.9863837 | AK4: 516 | AL4: 179 | AM4: 2.8826816 | AN4: 100 | AO4: Very Easy | AP4: 3.5115416 | AQ4: 0 | AR4: 5 | AT4: 4 | AU4: 1 | AV4: 0 | AW4: 0.61 | AX4: 23 | AY4: 18 | AZ4: 0 | BA4: 9 | BB4: 9 | BC4: 0 | BH4: cd1fa3ca1675ccdee09709431ed51cf4 | BI4: 0.03 | BJ4: Thu, 05 Feb 2026 01:01:36 GMT | BN4: ko | BO4: 1.1 | BP4: 2025 자음생크림 | 설화수 | BQ4: 10년 연속 안티에이징 크림 1위. 60년간 끊임없는 진화를 거듭해온 자음생크림은 한 순간의 에이징 케어를 넘어 피부의 장수를 바라봅니다. | BR4: website | BS4: 설화수 | BT4: https://www.sulwhasoo.com/kr/ko/about-sulwhasoo/brand-news/archive/__icsFiles/afieldfile/2025/08/05/250729_final_KR_CGRC_thumbnail_1.jpg | BU4: https://www.sulwhasoo.com/kr/ko/about-sulwhasoo/brand-news/archive/2025-concentrated-ginseng-rejuvenating-cream.html | BV4: summary_large_image | BW4: 2025 자음생크림 | 설화수 | BY4: https://www.sulwhasoo.com/kr/ko/about-sulwhasoo/brand-news/archive/2025-concentrated-ginseng-rejuvenating-cream.html | BZ4: schema.org | CD4: BreadcrumbList | CL4: https://www.sulwhasoo.com/kr/ko/about-sulwhasoo/brand-news/archive/2025-concentrated-ginseng-rejuvenating-cream.html | CM4: 2026-02-05 15:34:47
A5: https://www.sulwhasoo.com/kr/ko/about-sulwhasoo/brand-news/archive/2025-first-care-activating-serum-vi-introduction.html | B5: text/html | C5: 200 | D5: OK | E5: Indexable | G5: 윤조에센스 6세대 출시 - 브랜드 뉴스 | 설화수 | H5: 27 | I5: 210 | J5: 피부 본연의 힘을 깨워 건강한 윤기를 선사하는 FIRST STEP, 윤조에센스 6세대가 출시되었습니다. | K5: 57 | L5: 322 | N5: 0 | O5: 정체된 피부 흐름을 되살려, 다시 윤빛 도는 피부 설화수 윤조에센스 6세대 FIRST CARE ACTIVATING SERUM VI | P5: 72 | R5: 0 | S5: 시대와 세대를 뛰어넘는 안티에이징 에센스 설화수 베스트셀러1) 윤조에센스 | T5: 40 | U5: 윤조에센스 6세대 | V5: 9 | Z5: https://www.sulwhasoo.com/kr/ko/about-sulwhasoo/brand-news/archive/2025-first-care-activating-serum-vi-introduction.html | AF5: 47036 | AG5: 10839 | AH5: 10839 | AI5: 4.223774 | AK5: 362 | AL5: 128 | AM5: 2.828125 | AN5: 100 | AO5: Very Easy | AP5: 3.8650084 | AQ5: 0 | AR5: 5 | AT5: 4 | AU5: 1 | AV5: 0 | AW5: 0.61 | AX5: 17 | AY5: 12 | AZ5: 0 | BA5: 3 | BB5: 3 | BC5: 0 | BH5: 9a91a38cd2042e75c90440ff04867f79 | BI5: 0.009 | BJ5: Thu, 05 Feb 2026 01:01:36 GMT | BN5: ko | BO5: 1.1 | BP5: 윤조에센스 6세대 출시 - 브랜드 뉴스 | 설화수 | BQ5: 피부 본연의 힘을 깨워 건강한 윤기를 선사하는 FIRST STEP, 윤조에센스 6세대가 출시되었습니다. | BR5: website | BS5: 설화수 | BT5: https://www.sulwhasoo.com/kr/ko/about-sulwhasoo/brand-news/archive/__icsFiles/afieldfile/2025/02/14/250211_final_KR_first-care-activating-serum-vi_thumbnail_1.jpg | BU5: https://www.sulwhasoo.com/kr/ko/about-sulwhasoo/brand-news/archive/2025-first-care-activating-serum-vi-introduction.html | BV5: summary_large_image | BW5: 윤조에센스 6세대 출시 - 브랜드 뉴스 | 설화수 | BY5: https://www.sulwhasoo.com/kr/ko/about-sulwhasoo/brand-news/archive/2025-first-care-activating-serum-vi-introduction.html | BZ5: schema.org | CD5: BreadcrumbList | CL5: https://www.sulwhasoo.com/kr/ko/about-sulwhasoo/brand-news/archive/2025-first-care-activating-serum-vi-introduction.html | CM5: 2026-02-05 15:35:23
A6: https://www.sulwhasoo.com/kr/ko/about-sulwhasoo/brand-news/archive/2025-holiday-collection.html | B6: text/html | C6: 200 | D6: OK | E6: Indexable | G6: 2025 홀리데이 | 설화수 | H6: 15 | I6: 127 | J6: A Holiday of unexpected delight - 이번 연말, 설화수와 함께 당신만의 unexpected delight를 만나보세요. | K6: 80 | L6: 467 | N6: 0 | O6: A Holiday of unexpected delight | P6: 31 | R6: 0 | S6: 이번 연말, 설화수와 함께 당신만의 unexpected delight를 만나보세요. | T6: 46 | U6: 함께 사용하면 좋은 제품 | V6: 13 | Z6: https://www.sulwhasoo.com/kr/ko/about-sulwhasoo/brand-news/archive/2025-holiday-collection.html | AF6: 38412 | AG6: 9567 | AH6: 9567 | AI6: 3.7280973 | AK6: 135 | AL6: 44 | AM6: 3.0681818 | AN6: 100 | AO6: Very Easy | AP6: 2.0465734 | AQ6: 0 | AR6: 5 | AT6: 4 | AU6: 1 | AV6: 0 | AW6: 0.61 | AX6: 16 | AY6: 11 | AZ6: 0 | BA6: 4 | BB6: 4 | BC6: 0 | BH6: f5034583952bd7a97eed54cd5d75d6cf | BI6: 0.008 | BJ6: Thu, 05 Feb 2026 01:01:36 GMT | BN6: ko | BO6: 1.1 | BP6: 2025 홀리데이 | 설화수 | BQ6: A Holiday of unexpected delight - 이번 연말, 설화수와 함께 당신만의 unexpected delight를 만나보세요. | BR6: website | BS6: 설화수 | BT6: https://www.sulwhasoo.com/kr/ko/about-sulwhasoo/brand-news/archive/__icsFiles/afieldfile/2025/10/27/251027_final_KR_Holiday-Collection_brand-news_thumbnail_1.jpg | BU6: https://www.sulwhasoo.com/kr/ko/about-sulwhasoo/brand-news/archive/2025-holiday-collection.html | BV6: summary_large_image | BW6: 2025 홀리데이 | 설화수 | BY6: https://www.sulwhasoo.com/kr/ko/about-sulwhasoo/brand-news/archive/2025-holiday-collection.html | BZ6: schema.org | CD6: BreadcrumbList | CL6: https://www.sulwhasoo.com/kr/ko/about-sulwhasoo/brand-news/archive/2025-holiday-collection.html | CM6: 2026-02-05 15:35:13
A7: https://www.sulwhasoo.com/kr/ko/about-sulwhasoo/brand-news/archive/2026-lunar-new-year-limited-edition.html | B7: text/html | C7: 200 | D7: OK | E7: Indexable | G7: 윤조에센스 붉은 말의 해 에디션 | 설화수 | H7: 23 | I7: 179 | J7: 붉은 말의 해를 맞아 리미티드로 탄생한 설화수의 NO.1 에센스 - 설화수와 함께 힘차고 빛나는 새해를 시작하세요. | K7: 64 | L7: 343 | N7: 0 | O7: 윤조에센스 붉은 말의 해 에디션 | P7: 17 | R7: 0 | S7: Journey of Horse | T7: 16 | U7: 윤조에센스 말의 해 에디션 | V7: 14 | Z7: https://www.sulwhasoo.com/kr/ko/about-sulwhasoo/brand-news/archive/2026-lunar-new-year-limited-edition.html | AF7: 34834 | AG7: 9049 | AH7: 9049 | AI7: 3.5262415 | AK7: 112 | AL7: 37 | AM7: 3.027027 | AN7: 100 | AO7: Very Easy | AP7: 1.8169725 | AQ7: 0 | AR7: 5 | AT7: 4 | AU7: 1 | AV7: 0 | AW7: 0.61 | AX7: 17 | AY7: 12 | AZ7: 0 | BA7: 3 | BB7: 3 | BC7: 0 | BH7: af40aea8625600af065e7ac60c1b7ceb | BI7: 0.008 | BJ7: Thu, 05 Feb 2026 01:01:36 GMT | BN7: ko | BO7: 1.1 | BP7: 윤조에센스 붉은 말의 해 에디션 | 설화수 | BQ7: 붉은 말의 해를 맞아 리미티드로 탄생한 설화수의 NO.1 에센스 - 설화수와 함께 힘차고 빛나는 새해를 시작하세요. | BR7: website | BS7: 설화수 | BT7: https://www.sulwhasoo.com/kr/ko/about-sulwhasoo/brand-news/archive/__icsFiles/afieldfile/2025/12/26/251218_final_KR_2026LNY_thumbnail_1.jpg | BU7: https://www.sulwhasoo.com/kr/ko/about-sulwhasoo/brand-news/archive/2026-lunar-new-year-limited-edition.html | BV7: summary_large_image | BW7: 윤조에센스 붉은 말의 해 에디션 | 설화수 | BY7: https://www.sulwhasoo.com/kr/ko/about-sulwhasoo/brand-news/archive/2026-lunar-new-year-limited-edition.html | BZ7: schema.org | CD7: BreadcrumbList | CL7: https://www.sulwhasoo.com/kr/ko/about-sulwhasoo/brand-news/archive/2026-lunar-new-year-limited-edition.html | CM7: 2026-02-05 15:35:15
A8: https://www.sulwhasoo.com/kr/ko/about-sulwhasoo/brand-news/archive/archive.html | B8: text/html | C8: 200 | D8: OK | E8: Indexable | G8: 설화수 브랜드 뉴스 | 설화수 | H8: 16 | I8: 124 | J8: 설화수 브랜드 뉴스에서 최신 소식과 지난 활동을 만나보세요. 지속적인 혁신과 아름다움의 기록을 통해 설화수의 여정을 확인할 수 있습니다. | K8: 76 | L8: 401 | M8: 설화수, 설화수 아카이브, 설화수 브랜드 뉴스 | N8: 25 | O8: Archive | P8: 7 | R8: 0 | T8: 0 | V8: 0 | Z8: https://www.sulwhasoo.com/kr/ko/about-sulwhasoo/brand-news/archive/archive.html | AF8: 35679 | AG8: 9120 | AH8: 9120 | AI8: 3.553909 | AK8: 56 | AL8: 28 | AM8: 2 | AN8: 100 | AO8: Very Easy | AP8: 1.0172259 | AQ8: 0 | AR8: 5 | AT8: 4 | AU8: 1 | AV8: 0 | AW8: 0.61 | AX8: 23 | AY8: 18 | AZ8: 0 | BA8: 2 | BB8: 2 | BC8: 0 | BH8: e170bf7542e258fccfc490de07017168 | BI8: 0.01 | BJ8: Thu, 05 Feb 2026 01:01:22 GMT | BN8: ko | BO8: 1.1 | BP8: 설화수 브랜드 뉴스 | 설화수 | BQ8: 설화수 브랜드 뉴스에서 최신 소식과 지난 활동을 만나보세요. 지속적인 혁신과 아름다움의 기록을 통해 설화수의 여정을 확인할 수 있습니다. | BR8: website | BS8: 설화수 | BT8: https://www.sulwhasoo.com/kr/ko/resource/img/sulwhasoo-og-img_250304.jpg | BU8: https://www.sulwhasoo.com/kr/ko/about-sulwhasoo/brand-news/archive/archive.html | BV8: summary_large_image | BW8: 설화수 브랜드 뉴스 | 설화수 | BY8: https://www.sulwhasoo.com/kr/ko/about-sulwhasoo/brand-news/archive/archive.html | BZ8: schema.org | CD8: BreadcrumbList | CL8: https://www.sulwhasoo.com/kr/ko/about-sulwhasoo/brand-news/archive/archive.html | CM8: 2026-02-05 15:34:41
A9: https://www.sulwhasoo.com/kr/ko/about-sulwhasoo/brand-news/archive/concentrated-ginseng-renewing-cream-serum.html | B9: text/html | C9: 200 | D9: OK | E9: Indexable | G9: 자음생 크림&세럼 | 설화수 | H9: 15 | I9: 122 | J9: 단 48시간 안에 콜라겐 복구 무너진 피부의 기둥을 세워 단단하게 | K9: 36 | L9: 193 | N9: 0 | O9: 설화수 자음생크림 소개 | P9: 12 | R9: 0 | S9: 설화수 자음생크림&자음생세럼 | T9: 15 | V9: 0 | Z9: https://www.sulwhasoo.com/kr/ko/about-sulwhasoo/brand-news/archive/concentrated-ginseng-renewing-cream-serum.html | AF9: 55661 | AG9: 13029 | AH9: 13029 | AI9: 5.0771798 | AK9: 455 | AL9: 145 | AM9: 3.137931 | AN9: 100 | AO9: Very Easy | AP9: 4.6122708 | AQ9: 0 | AR9: 5 | AT9: 4 | AU9: 1 | AV9: 0 | AW9: 0.61 | AX9: 18 | AY9: 13 | AZ9: 0 | BA9: 6 | BB9: 4 | BC9: 0 | BH9: fd26f0a07efcd7386bddb7eeaa425db4 | BI9: 0.007 | BJ9: Thu, 05 Feb 2026 01:01:36 GMT | BN9: ko | BO9: 1.1 | BP9: 자음생 크림&세럼 | 설화수 | BQ9: 단 48시간 안에 콜라겐 복구 무너진 피부의 기둥을 세워 단단하게 | BR9: website | BS9: 설화수 | BT9: https://www.sulwhasoo.com/kr/ko/about-sulwhasoo/brand-news/archive/__icsFiles/afieldfile/2024/03/20/240319_final_KR_BRAND-NEWS_thumbnail_08_3.jpg | BU9: https://www.sulwhasoo.com/kr/ko/about-sulwhasoo/brand-news/archive/concentrated-ginseng-renewing-cream-serum.html | BV9: summary_large_image | BW9: 자음생 크림&세럼 | 설화수 | BY9: https://www.sulwhasoo.com/kr/ko/about-sulwhasoo/brand-news/archive/concentrated-ginseng-renewing-cream-serum.html | BZ9: schema.org | CD9: BreadcrumbList | CL9: https://www.sulwhasoo.com/kr/ko/about-sulwhasoo/brand-news/archive/concentrated-ginseng-renewing-cream-serum.html | CM9: 2026-02-05 15:34:53
A10: https://www.sulwhasoo.com/kr/ko/about-sulwhasoo/brand-news/archive/culture-project.html | B10: text/html | C10: 200 | D10: OK | E10: Indexable | G10: 내 손으로 알리는 한국 문화 – 컬처프로젝트 2.0 모집 | 설화수 | H10: 37 | I10: 293 | J10: 전통의 아름다움을 알리는 설화수의 문화 프로젝트. 민화를 현대적으로 재해석해 창작하고, 설화수와 함께 전시까지 경험해보세요. | K10: 69 | L10: 368 | N10: 0 | O10: We Create Culture 우리가 직접 만들고 알려나가는 한국의 문화, 설화수 컬처프로젝트 | P10: 53 | R10: 0 | S10: 설화수 컬처프로젝트란? | T10: 12 | U10: 1. 주요활동 | V10: 7 | Z10: https://www.sulwhasoo.com/kr/ko/about-sulwhasoo/brand-news/archive/culture-project.html | AF10: 61251 | AG10: 13424 | AH10: 13424 | AI10: 5.2311046 | AK10: 640 | AL10: 150 | AM10: 4.2666667 | AN10: 100 | AO10: Very Easy | AP10: 4.8207488 | AQ10: 0 | AR10: 5 | AT10: 4 | AU10: 1 | AV10: 0 | AW10: 0.61 | AX10: 17 | AY10: 12 | AZ10: 0 | BA10: 2 | BB10: 2 | BC10: 0 | BH10: b2b8a5fb38e71762ffee37e4fd91223 | BI10: 0.014 | BJ10: Thu, 05 Feb 2026 01:01:36 GMT | BN10: ko | BO10: 1.1 | BP10: 내 손으로 알리는 한국 문화 – 컬처프로젝트 2.0 모집 | 설화수 | BQ10: 전통의 아름다움을 알리는 설화수의 문화 프로젝트. 민화를 현대적으로 재해석해 창작하고, 설화수와 함께 전시까지 경험해보세요. | BR10: website | BS10: 설화수 | BT10: https://www.sulwhasoo.com/kr/ko/about-sulwhasoo/brand-news/archive/__icsFiles/afieldfile/2025/03/24/250324_final_KR_Culture-Project_Thumbnail_1.jpg | BU10: https://www.sulwhasoo.com/kr/ko/about-sulwhasoo/brand-news/archive/culture-project.html | BV10: summary_large_image | BW10: 내 손으로 알리는 한국 문화 – 컬처프로젝트 2.0 모집 | 설화수 | BY10: https://www.sulwhasoo.com/kr/ko/about-sulwhasoo/brand-news/archive/culture-project.html | BZ10: schema.org | CD10: BreadcrumbList | CL10: https://www.sulwhasoo.com/kr/ko/about-sulwhasoo/brand-news/archive/culture-project.html | CM10: 2026-02-05 15:35:47
A11: https://www.sulwhasoo.com/kr/ko/about-sulwhasoo/brand-news/archive/first-care-activating-serum-pop-up.html | B11: text/html | C11: 200 | D11: OK | E11: Indexable | G11: 윤조에센스 팝업스토어 | 설화수 | H11: 17 | I11: 137 | J11: FIRST CARE ACTIVATING SERUM | K11: 27 | L11: 207 | N11: 0 | O11: First Care Activating Serum Pop-up Store | P11: 40 | R11: 0 | T11: 0 | V11: 0 | Z11: https://www.sulwhasoo.com/kr/ko/about-sulwhasoo/brand-news/archive/first-care-activating-serum-pop-up.html | AF11: 30799 | AG11: 8612 | AH11: 8612 | AI11: 3.35595 | AK11: 77 | AL11: 34 | AM11: 2.2647059 | AN11: 100 | AO11: Very Easy | AP11: 1.5408008 | AQ11: 0 | AR11: 5 | AT11: 4 | AU11: 1 | AV11: 0 | AW11: 0.61 | AX11: 16 | AY11: 11 | AZ11: 0 | BA11: 2 | BB11: 2 | BC11: 0 | BH11: 8ea890ffa6a65f6dc9a08714d5f336f9 | BI11: 0.006 | BJ11: Thu, 05 Feb 2026 01:01:36 GMT | BN11: ko | BO11: 1.1 | BP11: 윤조에센스 팝업스토어 | 설화수 | BQ11: FIRST CARE ACTIVATING SERUM | BR11: website | BS11: 설화수 | BT11: https://www.sulwhasoo.com/kr/ko/about-sulwhasoo/brand-news/archive/__icsFiles/afieldfile/2025/03/31/250327_final_KR_first-care-activating-serum-pop-up_main_Thumbnail_PC_1.jpg | BU11: https://www.sulwhasoo.com/kr/ko/about-sulwhasoo/brand-news/archive/first-care-activating-serum-pop-up.html | BV11: summary_large_image | BW11: 윤조에센스 팝업스토어 | 설화수 | BY11: https://www.sulwhasoo.com/kr/ko/about-sulwhasoo/brand-news/archive/first-care-activating-serum-pop-up.html | BZ11: schema.org | CD11: BreadcrumbList | CL11: https://www.sulwhasoo.com/kr/ko/about-sulwhasoo/brand-news/archive/first-care-activating-serum-pop-up.html | CM11: 2026-02-05 15:34:58
A12: https://www.sulwhasoo.com/kr/ko/about-sulwhasoo/brand-news/archive/holistic-scanner-service.html | B12: text/html | C12: 200 | D12: OK | E12: Indexable | G12: 홀리스틱 스캐너 서비스 | 설화수 | H12: 18 | I12: 142 | J12: 피부 근본의 힘, '자생력'을 강화하여 노화 근본부터 케어하는 설화수 홀리스틱 피부 진단 서비스를 특별한 혜택과 함께 만나보세요. | K12: 72 | L12: 371 | N12: 0 | O12: 홀리스틱 스캐너 서비스 | P12: 12 | R12: 0 | S12: 서비스 체험 고객 대상 특별 이벤트 | T12: 19 | U12: 체험 후 제품 구매 시 프로모션 | V12: 17 | Z12: https://www.sulwhasoo.com/kr/ko/about-sulwhasoo/brand-news/archive/holistic-scanner-service.html | AF12: 56736 | AG12: 12343 | AH12: 12343 | AI12: 4.8098573 | AK12: 162 | AL12: 66 | AM12: 2.4545455 | AN12: 100 | AO12: Very Easy | AP12: 1.472908 | AQ12: 0 | AR12: 5 | AT12: 4 | AU12: 1 | AV12: 0 | AW12: 0.61 | AX12: 16 | AY12: 11 | AZ12: 0 | BA12: 5 | BB12: 5 | BC12: 0 | BH12: 56a911740d9a2a329e376867c28ca6f | BI12: 0.006 | BJ12: Thu, 05 Feb 2026 01:01:36 GMT | BN12: ko | BO12: 1.1 | BP12: 홀리스틱 스캐너 서비스 | 설화수 | BQ12: 피부 근본의 힘, '자생력'을 강화하여 노화 근본부터 케어하는 설화수 홀리스틱 피부 진단 서비스를 특별한 혜택과 함께 만나보세요. | BR12: website | BS12: 설화수 | BT12: https://www.sulwhasoo.com/kr/ko/about-sulwhasoo/brand-news/archive/__icsFiles/afieldfile/2025/11/07/251106_final_KR_holisticscanner_thumbnail_1.jpg | BU12: https://www.sulwhasoo.com/kr/ko/about-sulwhasoo/brand-news/archive/holistic-scanner-service.html | BV12: summary_large_image | BW12: 홀리스틱 스캐너 서비스 | 설화수 | BY12: https://www.sulwhasoo.com/kr/ko/about-sulwhasoo/brand-news/archive/holistic-scanner-service.html | BZ12: schema.org | CD12: BreadcrumbList | CL12: https://www.sulwhasoo.com/kr/ko/about-sulwhasoo/brand-news/archive/holistic-scanner-service.html | CM12: 2026-02-05 15:34:52
A13: https://www.sulwhasoo.com/kr/ko/about-sulwhasoo/brand-news/archive/insamjang-pop-up-store.html | B13: text/html | C13: 200 | D13: OK | E13: Indexable | G13: 인삼장 팝업스토어 | 설화수 | H13: 15 | I13: 119 | J13: 인삼 헤리티지의 현대적인 재해석 | K13: 17 | L13: 93 | N13: 0 | P13: 0 | R13: 0 | T13: 0 | V13: 0 | Z13: https://www.sulwhasoo.com/kr/ko/about-sulwhasoo/brand-news/archive/insamjang-pop-up-store.html | AF13: 32589 | AG13: 8980 | AH13: 8980 | AI13: 3.4993533 | AK13: 101 | AL13: 46 | AM13: 2.1956522 | AN13: 100 | AO13: Very Easy | AP13: 1.7215109 | AQ13: 0 | AR13: 5 | AT13: 4 | AU13: 1 | AV13: 0 | AW13: 0.61 | AX13: 16 | AY13: 11 | AZ13: 0 | BA13: 4 | BB13: 4 | BC13: 0 | BH13: 43f8bda65cfa30bf8709396c4fb28d66 | BI13: 0.008 | BJ13: Thu, 05 Feb 2026 01:01:36 GMT | BN13: ko | BO13: 1.1 | BP13: 인삼장 팝업스토어 | 설화수 | BQ13: 인삼 헤리티지의 현대적인 재해석 | BR13: website | BS13: 설화수 | BT13: https://www.sulwhasoo.com/kr/ko/about-sulwhasoo/brand-news/archive/__icsFiles/afieldfile/2024/03/28/240327_final_KR_insamjang-pop-up-store_thumbnail_pc_1.jpg | BU13: https://www.sulwhasoo.com/kr/ko/about-sulwhasoo/brand-news/archive/insamjang-pop-up-store.html | BV13: summary_large_image | BW13: 인삼장 팝업스토어 | 설화수 | BY13: https://www.sulwhasoo.com/kr/ko/about-sulwhasoo/brand-news/archive/insamjang-pop-up-store.html | BZ13: schema.org | CD13: BreadcrumbList | CL13: https://www.sulwhasoo.com/kr/ko/about-sulwhasoo/brand-news/archive/insamjang-pop-up-store.html | CM13: 2026-02-05 15:34:41
A14: https://www.sulwhasoo.com/kr/ko/about-sulwhasoo/brand-news/archive/lumiwise-brightening-ampoule-serum.html | B14: text/html | C14: 200 | D14: OK | E14: Indexable | G14: 설화수 자정앰플세럼 – NEW 브라이트닝 솔루션 | 설화수 | H14: 32 | I14: 276 | J14: 한 순간이 아닌 한결같이 이어지는 맑고 투명한 피부를 위해 설화수가 제시하는 NEW 브라이트닝 솔루션 자정앰플세럼을 만나보세요. | K14: 71 | L14: 391 | N14: 0 | O14: 다시 짙어지지 않고* 맑게 이어지는 피부 자정앰플세럼 | P14: 29 | R14: 0 | S14: 노화로 인한 칙칙함을 개선하는 설화수만의 브라이트닝 솔루션 | T14: 32 | U14: 자정앰플세럼 | V14: 6 | Z14: https://www.sulwhasoo.com/kr/ko/about-sulwhasoo/brand-news/archive/lumiwise-brightening-ampoule-serum.html | AF14: 89981 | AG14: 15626 | AH14: 15626 | AI14: 6.0891866 | AK14: 408 | AL14: 117 | AM14: 3.4871795 | AN14: 100 | AO14: Very Easy | AP14: 2.0814426 | AQ14: 0 | AR14: 5 | AT14: 5 | AU14: 2 | AV14: 0 | AW14: 1.21 | AX14: 21 | AY14: 16 | AZ14: 0 | BA14: 2 | BB14: 2 | BC14: 0 | BH14: 6b3875cb4dd263b11a4170d2dbbbac36 | BI14: 0.007 | BJ14: Thu, 05 Feb 2026 01:01:36 GMT | BN14: ko | BO14: 1.1 | BP14: 설화수 자정앰플세럼 – NEW 브라이트닝 솔루션 | 설화수 | BQ14: 한 순간이 아닌 한결같이 이어지는 맑고 투명한 피부를 위해 설화수가 제시하는 NEW 브라이트닝 솔루션 자정앰플세럼을 만나보세요. | BR14: website | BS14: 설화수 | BT14: https://www.sulwhasoo.com/kr/ko/about-sulwhasoo/brand-news/archive/__icsFiles/afieldfile/2026/01/28/260121_final_KR_lumiwisebrighteningampouleserum_thumbnail_1.jpg | BU14: https://www.sulwhasoo.com/kr/ko/about-sulwhasoo/brand-news/archive/lumiwise-brightening-ampoule-serum.html | BV14: summary_large_image | BW14: 설화수 자정앰플세럼 – NEW 브라이트닝 솔루션 | 설화수 | BY14: https://www.sulwhasoo.com/kr/ko/about-sulwhasoo/brand-news/archive/lumiwise-brightening-ampoule-serum.html | BZ14: schema.org | CD14: BreadcrumbList | CL14: https://www.sulwhasoo.com/kr/ko/about-sulwhasoo/brand-news/archive/lumiwise-brightening-ampoule-serum.html | CM14: 2026-02-05 15:34:59
A15: https://www.sulwhasoo.com/kr/ko/about-sulwhasoo/brand-news/archive/mothers-day-campaign.html | B15: text/html | C15: 200 | D15: OK | E15: Indexable | G15: Mother’s day | 설화수 | H15: 18 | I15: 156 | J15: 함께 했던 순간들 보다 더 언제나 늘 함께 해 | K15: 25 | L15: 126 | N15: 0 | P15: 0 | R15: 0 | T15: 0 | V15: 0 | Z15: https://www.sulwhasoo.com/kr/ko/about-sulwhasoo/brand-news/archive/mothers-day-campaign.html | AF15: 62976 | AG15: 14944 | AH15: 14944 | AI15: 5.8234228 | AK15: 792 | AL15: 176 | AM15: 4.5 | AN15: 100 | AO15: Very Easy | AP15: 6.3172579 | AQ15: 0 | AR15: 5 | AT15: 4 | AU15: 1 | AV15: 0 | AW15: 0.61 | AX15: 16 | AY15: 11 | AZ15: 0 | BA15: 5 | BB15: 5 | BC15: 0 | BH15: dc250587ea139c143fc1277f2fc1c7db | BI15: 0.007 | BJ15: Thu, 05 Feb 2026 01:01:36 GMT | BN15: ko | BO15: 1.1 | BP15: Mother’s day | 설화수 | BQ15: 함께 했던 순간들 보다 더 언제나 늘 함께 해 | BR15: website | BS15: 설화수 | BT15: https://www.sulwhasoo.com/kr/ko/about-sulwhasoo/brand-news/archive/__icsFiles/afieldfile/2024/04/12/240409_final_KR_MOTHERS-DAY-CAMPAIGN_thumbnail_1.jpg | BU15: https://www.sulwhasoo.com/kr/ko/about-sulwhasoo/brand-news/archive/mothers-day-campaign.html | BV15: summary_large_image | BW15: Mother’s day | 설화수 | BY15: https://www.sulwhasoo.com/kr/ko/about-sulwhasoo/brand-news/archive/mothers-day-campaign.html | BZ15: schema.org | CD15: BreadcrumbList | CL15: https://www.sulwhasoo.com/kr/ko/about-sulwhasoo/brand-news/archive/mothers-day-campaign.html | CM15: 2026-02-05 15:35:54
A16: https://www.sulwhasoo.com/kr/ko/about-sulwhasoo/brand-news/archive/news/news.html | B16: text/html | C16: 200 | D16: OK | E16: Indexable | G16: 브랜드 뉴스 - News | 설화수 | H16: 20 | I16: 158 | J16: 브랜드 뉴스의 News 목록을 보실 수 있는 페이지입니다. | K16: 32 | L16: 180 | N16: 0 | O16: Archive | P16: 7 | R16: 0 | T16: 0 | V16: 0 | Z16: https://www.sulwhasoo.com/kr/ko/about-sulwhasoo/brand-news/archive/news/news.html | AF16: 34992 | AG16: 9044 | AH16: 9044 | AI16: 3.5242931 | AK16: 54 | AL16: 27 | AM16: 2 | AN16: 100 | AO16: Very Easy | AP16: 1.0117993 | AQ16: 0 | AR16: 6 | AT16: 7 | AU16: 3 | AV16: 0 | AW16: 1.82 | AX16: 22 | AY16: 16 | AZ16: 0 | BA16: 2 | BB16: 2 | BC16: 0 | BH16: 1b42848ebe449cc4bfbb3fa027d53862 | BI16: 0.008 | BJ16: Mon, 12 Jan 2026 06:36:00 GMT | BN16: ko | BO16: 1.1 | BP16: 브랜드 뉴스 - News | 설화수 | BQ16: 브랜드 뉴스의 News 목록을 보실 수 있는 페이지입니다. | BR16: website | BS16: 설화수 | BT16: https://www.sulwhasoo.com/kr/ko/resource/img/sulwhasoo-og-img_250304.jpg | BU16: https://www.sulwhasoo.com/kr/ko/about-sulwhasoo/brand-news/archive/news/news.html | BV16: summary_large_image | BW16: 브랜드 뉴스 - News | 설화수 | BY16: https://www.sulwhasoo.com/kr/ko/about-sulwhasoo/brand-news/archive/news/news.html | BZ16: schema.org | CD16: BreadcrumbList | CL16: https://www.sulwhasoo.com/kr/ko/about-sulwhasoo/brand-news/archive/news/news.html | CM16: 2026-02-05 15:34:48
A17: https://www.sulwhasoo.com/kr/ko/about-sulwhasoo/brand-news/archive/our_product/our_product.html | B17: text/html | C17: 200 | D17: OK | E17: Indexable | G17: 브랜드 뉴스 - Our Product | 설화수 | H17: 26 | I17: 215 | J17: 브랜드 뉴스의 Our Product 목록을 보실 수 있는 페이지입니다. | K17: 39 | L17: 221 | N17: 0 | O17: Archive | P17: 7 | R17: 0 | T17: 0 | V17: 0 | Z17: https://www.sulwhasoo.com/kr/ko/about-sulwhasoo/brand-news/archive/our_product/our_product.html | AF17: 35322 | AG17: 9052 | AH17: 9052 | AI17: 3.5274105 | AK17: 54 | AL17: 27 | AM17: 2 | AN17: 100 | AO17: Very Easy | AP17: 1.0020449 | AQ17: 0 | AR17: 6 | AT17: 7 | AU17: 3 | AV17: 0 | AW17: 1.82 | AX17: 22 | AY17: 16 | AZ17: 0 | BA17: 2 | BB17: 2 | BC17: 0 | BH17: 6cf354f62b67b33d0060ba0830c898f0 | BI17: 0.008 | BJ17: Mon, 12 Jan 2026 06:36:06 GMT | BN17: ko | BO17: 1.1 | BP17: 브랜드 뉴스 - Our Product | 설화수 | BQ17: 브랜드 뉴스의 Our Product 목록을 보실 수 있는 페이지입니다. | BR17: website | BS17: 설화수 | BT17: https://www.sulwhasoo.com/kr/ko/resource/img/sulwhasoo-og-img_250304.jpg | BU17: https://www.sulwhasoo.com/kr/ko/about-sulwhasoo/brand-news/archive/our_product/our_product.html | BV17: summary_large_image | BW17: 브랜드 뉴스 - Our Product | 설화수 | BY17: https://www.sulwhasoo.com/kr/ko/about-sulwhasoo/brand-news/archive/our_product/our_product.html | BZ17: schema.org | CD17: BreadcrumbList | CL17: https://www.sulwhasoo.com/kr/ko/about-sulwhasoo/brand-news/archive/our_product/our_product.html | CM17: 2026-02-05 15:34:46
A18: https://www.sulwhasoo.com/kr/ko/about-sulwhasoo/brand-story/brand-story.html | B18: text/html | C18: 200 | D18: OK | E18: Indexable | G18: 설화수 브랜드 스토리, 진정한 아름다움을 향한 설화수의 여정 | 설화수 | H18: 40 | I18: 306 | J18: 설화수는 전통의 지혜와 현대 기술을 융합하여 피부 본연의 자생력을 깨우고 윤기 있는 피부를 선사합니다. 설화수의 여정을 만나보세요. | K18: 73 | L18: 386 | N18: 0 | O18: 시간의 흐름에 지지 않는 아름다움 홀리스틱 뷰티 | P18: 26 | R18: 0 | S18: 집념의 60년 연구, 피부 장수를 위한 인삼 | T18: 24 | U18: 5종 식물 원료 조합의 시너지 피부 능력을 키우는 자음단® | V18: 32 | Z18: https://www.sulwhasoo.com/kr/ko/about-sulwhasoo/brand-story/brand-story.html | AF18: 54403 | AG18: 10682 | AH18: 10682 | AI18: 4.1625938 | AK18: 422 | AL18: 87 | AM18: 4.8505747 | AN18: 100 | AO18: Very Easy | AP18: 3.5965707 | AQ18: 0 | AR18: 4 | AT18: 4 | AU18: 1 | AV18: 0 | AW18: 0.61 | AX18: 16 | AY18: 11 | AZ18: 0 | BA18: 2 | BB18: 2 | BC18: 0 | BH18: d14df39dc5a8af20d6caf2e768aaf79a | BI18: 0.006 | BJ18: Mon, 12 Jan 2026 06:35:58 GMT | BN18: ko | BO18: 1.1 | BP18: 설화수 브랜드 스토리, 진정한 아름다움을 향한 설화수의 여정 | 설화수 | BQ18: 설화수는 전통의 지혜와 현대 기술을 융합하여 피부 본연의 자생력을 깨우고 윤기 있는 피부를 선사합니다. 설화수의 여정을 만나보세요. | BR18: website | BS18: 설화수 | BT18: https://www.sulwhasoo.com/kr/ko/resource/img/sulwhasoo-og-img_250304.jpg | BU18: https://www.sulwhasoo.com/kr/ko/about-sulwhasoo/brand-story/brand-story.html | BV18: summary_large_image | BW18: 설화수 브랜드 스토리, 진정한 아름다움을 향한 설화수의 여정 | 설화수 | BY18: https://www.sulwhasoo.com/kr/ko/about-sulwhasoo/brand-story/brand-story.html | BZ18: schema.org | CD18: BreadcrumbList | CL18: https://www.sulwhasoo.com/kr/ko/about-sulwhasoo/brand-story/brand-story.html | CM18: 2026-02-05 15:35:46
A19: https://www.sulwhasoo.com/kr/ko/about-sulwhasoo/brand-sustainability/anti-counterfeit/anti-counterfeit.html | B19: text/html | C19: 200 | D19: OK | E19: Indexable | H19: 0 | I19: 0 | K19: 0 | L19: 0 | N19: 0 | O19: 진정한 아름다움을 지키는 설화수의 여정에 함께해 주세요 | P19: 30 | R19: 0 | S19: 설화수의 위조품 근절 노력 | T19: 14 | U19: 당신의 현명한 선택이 진정한 아름다움을 완성합니다. | V19: 28 | Z19: https://www.sulwhasoo.com/kr/ko/about-sulwhasoo/brand-sustainability/anti-counterfeit/anti-counterfeit.html | AF19: 33414 | AG19: 8798 | AH19: 8798 | AI19: 3.428431 | AK19: 443 | AL19: 95 | AM19: 4.6631579 | AN19: 100 | AO19: Very Easy | AP19: 6.6241155 | AQ19: 0 | AR19: 5 | AT19: 4 | AU19: 1 | AV19: 0 | AW19: 0.61 | AX19: 17 | AY19: 11 | AZ19: 0 | BA19: 2 | BB19: 2 | BC19: 0 | BH19: 75dd0984461fc619e1ddd36bb2faff0e | BI19: 0.007 | BJ19: Mon, 12 Jan 2026 06:36:00 GMT | BN19: ko | BO19: 1.1 | BZ19: schema.org | CD19: BreadcrumbList | CL19: https://www.sulwhasoo.com/kr/ko/about-sulwhasoo/brand-sustainability/anti-counterfeit/anti-counterfeit.html | CM19: 2026-02-05 15:35:06
A20: https://www.sulwhasoo.com/kr/ko/about-sulwhasoo/brand-sustainability/index.html | B20: text/html | C20: 200 | D20: OK | E20: Indexable | H20: 0 | I20: 0 | K20: 0 | L20: 0 | N20: 0 | P20: 0 | R20: 0 | T20: 0 | V20: 0 | AF20: 130 | AG20: 109 | AH20: 109 | AI20: 0.042475447 | AK20: 0 | AP20: 0 | AQ20: 0 | AR20: 4 | AT20: 0 | AU20: 0 | AV20: 0 | AW20: 0 | AX20: 0 | AY20: 0 | AZ20: 0 | BA20: 0 | BB20: 0 | BC20: 0 | BH20: abf42f9169015331b4562cd5ef7a4e9a | BI20: 0.011 | BJ20: Mon, 12 Jan 2026 06:35:58 GMT | BO20: 1.1 | CL20: https://www.sulwhasoo.com/kr/ko/about-sulwhasoo/brand-sustainability/index.html | CM20: 2026-02-05 15:35:57
A21: https://www.sulwhasoo.com/kr/ko/about-sulwhasoo/brand-sustainability/sustainability/brand-sustainability.html | B21: text/html | C21: 200 | D21: OK | E21: Indexable | H21: 0 | I21: 0 | K21: 0 | L21: 0 | N21: 0 | O21: 설화수 ESG | P21: 7 | R21: 0 | S21: 지속 가능한 미래를 위한 설화수의 약속 | T21: 21 | V21: 0 | Z21: https://www.sulwhasoo.com/kr/ko/about-sulwhasoo/brand-sustainability/sustainability/brand-sustainability.html | AF21: 53695 | AG21: 11759 | AH21: 11759 | AI21: 4.5822824 | AK21: 559 | AL21: 115 | AM21: 4.8608696 | AN21: 100 | AO21: Very Easy | AP21: 5.1842623 | AQ21: 0 | AR21: 5 | AT21: 4 | AU21: 1 | AV21: 0 | AW21: 0.61 | AX21: 17 | AY21: 12 | AZ21: 0 | BA21: 2 | BB21: 2 | BC21: 0 | BH21: ab3fc91609a41bda08967a562a6c7940 | BI21: 0.006 | BJ21: Mon, 12 Jan 2026 06:36:02 GMT | BN21: ko | BO21: 1.1 | BZ21: schema.org | CD21: BreadcrumbList | CL21: https://www.sulwhasoo.com/kr/ko/about-sulwhasoo/brand-sustainability/sustainability/brand-sustainability.html | CM21: 2026-02-05 15:35:22
A22: https://www.sulwhasoo.com/kr/ko/about-sulwhasoo/classic-luxury-set/classic-luxury-set.html | B22: text/html | C22: 200 | D22: OK | E22: Indexable | G22: 설화수 명작컬렉션 | 설화수 | H22: 15 | I22: 119 | J22: 설화수의 명작컬렉션을 소개합니다. | Sulwhasoo | K22: 30 | L22: 178 | M22: 설화수, 시즌스페셜, 명작 컬렉션 | N22: 18 | O22: 명작 컬렉션 | P22: 6 | R22: 0 | T22: 0 | V22: 0 | Z22: https://www.sulwhasoo.com/kr/ko/about-sulwhasoo/classic-luxury-set/classic-luxury-set.html | AF22: 27318 | AG22: 7222 | AH22: 7222 | AI22: 2.8142906 | AK22: 47 | AL22: 22 | AM22: 2.1363636 | AN22: 100 | AO22: Very Easy | AP22: 1.2201715 | AQ22: 0 | AR22: 4 | AT22: 4 | AU22: 1 | AV22: 0 | AW22: 0.61 | AX22: 20 | AY22: 15 | AZ22: 0 | BA22: 2 | BB22: 2 | BC22: 0 | BH22: 4a13998ad2f028c0477c225c85bd2d74 | BI22: 0.007 | BJ22: Mon, 12 Jan 2026 06:36:00 GMT | BN22: ko | BO22: 1.1 | BP22: 설화수 명작컬렉션 | 설화수 | BQ22: 설화수의 명작컬렉션을 소개합니다. | Sulwhasoo | BR22: website | BS22: 설화수 | BT22: https://www.sulwhasoo.com/kr/ko/resource/img/sulwhasoo-og-img_250304.jpg | BU22: https://www.sulwhasoo.com/kr/ko/about-sulwhasoo/classic-luxury-set/classic-luxury-set.html | BV22: summary_large_image | BW22: 설화수 명작컬렉션 | 설화수 | BY22: https://www.sulwhasoo.com/kr/ko/about-sulwhasoo/classic-luxury-set/classic-luxury-set.html | BZ22: schema.org | CD22: BreadcrumbList | CL22: https://www.sulwhasoo.com/kr/ko/about-sulwhasoo/classic-luxury-set/classic-luxury-set.html | CM22: 2026-02-05 15:35:19
A23: https://www.sulwhasoo.com/kr/ko/about-sulwhasoo/culture/sws-culture.html | B23: text/html | C23: 200 | D23: OK | E23: Indexable | G23: 설화문화전 - 설화수 라운지 | 설화수 | H23: 21 | I23: 162 | J23: 설화 문화전은 한국 문화의 아름다운 가치를 현대적으로 재해석함으로써 한국의 미를 널리 알리는 설화수 문화 활동입니다. 설화 문화전 게시물 전체 보기 | Sulwhasoo | K23: 94 | L23: 511 | M23: 설화문화전, 한국의 미, 설화수 문화 메세나 | N23: 24 | O23: 설화 문화전 | P23: 6 | R23: 0 | S23: 창, 전통과 현대의 중첩 | T23: 13 | U23: 창, 전통과 현대의 중첩 | V23: 13 | Z23: https://www.sulwhasoo.com/kr/ko/about-sulwhasoo/culture/sws-culture.html | AF23: 38983 | AG23: 8245 | AH23: 8245 | AI23: 3.2129363 | AK23: 272 | AL23: 116 | AM23: 2.3448276 | AN23: 100 | AO23: Very Easy | AP23: 3.6290214 | AQ23: 0 | AR23: 4 | AT23: 4 | AU23: 1 | AV23: 0 | AW23: 0.61 | AX23: 28 | AY23: 23 | AZ23: 0 | BA23: 2 | BB23: 2 | BC23: 0 | BH23: a9852fae784cc7d72e0e9391a1dad81f | BI23: 0.007 | BJ23: Mon, 12 Jan 2026 06:36:04 GMT | BN23: ko | BO23: 1.1 | BP23: 설화문화전 - 설화수 라운지 | 설화수 | BQ23: 설화 문화전은 한국 문화의 아름다운 가치를 현대적으로 재해석함으로써 한국의 미를 널리 알리는 설화수 문화 활동입니다. 설화 문화전 게시물 전체 보기 | Sulwhasoo | BR23: website | BS23: 설화수 | BT23: https://www.sulwhasoo.com/kr/ko/resource/img/sulwhasoo-og-img_250304.jpg | BU23: https://www.sulwhasoo.com/kr/ko/about-sulwhasoo/culture/sws-culture.html | BV23: summary_large_image | BW23: 설화문화전 - 설화수 라운지 | 설화수 | BY23: https://www.sulwhasoo.com/kr/ko/about-sulwhasoo/culture/sws-culture.html | BZ23: schema.org | CD23: BreadcrumbList | CL23: https://www.sulwhasoo.com/kr/ko/about-sulwhasoo/culture/sws-culture.html | CM23: 2026-02-05 15:35:00
A24: https://www.sulwhasoo.com/kr/ko/about-sulwhasoo/culture-project/archive.html | B24: text/html | C24: 200 | D24: OK | E24: Indexable | G24: 아카이브 | 컬처프로젝트 | 설화수 | H24: 19 | I24: 147 | J24: 설화수 컬처프로젝트는 한국 전통 문화를 대학생들의 시각으로 재해석하여 동시대적 문화로 널리 알리기 위한 대학생 문화 후원 활동입니다. | K24: 74 | L24: 394 | N24: 0 | O24: 컬처 프로젝트 | P24: 7 | R24: 0 | S24: 민화 Minhwa | T24: 9 | U24: 각게수리 Gakgesuri | V24: 14 | Z24: https://www.sulwhasoo.com/kr/ko/about-sulwhasoo/culture-project/archive.html | AF24: 27053 | AG24: 7190 | AH24: 7190 | AI24: 2.8018208 | AK24: 89 | AL24: 30 | AM24: 2.9666667 | AN24: 100 | AO24: Very Easy | AP24: 1.9954013 | AQ24: 0 | AR24: 4 | AT24: 6 | AU24: 3 | AV24: 0 | AW24: 1.82 | AX24: 18 | AY24: 13 | AZ24: 0 | BA24: 2 | BB24: 2 | BC24: 0 | BH24: 8ac825dd6daab19359cc0ca85b47c840 | BI24: 0.006 | BJ24: Mon, 12 Jan 2026 06:36:00 GMT | BN24: ko | BO24: 1.1 | BP24: 아카이브 | 컬처프로젝트 | 설화수 | BQ24: 설화수 컬처프로젝트는 한국 전통 문화를 대학생들의 시각으로 재해석하여 동시대적 문화로 널리 알리기 위한 대학생 문화 후원 활동입니다. | BR24: website | BS24: 설화수 | BT24: https://www.sulwhasoo.com/kr/ko/meta/__icsFiles/afieldfile/2025/10/02/sulwhasoo-og-img_250304_1.jpg | BU24: https://www.sulwhasoo.com/kr/ko/about-sulwhasoo/culture-project/archive.html | BV24: summary_large_image | BW24: 아카이브 | 컬처프로젝트 | 설화수 | BY24: https://www.sulwhasoo.com/kr/ko/about-sulwhasoo/culture-project/archive.html | BZ24: schema.org | CD24: BreadcrumbList | CL24: https://www.sulwhasoo.com/kr/ko/about-sulwhasoo/culture-project/archive.html | CM24: 2026-02-05 15:35:02
A25: https://www.sulwhasoo.com/kr/ko/about-sulwhasoo/culture-project/season-one.html | B25: text/html | C25: 200 | D25: OK | E25: Non-Indexable | F25: Canonicalised | G25: 아카이브 | 컬처프로젝트 | 설화수 | H25: 19 | I25: 147 | J25: 설화수 컬처프로젝트는 한국 전통 문화를 대학생들의 시각으로 재해석하여 동시대적 문화로 널리 알리기 위한 대학생 문화 후원 활동입니다. | K25: 74 | L25: 394 | N25: 0 | O25: 설화수 컬쳐 프로젝트 SEASON ONE | P25: 22 | R25: 0 | T25: 0 | V25: 0 | Z25: https://www.sulwhasoo.com/kr/ko/about-sulwhasoo/culture-project/archive.html | AF25: 39217 | AG25: 8779 | AH25: 8779 | AI25: 3.4210271 | AK25: 204 | AL25: 54 | AM25: 3.7777778 | AN25: 100 | AO25: Very Easy | AP25: 2.9390254 | AQ25: 0 | AR25: 4 | AT25: 5 | AU25: 2 | AV25: 0 | AW25: 1.21 | AX25: 17 | AY25: 12 | AZ25: 0 | BA25: 2 | BB25: 2 | BC25: 0 | BH25: f12d4b2b9f35c2546f9d301924818195 | BI25: 0.007 | BJ25: Mon, 12 Jan 2026 06:36:00 GMT | BN25: ko | BO25: 1.1 | BP25: 아카이브 | 컬처프로젝트 | 설화수 | BQ25: 설화수 컬처프로젝트는 한국 전통 문화를 대학생들의 시각으로 재해석하여 동시대적 문화로 널리 알리기 위한 대학생 문화 후원 활동입니다. | BR25: website | BS25: 설화수 | BT25: https://www.sulwhasoo.com/kr/ko/meta/__icsFiles/afieldfile/2025/10/02/sulwhasoo-og-img_250304_1.jpg | BU25: https://www.sulwhasoo.com/kr/ko/about-sulwhasoo/culture-project/archive.html | BV25: summary_large_image | BW25: 아카이브 | 컬처프로젝트 | 설화수 | BY25: https://www.sulwhasoo.com/kr/ko/about-sulwhasoo/culture-project/archive.html | BZ25: schema.org | CD25: BreadcrumbList | CL25: https://www.sulwhasoo.com/kr/ko/about-sulwhasoo/culture-project/season-one.html | CM25: 2026-02-05 15:35:24
A26: https://www.sulwhasoo.com/kr/ko/about-sulwhasoo/culture-project/season-two.html | B26: text/html | C26: 200 | D26: OK | E26: Non-Indexable | F26: Canonicalised | G26: 아카이브 | 컬처프로젝트 | 설화수 | H26: 19 | I26: 147 | J26: 설화수 컬처프로젝트는 한국 전통 문화를 대학생들의 시각으로 재해석하여 동시대적 문화로 널리 알리기 위한 대학생 문화 후원 활동입니다. | K26: 74 | L26: 394 | N26: 0 | O26: 설화수 컬쳐 프로젝트 SEASON TWO | P26: 22 | R26: 0 | T26: 0 | V26: 0 | Z26: https://www.sulwhasoo.com/kr/ko/about-sulwhasoo/culture-project/archive.html | AF26: 72161 | AG26: 12546 | AH26: 12546 | AI26: 4.8889629 | AK26: 843 | AL26: 167 | AM26: 5.0479042 | AN26: 100 | AO26: Very Easy | AP26: 6.3074841 | AQ26: 0 | AR26: 4 | AT26: 5 | AU26: 2 | AV26: 0 | AW26: 1.21 | AX26: 17 | AY26: 12 | AZ26: 0 | BA26: 2 | BB26: 2 | BC26: 0 | BH26: 4c1f97a7f07fa4bb61ad0a473ff8590b | BI26: 0.008 | BJ26: Mon, 12 Jan 2026 06:36:00 GMT | BN26: ko | BO26: 1.1 | BP26: 아카이브 | 컬처프로젝트 | 설화수 | BQ26: 설화수 컬처프로젝트는 한국 전통 문화를 대학생들의 시각으로 재해석하여 동시대적 문화로 널리 알리기 위한 대학생 문화 후원 활동입니다. | BR26: website | BS26: 설화수 | BT26: https://www.sulwhasoo.com/kr/ko/meta/__icsFiles/afieldfile/2025/10/02/sulwhasoo-og-img_250304_1.jpg | BU26: https://www.sulwhasoo.com/kr/ko/about-sulwhasoo/culture-project/archive.html | BV26: summary_large_image | BW26: 아카이브 | 컬처프로젝트 | 설화수 | BY26: https://www.sulwhasoo.com/kr/ko/about-sulwhasoo/culture-project/archive.html | BZ26: schema.org | CD26: BreadcrumbList | CL26: https://www.sulwhasoo.com/kr/ko/about-sulwhasoo/culture-project/season-two.html | CM26: 2026-02-05 15:35:43
A27: https://www.sulwhasoo.com/kr/ko/about-sulwhasoo/salon-sulwhasoo/salon-sulwhasoo.html | B27: text/html | C27: 200 | D27: OK | E27: Indexable | G27: 살롱 설화수 | 설화수 | H27: 12 | I27: 92 | J27: <살롱설화수> 전통과 현대를 잇는 다양한 분야의 아티스트들과 소통하며 영감을 나누는 특별한 여정 | K27: 53 | L27: 287 | N27: 0 | O27: 살롱 설화수 | P27: 6 | R27: 0 | S27: Art & Heritage to life ‘Salon Sulwhasoo’ | T27: 40 | U27: Capturing the Beauty of Eastern & Western | V27: 41 | Z27: https://www.sulwhasoo.com/kr/ko/about-sulwhasoo/salon-sulwhasoo/salon-sulwhasoo.html | AF27: 85607 | AG27: 14654 | AH27: 14654 | AI27: 5.7104147 | AK27: 667 | AL27: 177 | AM27: 3.7683616 | AN27: 100 | AO27: Very Easy | AP27: 3.7431746 | AQ27: 0 | AR27: 4 | AT27: 4 | AU27: 1 | AV27: 0 | AW27: 0.61 | AX27: 16 | AY27: 11 | AZ27: 0 | BA27: 2 | BB27: 2 | BC27: 0 | BH27: 4353fa41180b35768d872cd41dd3e797 | BI27: 0.007 | BJ27: Mon, 12 Jan 2026 06:36:04 GMT | BN27: ko | BO27: 1.1 | BP27: 살롱 설화수 | 설화수 | BR27: website | BS27: 설화수 | BT27: https://www.sulwhasoo.com/kr/ko/meta/__icsFiles/afieldfile/2024/12/06/salon_og_v241126.png | BU27: https://www.sulwhasoo.com/kr/ko/about-sulwhasoo/salon-sulwhasoo/salon-sulwhasoo.html | BV27: summary_large_image | BW27: 살롱 설화수 | 설화수 | BY27: https://www.sulwhasoo.com/kr/ko/about-sulwhasoo/salon-sulwhasoo/salon-sulwhasoo.html | BZ27: schema.org | CD27: BreadcrumbList | CL27: https://www.sulwhasoo.com/kr/ko/about-sulwhasoo/salon-sulwhasoo/salon-sulwhasoo.html | CM27: 2026-02-05 15:34:56
A28: https://www.sulwhasoo.com/kr/ko/best/best-seller.html | B28: text/html | C28: 200 | D28: OK | E28: Indexable | G28: 설화수 베스트셀러 제품 | 설화수 | H28: 18 | I28: 142 | J28: 설화수에서 가장 사랑받는 베스트셀러 제품을 소개합니다. 설화수 스킨케어, 메이크업, 명작 컬렉션 및 남성 제품 베스트셀러 상품 | Sulwhasoo | K28: 82 | L28: 445 | M28: 설화수 베스트셀러 제품 | N28: 12 | O28: 베스트셀러 | P28: 5 | R28: 0 | S28: BEST SELLER | T28: 11 | V28: 0 | Z28: https://www.sulwhasoo.com/kr/ko/best/best-seller.html | AF28: 67861 | AG28: 10424 | AH28: 10424 | AI28: 4.0620556 | AK28: 253 | AL28: 103 | AM28: 2.4563107 | AN28: 100 | AO28: Very Easy | AP28: 1.906695 | AQ28: 0 | AR28: 3 | AT28: 5 | AU28: 2 | AV28: 0 | AW28: 1.21 | AX28: 20 | AY28: 13 | AZ28: 0 | BA28: 14 | BB28: 8 | BC28: 0 | BH28: 4a17bbb5e1f969d3088498754022319 | BI28: 0.007 | BJ28: Thu, 15 Jan 2026 04:16:50 GMT | BN28: ko | BO28: 1.1 | BP28: 설화수 베스트셀러 제품 | 설화수 | BQ28: 설화수에서 가장 사랑받는 베스트셀러 제품을 소개합니다. 설화수 스킨케어, 메이크업, 명작 컬렉션 및 남성 제품 베스트셀러 상품 | Sulwhasoo | BR28: website | BS28: 설화수 | BT28: https://www.sulwhasoo.com/kr/ko/resource/img/sulwhasoo-og-img_250304.jpg | BU28: https://www.sulwhasoo.com/kr/ko/best/best-seller.html | BV28: summary_large_image | BW28: 설화수 베스트셀러 제품 | 설화수 | BY28: https://www.sulwhasoo.com/kr/ko/best/best-seller.html | BZ28: schema.org | CD28: BreadcrumbList | CL28: https://www.sulwhasoo.com/kr/ko/best/best-seller.html | CM28: 2026-02-05 15:34:38
A29: https://www.sulwhasoo.com/kr/ko/concentrated-ginseng-rejuvenating/introduction.html | B29: text/html | C29: 200 | D29: OK | E29: Indexable | G29: 자음생크림 소개 - 독보적 인삼 헤리티지 | 설화수 | H29: 28 | I29: 217 | J29: 10년 연속 안티에이징 크림 1위. 60년간 끊임없는 진화를 거듭해온 자음생크림은 한 순간의 에이징 케어를 넘어 피부의 장수를 바라봅니다. | K29: 77 | L29: 417 | N29: 0 | O29: 설화수 자음생크림 | P29: 9 | R29: 0 | S29: 설화수 자음생크림 소개 영상 | T29: 15 | U29: 10년 연속 안티에이징 크림 1위* 자음생크림 | V29: 25 | Z29: https://www.sulwhasoo.com/kr/ko/concentrated-ginseng-rejuvenating/introduction.html | AF29: 67543 | AG29: 11376 | AH29: 11376 | AI29: 4.4330338 | AK29: 514 | AL29: 177 | AM29: 2.9039548 | AN29: 100 | AO29: Very Easy | AP29: 3.7515461 | AQ29: 0 | AR29: 3 | AT29: 5 | AU29: 2 | AV29: 0 | AW29: 1.21 | AX29: 23 | AY29: 18 | AZ29: 0 | BA29: 9 | BB29: 9 | BC29: 0 | BH29: ca1cbd9252e15bc217a14e39b7043a2 | BI29: 0.006 | BJ29: Mon, 12 Jan 2026 06:36:04 GMT | BN29: ko | BO29: 1.1 | BP29: 자음생크림 소개 - 독보적 인삼 헤리티지 | 설화수 | BQ29: 10년 연속 안티에이징 크림 1위. 60년간 끊임없는 진화를 거듭해온 자음생크림은 한 순간의 에이징 케어를 넘어 피부의 장수를 바라봅니다. | BR29: website | BS29: 설화수 | BT29: https://www.sulwhasoo.com/kr/ko/resource/img/sulwhasoo-og-img_250304.jpg | BU29: https://www.sulwhasoo.com/kr/ko/concentrated-ginseng-rejuvenating/introduction.html | BV29: summary_large_image | BW29: 자음생크림 소개 - 독보적 인삼 헤리티지 | 설화수 | BY29: https://www.sulwhasoo.com/kr/ko/concentrated-ginseng-rejuvenating/introduction.html | BZ29: schema.org | CD29: BreadcrumbList | CL29: https://www.sulwhasoo.com/kr/ko/concentrated-ginseng-rejuvenating/introduction.html | CM29: 2026-02-05 15:35:18
A30: https://www.sulwhasoo.com/kr/ko/coverpage/2023-holiday-collection/introduction.html | B30: text/html | C30: 200 | D30: OK | E30: Indexable | G30: 2023 설화수 홀리데이 컬렉션 | 설화수 | H30: 23 | I30: 191 | J30: 반짝이는 것들로 가득할 2023년 겨울에 설화수만의 아티스틱 한 터치로 특별함을 더했습니다. | K30: 51 | L30: 282 | N30: 0 | O30: SULWHASOO HOLIDAY COLLECTION 소개 | P30: 31 | R30: 0 | S30: HAPPY HOLIDAY 설화수 홀리데이 컬렉션 | T30: 26 | U30: 나의 첫 설화수 홀리데이 에디션 | V30: 17 | Z30: https://www.sulwhasoo.com/kr/ko/coverpage/2023-holiday-collection/introduction.html | AF30: 58418 | AG30: 11579 | AH30: 11579 | AI30: 4.5121395 | AK30: 539 | AL30: 158 | AM30: 3.4113924 | AN30: 100 | AO30: Very Easy | AP30: 4.5474248 | AQ30: 0 | AR30: 4 | AT30: 4 | AU30: 1 | AV30: 0 | AW30: 0.61 | AX30: 18 | AY30: 13 | AZ30: 0 | BA30: 4 | BB30: 4 | BC30: 0 | BH30: 69c9bc3761769a95b4ae8a955ee19ae2 | BI30: 0.01 | BJ30: Mon, 12 Jan 2026 06:36:02 GMT | BN30: ko | BO30: 1.1 | BP30: 2023 설화수 홀리데이 컬렉션 | 설화수 | BQ30: 반짝이는 것들로 가득할 2023년 겨울에 설화수만의 아티스틱 한 터치로 특별함을 더했습니다. | BR30: website | BS30: 설화수 | BT30: https://www.sulwhasoo.com/kr/ko/resource/img/sulwhasoo-og-img_250304.jpg | BU30: https://www.sulwhasoo.com/kr/ko/coverpage/2023-holiday-collection/introduction.html | BV30: summary_large_image | BW30: 2023 설화수 홀리데이 컬렉션 | 설화수 | BY30: https://www.sulwhasoo.com/kr/ko/coverpage/2023-holiday-collection/introduction.html | BZ30: schema.org | CD30: BreadcrumbList | CL30: https://www.sulwhasoo.com/kr/ko/coverpage/2023-holiday-collection/introduction.html | CM30: 2026-02-05 15:35:56
A31: https://www.sulwhasoo.com/kr/ko/coverpage/2024-lunar-new-year-limited-edition/introduction.html | B31: text/html | C31: 200 | D31: OK | E31: Indexable | G31: 2024 윤조에센스 용의 해 에디션 | 설화수 | H31: 25 | I31: 205 | J31: 용의 해를 맞아 리미티드로 탄생한 설화수의 NO.1 에센스, 윤조에센스 용의 해 에디션을 소개합니다. | K31: 56 | L31: 303 | N31: 0 | O31: 윤조에센스 용의 해 에디션 소개 | P31: 17 | R31: 0 | S31: HAPPY NEW YEAR FROM SULWHASOO 윤조에센스 용의 해 에디션 | T31: 44 | U31: 윤조에센스 용의 해 에디션 | V31: 14 | Z31: https://www.sulwhasoo.com/kr/ko/coverpage/2024-lunar-new-year-limited-edition/introduction.html | AF31: 45246 | AG31: 10440 | AH31: 10440 | AI31: 4.0682905 | AK31: 363 | AL31: 110 | AM31: 3.3 | AN31: 100 | AO31: Very Easy | AP31: 4.266789 | AQ31: 0 | AR31: 4 | AT31: 4 | AU31: 1 | AV31: 0 | AW31: 0.61 | AX31: 17 | AY31: 12 | AZ31: 0 | BA31: 3 | BB31: 3 | BC31: 0 | BH31: b22cdc6ab74743828b2b2c2d64442cbd | BI31: 0.031 | BJ31: Mon, 12 Jan 2026 06:36:02 GMT | BN31: ko | BO31: 1.1 | BP31: 2024 윤조에센스 용의 해 에디션 | 설화수 | BQ31: 용의 해를 맞아 리미티드로 탄생한 설화수의 NO.1 에센스, 윤조에센스 용의 해 에디션을 소개합니다. | BR31: website | BS31: 설화수 | BT31: https://www.sulwhasoo.com/kr/ko/resource/img/sulwhasoo-og-img_250304.jpg | BU31: https://www.sulwhasoo.com/kr/ko/coverpage/2024-lunar-new-year-limited-edition/introduction.html | BV31: summary_large_image | BW31: 2024 윤조에센스 용의 해 에디션 | 설화수 | BY31: https://www.sulwhasoo.com/kr/ko/coverpage/2024-lunar-new-year-limited-edition/introduction.html | BZ31: schema.org | CD31: BreadcrumbList | CL31: https://www.sulwhasoo.com/kr/ko/coverpage/2024-lunar-new-year-limited-edition/introduction.html | CM31: 2026-02-05 15:35:58
A32: https://www.sulwhasoo.com/kr/ko/coverpage/perfecting-cushion/introduction.html | B32: text/html | C32: 200 | D32: OK | E32: Indexable | G32: NEW 퍼펙팅 쿠션 & 퍼펙팅 쿠션 에어리 소개 | 설화수 | H32: 32 | I32: 267 | J32: 설화수 대표 윤조에센스* 성분으로 메이크업과 스킨케어 효과를 동시에 구현한 스킨케어링 메이크업 쿠션을 소개합니다. | K32: 63 | L32: 340 | N32: 0 | O32: Sulwhasoo Perfecting Cushion 소개 | P32: 31 | R32: 0 | S32: Sulwhasoo Perfecting Cushion 특징 | T32: 31 | U32: 나에게 딱 맞는 퍼펙팅 쿠션을 선택해보세요. | V32: 24 | Z32: https://www.sulwhasoo.com/kr/ko/coverpage/perfecting-cushion/introduction.html | AF32: 88207 | AG32: 12317 | AH32: 12317 | AI32: 4.7997255 | AK32: 530 | AL32: 167 | AM32: 3.1736527 | AN32: 100 | AO32: Very Easy | AP32: 3.3304021 | AQ32: 0 | AR32: 4 | AT32: 4 | AU32: 1 | AV32: 0 | AW32: 0.61 | AX32: 18 | AY32: 13 | AZ32: 0 | BA32: 4 | BB32: 4 | BC32: 0 | BH32: 118de7c49d4b26543c62e466859a2b1e | BI32: 0.008 | BJ32: Mon, 12 Jan 2026 06:36:00 GMT | BN32: ko | BO32: 1.1 | BP32: NEW 퍼펙팅 쿠션 & 퍼펙팅 쿠션 에어리 소개 | 설화수 | BQ32: 설화수 대표 윤조에센스* 성분으로 메이크업과 스킨케어 효과를 동시에 구현한 스킨케어링 메이크업 쿠션을 소개합니다. | BR32: website | BS32: 설화수 | BT32: https://www.sulwhasoo.com/kr/ko/resource/img/sulwhasoo-og-img_250304.jpg | BU32: https://www.sulwhasoo.com/kr/ko/coverpage/perfecting-cushion/introduction.html | BV32: summary_large_image | BW32: NEW 퍼펙팅 쿠션 & 퍼펙팅 쿠션 에어리 소개 | 설화수 | BY32: https://www.sulwhasoo.com/kr/ko/coverpage/perfecting-cushion/introduction.html | BZ32: schema.org | CD32: BreadcrumbList | CL32: https://www.sulwhasoo.com/kr/ko/coverpage/perfecting-cushion/introduction.html | CM32: 2026-02-05 15:35:49
A33: https://www.sulwhasoo.com/kr/ko/first-care-activating/first-care-activating-serum-vi.html | B33: text/html | C33: 200 | D33: OK | E33: Non-Indexable | F33: Canonicalised | G33: 윤조에센스 6세대 소개 | 설화수 | H33: 18 | I33: 144 | J33: 피부 능력을 깨우고 피부 건강을 전반적으로 개선하여 건강한 윤기를 선사하는 FIRST STEP, 설화수 윤조에센스 6세대를 소개합니다. | K33: 75 | L33: 418 | N33: 0 | O33: 정체된 피부 흐름을 되살려, 다시 윤빛 도는 피부 설화수 윤조에센스 6세대 FIRST CARE ACTIVATING SERUM VI | P33: 72 | R33: 0 | S33: 시대와 세대를 뛰어넘는 안티에이징 에센스 설화수 베스트셀러1) 윤조에센스 | T33: 40 | U33: 윤조에센스 6세대 | V33: 9 | Z33: https://www.sulwhasoo.com/kr/ko/about-sulwhasoo/brand-news/archive/2025-first-care-activating-serum-vi-introduction.html | AF33: 42382 | AG33: 9461 | AH33: 9461 | AI33: 3.6867909 | AK33: 360 | AL33: 126 | AM33: 2.8571429 | AN33: 100 | AO33: Very Easy | AP33: 4.290771 | AQ33: 0 | AR33: 3 | AT33: 4 | AU33: 1 | AV33: 0 | AW33: 0.61 | AX33: 17 | AY33: 12 | AZ33: 0 | BA33: 3 | BB33: 3 | BC33: 0 | BH33: 55e52a99653c903705b91ea1b79d207f | BI33: 0.023 | BJ33: Mon, 12 Jan 2026 06:36:04 GMT | BN33: ko | BO33: 1.1 | BP33: 윤조에센스 6세대 소개 | 설화수 | BQ33: 피부 능력을 깨우고 피부 건강을 전반적으로 개선하여 건강한 윤기를 선사하는 FIRST STEP, 설화수 윤조에센스 6세대를 소개합니다. | BR33: website | BS33: 설화수 | BT33: https://www.sulwhasoo.com/kr/ko/resource/img/sulwhasoo-og-img_250304.jpg | BU33: https://www.sulwhasoo.com/kr/ko/first-care-activating/first-care-activating-serum-vi.html | BV33: summary_large_image | BW33: 윤조에센스 6세대 소개 | 설화수 | BY33: https://www.sulwhasoo.com/kr/ko/first-care-activating/first-care-activating-serum-vi.html | BZ33: schema.org | CD33: BreadcrumbList | CL33: https://www.sulwhasoo.com/kr/ko/first-care-activating/first-care-activating-serum-vi.html | CM33: 2026-02-05 15:34:45
A34: https://www.sulwhasoo.com/kr/ko/flagship/bukchon/index.html | B34: text/html | C34: 200 | D34: OK | E34: Indexable | G34: 북촌 설화수의 집 - 설화수 북촌 | 설화수 | H34: 24 | I34: 181 | J34: 한국적인 가치와 아름다움을 동시대적 해석으로 담아낸, 북촌 설화수의 집 | Sulwhasoo | K34: 51 | L34: 285 | N34: 0 | O34: The House of Sulwhasoo Bukchon | P34: 30 | R34: 0 | S34: BUKCHON HISTORY | T34: 15 | V34: 0 | Z34: https://www.sulwhasoo.com/kr/ko/flagship/bukchon/index.html | AF34: 100452 | AG34: 18231 | AH34: 18231 | AI34: 7.1043108 | AK34: 895 | AL34: 204 | AM34: 4.3872549 | AN34: 100 | AO34: Very Easy | AP34: 4.19626 | AQ34: 0 | AR34: 4 | AT34: 6 | AU34: 3 | AV34: 0 | AW34: 1.82 | AX34: 16 | AY34: 11 | AZ34: 0 | BA34: 4 | BB34: 3 | BC34: 0 | BH34: 1c8442ec43c7bf3aa25d3a345b642cec | BI34: 0.01 | BJ34: Mon, 12 Jan 2026 06:36:04 GMT | BN34: ko | BO34: 1.1 | BP34: 북촌 설화수의 집 - 설화수 북촌 | 설화수 | BQ34: 한국적인 가치와 아름다움을 동시대적 해석으로 담아낸, 북촌 설화수의 집 | Sulwhasoo | BR34: website | BS34: 설화수 | BT34: https://www.sulwhasoo.com/kr/ko/resource/img/sulwhasoo-og-img_250304.jpg | BU34: https://www.sulwhasoo.com/kr/ko/flagship/bukchon/index.html | BV34: summary_large_image | BW34: 북촌 설화수의 집 - 설화수 북촌 | 설화수 | BY34: https://www.sulwhasoo.com/kr/ko/flagship/bukchon/index.html | BZ34: schema.org | CD34: BreadcrumbList | CL34: https://www.sulwhasoo.com/kr/ko/flagship/bukchon/index.html | CM34: 2026-02-05 15:34:57
A35: https://www.sulwhasoo.com/kr/ko/flagship/dosan/index.html | B35: text/html | C35: 200 | D35: OK | E35: Indexable | G35: 설화수 플래그십 스토어 – 설화수 도산 | 설화수 | H35: 27 | I35: 215 | J35: 아시안 뷰티의 정수를 오롯이 담은 시그니쳐 공간, 설화수 도산 플래그십 스토어 | Sulwhasoo | K35: 55 | L35: 303 | N35: 0 | O35: Sulwhasoo Dosan Flagship Store | P35: 30 | R35: 0 | S35: DOSAN DESIGN STORY | T35: 18 | V35: 0 | Z35: https://www.sulwhasoo.com/kr/ko/flagship/dosan/index.html | AF35: 172848 | AG35: 22366 | AH35: 22366 | AI35: 8.71565 | AK35: 1371 | AL35: 275 | AM35: 4.9854545 | AN35: 100 | AO35: Very Easy | AP35: 3.9038982 | AQ35: 0 | AR35: 4 | AT35: 6 | AU35: 3 | AV35: 0 | AW35: 1.82 | AX35: 16 | AY35: 11 | AZ35: 0 | BA35: 4 | BB35: 3 | BC35: 0 | BH35: 2f26d76ab3450575a7ca51eefc385d2f | BI35: 0.007 | BJ35: Mon, 12 Jan 2026 06:36:04 GMT | BN35: ko | BO35: 1.1 | BP35: 설화수 플래그십 스토어 – 설화수 도산 | 설화수 | BQ35: 아시안 뷰티의 정수를 오롯이 담은 시그니쳐 공간, 설화수 도산 플래그십 스토어 | Sulwhasoo | BR35: website | BS35: 설화수 | BT35: https://www.sulwhasoo.com/kr/ko/resource/img/sulwhasoo-og-img_250304.jpg | BU35: https://www.sulwhasoo.com/kr/ko/flagship/dosan/index.html | BV35: summary_large_image | BW35: 설화수 플래그십 스토어 – 설화수 도산 | 설화수 | BY35: https://www.sulwhasoo.com/kr/ko/flagship/dosan/index.html | BZ35: schema.org | CD35: BreadcrumbList | CL35: https://www.sulwhasoo.com/kr/ko/flagship/dosan/index.html | CM35: 2026-02-05 15:34:43
A36: https://www.sulwhasoo.com/kr/ko/flagship/flagship_reservation/flagship_reservation.html | B36: text/html | C36: 200 | D36: OK | E36: Indexable | G36: 설화수 플래그십 스토어 - 서비스 예약확인/취소 | 설화수 | H36: 32 | I36: 252 | J36: 설화수 플래그십 스토어 서비스를 예약하실 수 있는 페이지 입니다. 로그인 후 이용가능 | Sulwhasoo | K36: 59 | L36: 325 | M36: 플래그십 스토어, 포장서비스, 도슨트 투어, VIP서비스, 예약 | N36: 35 | O36: 설화수 도산 플래그십 스토어 서비스 예약 | P36: 22 | Q36: 예약 안내 | R36: 5 | T36: 0 | V36: 0 | Z36: https://www.sulwhasoo.com/kr/ko/flagship/flagship_reservation/flagship_reservation.html | AF36: 102786 | AG36: 22341 | AH36: 22341 | AI36: 8.7059079 | AK36: 427 | AL36: 103 | AM36: 4.1456311 | AN36: 100 | AO36: Very Easy | AP36: 1.962409 | AQ36: 0 | AR36: 4 | AT36: 5 | AU36: 1 | AV36: 0 | AW36: 0.61 | AX36: 19 | AY36: 13 | AZ36: 0 | BA36: 3 | BB36: 3 | BC36: 0 | BH36: 7006e4abfc977fbfe89da595653c06f6 | BI36: 0.025 | BJ36: Mon, 12 Jan 2026 06:36:00 GMT | BN36: ko | BO36: 1.1 | BP36: 설화수 플래그십 스토어 - 서비스 예약확인/취소 | 설화수 | BQ36: 설화수 플래그십 스토어 서비스를 예약하실 수 있는 페이지 입니다. 로그인 후 이용가능 | Sulwhasoo | BR36: website | BS36: 설화수 | BT36: https://www.sulwhasoo.com/kr/ko/resource/img/sulwhasoo-og-img_250304.jpg | BU36: https://www.sulwhasoo.com/kr/ko/flagship/flagship_reservation/flagship_reservation.html | BV36: summary_large_image | BW36: 설화수 플래그십 스토어 - 서비스 예약확인/취소 | 설화수 | BY36: https://www.sulwhasoo.com/kr/ko/flagship/flagship_reservation/flagship_reservation.html | BZ36: schema.org | CD36: BreadcrumbList | CL36: https://www.sulwhasoo.com/kr/ko/flagship/flagship_reservation/flagship_reservation.html | CM36: 2026-02-05 15:35:05
A37: https://www.sulwhasoo.com/kr/ko/flagship/intro/index.html | B37: text/html | C37: 200 | D37: OK | E37: Indexable | G37: 설화수 플래그십 스토어 | 설화수 | H37: 18 | I37: 142 | J37: 설화수 플래그십 스토어를 소개합니다. 설화수 도산, 설화수 북촌 | Sulwhasoo | K37: 47 | L37: 262 | N37: 0 | O37: 플래그십 스토어 | P37: 8 | R37: 0 | S37: Dosan Flagship Store | T37: 20 | U37: The House of Sulwhasoo Bukchon | V37: 30 | Z37: https://www.sulwhasoo.com/kr/ko/flagship/intro/index.html | AF37: 38840 | AG37: 10122 | AH37: 10122 | AI37: 3.9443713 | AK37: 65 | AL37: 30 | AM37: 2.1666667 | AN37: 100 | AO37: Very Easy | AP37: 1.1147262 | AQ37: 0 | AR37: 4 | AT37: 5 | AU37: 2 | AV37: 0 | AW37: 1.21 | AX37: 18 | AY37: 13 | AZ37: 0 | BA37: 2 | BB37: 2 | BC37: 0 | BH37: 1144b7be4dcc552f4b1eb3d7c4f420 | BI37: 0.006 | BJ37: Mon, 12 Jan 2026 06:36:02 GMT | BN37: ko | BO37: 1.1 | BP37: 설화수 플래그십 스토어 | 설화수 | BQ37: 설화수 플래그십 스토어를 소개합니다. 설화수 도산, 설화수 북촌 | Sulwhasoo | BR37: website | BS37: 설화수 | BT37: https://www.sulwhasoo.com/kr/ko/resource/img/sulwhasoo-og-img_250304.jpg | BU37: https://www.sulwhasoo.com/kr/ko/flagship/intro/index.html | BV37: summary_large_image | BW37: 설화수 플래그십 스토어 | 설화수 | BY37: https://www.sulwhasoo.com/kr/ko/flagship/intro/index.html | BZ37: schema.org | CD37: BreadcrumbList | CL37: https://www.sulwhasoo.com/kr/ko/flagship/intro/index.html | CM37: 2026-02-05 15:35:38
A38: https://www.sulwhasoo.com/kr/ko/gift/packing-service.html | B38: text/html | C38: 200 | D38: OK | E38: Indexable | G38: 설화수 기프트 - 설화수의 특별한 선물 | 설화수 | H38: 27 | I38: 208 | J38: 설화수가 진심을 담아 준비한 포장 서비스, 지함보를 만나보세요. | Sulwhasoo | K38: 47 | L38: 262 | N38: 0 | O38: 설화수 기프트 소개 | P38: 10 | R38: 0 | S38: Sulwhasoo Gift | T38: 14 | U38: 지함보 jihambo | V38: 11 | Z38: https://www.sulwhasoo.com/kr/ko/gift/packing-service.html | AF38: 60946 | AG38: 12668 | AH38: 12668 | AI38: 4.9365042 | AK38: 223 | AL38: 56 | AM38: 3.9821429 | AN38: 100 | AO38: Very Easy | AP38: 1.9008279 | AQ38: 0 | AR38: 3 | AT38: 4 | AU38: 1 | AV38: 0 | AW38: 0.61 | AX38: 17 | AY38: 12 | AZ38: 0 | BA38: 2 | BB38: 2 | BC38: 0 | BH38: 7f377498b1e9732370a4ec8b3e000c42 | BI38: 0.007 | BJ38: Mon, 12 Jan 2026 06:35:58 GMT | BN38: ko | BO38: 1.1 | BP38: 설화수 기프트 - 설화수의 특별한 선물 | 설화수 | BQ38: 설화수가 진심을 담아 준비한 포장 서비스, 지함보를 만나보세요. | Sulwhasoo | BR38: website | BS38: 설화수 | BT38: https://www.sulwhasoo.com/kr/ko/resource/img/sulwhasoo-og-img_250304.jpg | BU38: https://www.sulwhasoo.com/kr/ko/gift/packing-service.html | BV38: summary_large_image | BW38: 설화수 기프트 - 설화수의 특별한 선물 | 설화수 | BY38: https://www.sulwhasoo.com/kr/ko/gift/packing-service.html | BZ38: schema.org | CD38: BreadcrumbList | CL38: https://www.sulwhasoo.com/kr/ko/gift/packing-service.html | CM38: 2026-02-05 15:35:07
A39: https://www.sulwhasoo.com/kr/ko/index.html | B39: text/html | C39: 200 | D39: OK | E39: Indexable | G39: 시간의 흐름에 지지 않는 아름다움을 위한 여정 | 설화수 | H39: 31 | I39: 243 | J39: 시간의 흐름에 지지 않는 아름다움을 위한 여정 | Sulwhasoo | K39: 37 | L39: 210 | M39: 설화수, 브랜드 스토리, 스킨케어, 메이크업, 맨, 설화수 매장안내, 설화수 스파, 설화수 플래그십스토어 | N39: 58 | O39: 설화수 메인 | P39: 6 | R39: 0 | S39: 설화수 추천 | T39: 6 | U39: 베스트 셀러 | V39: 6 | Z39: https://www.sulwhasoo.com/kr/ko/index.html | AF39: 72333 | AG39: 14644 | AH39: 14644 | AI39: 5.7065179 | AK39: 301 | AL39: 102 | AM39: 2.9509804 | AN39: 100 | AO39: Very Easy | AP39: 2.3969402 | AQ39: 0 | AR39: 2 | AT39: 496 | AU39: 164 | AV39: 0 | AW39: 99.39 | AX39: 36 | AY39: 24 | AZ39: 0 | BA39: 3 | BB39: 3 | BC39: 0 | BH39: 4857cdca7460f7e7e85694e074662b08 | BI39: 0.007 | BJ39: Fri, 30 Jan 2026 08:09:28 GMT | BN39: ko | BO39: 1.1 | BP39: 시간의 흐름에 지지 않는 아름다움을 위한 여정 | 설화수 | BQ39: 시간의 흐름에 지지 않는 아름다움을 위한 여정 | Sulwhasoo | BR39: website | BS39: 설화수 | BT39: https://www.sulwhasoo.com/kr/ko/resource/img/sulwhasoo-og-img_250304.jpg | BU39: https://www.sulwhasoo.com/kr/ko/index.html | BV39: summary_large_image | BW39: 시간의 흐름에 지지 않는 아름다움을 위한 여정 | 설화수 | BY39: https://www.sulwhasoo.com/kr/ko/index.html | BZ39: schema.org | CA39: schema.org | CD39: Organization | CE39: WebSite | CL39: https://www.sulwhasoo.com/kr/ko/index.html | CM39: 2026-02-05 15:35:21
A40: https://www.sulwhasoo.com/kr/ko/misc/anti-counterfeit/anti-counterfeit.html | B40: text/html | C40: 200 | D40: OK | E40: Indexable | G40: 위조품 방지 | 설화수 | H40: 12 | I40: 92 | J40: ‘진정한' 아름다움을 지키는 설화수의 여정에 함께해 주세요 | K40: 32 | L40: 167 | N40: 0 | O40: 진정한 아름다움을 지키는 설화수의 여정에 함께해 주세요 | P40: 30 | R40: 0 | S40: 설화수의 위조품 근절 노력 | T40: 14 | U40: 당신의 현명한 선택이 진정한 아름다움을 완성합니다. | V40: 28 | Z40: https://www.sulwhasoo.com/kr/ko/misc/anti-counterfeit/anti-counterfeit.html | AF40: 33760 | AG40: 8806 | AH40: 8806 | AI40: 3.4315485 | AK40: 443 | AL40: 95 | AM40: 4.6631579 | AN40: 100 | AO40: Very Easy | AP40: 6.5831857 | AQ40: 0 | AR40: 4 | AT40: 4 | AU40: 1 | AV40: 0 | AW40: 0.61 | AX40: 17 | AY40: 11 | AZ40: 0 | BA40: 2 | BB40: 2 | BC40: 0 | BH40: 9dfbb58d992ccfd37fb1cdf61f1a8d35 | BI40: 0.007 | BJ40: Mon, 12 Jan 2026 06:36:02 GMT | BN40: ko | BO40: 1.1 | BP40: 위조품 방지 | 설화수 | BQ40: ‘진정한' 아름다움을 지키는 설화수의 여정에 함께해 주세요 | BR40: website | BS40: 설화수 | BT40: https://www.sulwhasoo.com/kr/ko/resource/img/sulwhasoo-og-img_250304.jpg | BU40: https://www.sulwhasoo.com/kr/ko/misc/anti-counterfeit/anti-counterfeit.html | BV40: summary_large_image | BW40: 위조품 방지 | 설화수 | BY40: https://www.sulwhasoo.com/kr/ko/misc/anti-counterfeit/anti-counterfeit.html | CL40: https://www.sulwhasoo.com/kr/ko/misc/anti-counterfeit/anti-counterfeit.html | CM40: 2026-02-05 15:35:07
A41: https://www.sulwhasoo.com/kr/ko/misc/cover/dressing_stand/dressing_stand.html | B41: text/html | C41: 200 | D41: OK | E41: Indexable | G41: 설화수 십장생문 경대 - 명작 컬렉션 | 설화수 | H41: 26 | I41: 199 | J41: 설화수의 자음생명작세트컬렉션 십장생문 경대는 소중한이의 건강과 영원한 생명을 염원하며 한국의 전통장인과 함께 완성한 설화수 명작세트컬렉션입니다. | Sulwhasoo | K41: 92 | L41: 514 | N41: 0 | O41: 2018 자음생 명작세트 컬렉션 [십장생문 경대] | P41: 27 | R41: 0 | S41: 십장생 금사 자수 보자기 전통 포장 | T41: 19 | U41: 귀한 마음을 수놓은 십장생 금사 자수 | V41: 20 | Z41: https://www.sulwhasoo.com/kr/ko/misc/cover/dressing_stand/dressing_stand.html | AF41: 45656 | AG41: 11069 | AH41: 11069 | AI41: 4.3134011 | AK41: 499 | AL41: 87 | AM41: 5.7356322 | AN41: 100 | AO41: Very Easy | AP41: 5.2997332 | AQ41: 0 | AR41: 5 | AT41: 5 | AU41: 2 | AV41: 0 | AW41: 1.21 | AX41: 16 | AY41: 11 | AZ41: 0 | BA41: 3 | BB41: 3 | BC41: 0 | BH41: 63be6dae6de09b0e0365b4ac64e148a2 | BI41: 0.007 | BJ41: Mon, 12 Jan 2026 06:36:00 GMT | BN41: ko | BO41: 1.1 | BP41: 설화수 십장생문 경대 - 명작 컬렉션 | 설화수 | BQ41: 설화수의 자음생명작세트컬렉션 십장생문 경대는 소중한이의 건강과 영원한 생명을 염원하며 한국의 전통장인과 함께 완성한 설화수 명작세트컬렉션입니다. | Sulwhasoo | BR41: website | BS41: 설화수 | BT41: https://www.sulwhasoo.com/kr/ko/resource/img/sulwhasoo-og-img_250304.jpg | BU41: https://www.sulwhasoo.com/kr/ko/misc/cover/dressing_stand/dressing_stand.html | BV41: summary_large_image | BW41: 설화수 십장생문 경대 - 명작 컬렉션 | 설화수 | BY41: https://www.sulwhasoo.com/kr/ko/misc/cover/dressing_stand/dressing_stand.html | BZ41: schema.org | CD41: BreadcrumbList | CL41: https://www.sulwhasoo.com/kr/ko/misc/cover/dressing_stand/dressing_stand.html | CM41: 2026-02-05 15:34:46
A42: https://www.sulwhasoo.com/kr/ko/misc/cover/saekdong_chest/saekdong_chest.html | B42: text/html | C42: 200 | D42: OK | E42: Indexable | G42: 설화수 색동목장 - 명작 컬렉션 | 설화수 | H42: 23 | I42: 176 | J42: 설화수의 진설명작세트컬렉션 색동목장은 진설의 기품과 한결같은 아름다움과 한국의 전통장인과 함께 완성한 설화수 명작세트 컬렉션입니다. | Sulwhasoo | K42: 85 | L42: 475 | N42: 0 | O42: 설화수 명작세트 컬렉션 | P42: 12 | R42: 0 | S42: 2019 진설 명작세트 컬렉션 [색동목장] | T42: 23 | U42: 국가무형문화유산 - 목상감(Wood Inlay) | V42: 26 | Z42: https://www.sulwhasoo.com/kr/ko/misc/cover/saekdong_chest/saekdong_chest.html | AF42: 42803 | AG42: 10851 | AH42: 10851 | AI42: 4.2284502 | AK42: 394 | AL42: 82 | AM42: 4.804878 | AN42: 100 | AO42: Very Easy | AP42: 4.7817845 | AQ42: 0 | AR42: 5 | AT42: 5 | AU42: 2 | AV42: 0 | AW42: 1.21 | AX42: 16 | AY42: 11 | AZ42: 0 | BA42: 3 | BB42: 3 | BC42: 0 | BH42: b24d44f190fda1dbf5bad754393d908 | BI42: 0.009 | BJ42: Mon, 12 Jan 2026 06:36:02 GMT | BN42: ko | BO42: 1.1 | BP42: 설화수 색동목장 - 명작 컬렉션 | 설화수 | BQ42: 설화수의 진설명작세트컬렉션 색동목장은 진설의 기품과 한결같은 아름다움과 한국의 전통장인과 함께 완성한 설화수 명작세트 컬렉션입니다. | Sulwhasoo | BR42: website | BS42: 설화수 | BT42: https://www.sulwhasoo.com/kr/ko/resource/img/sulwhasoo-og-img_250304.jpg | BU42: https://www.sulwhasoo.com/kr/ko/misc/cover/saekdong_chest/saekdong_chest.html | BV42: summary_large_image | BW42: 설화수 색동목장 - 명작 컬렉션 | 설화수 | BY42: https://www.sulwhasoo.com/kr/ko/misc/cover/saekdong_chest/saekdong_chest.html | BZ42: schema.org | CD42: BreadcrumbList | CL42: https://www.sulwhasoo.com/kr/ko/misc/cover/saekdong_chest/saekdong_chest.html | CM42: 2026-02-05 15:35:31
A43: https://www.sulwhasoo.com/kr/ko/misc/cover/shineclassic2020/shineclassic2020.html | B43: text/html | C43: 200 | D43: OK | E43: Indexable | G43: 설화수 실란 - 명작 컬렉션 | 설화수 | H43: 21 | I43: 158 | J43: 설화수의 실란 명작컬렉션은 전통 장인의 기술을 향한 강한 집념과 열정을 바탕으로 한국 미의 본질을 한 단계 더 발전시켜 새로운 아름다움을 전달하는 컬렉션입니다. | Sulwhasoo | K43: 101 | L43: 547 | M43: 설화수, 시즌스페셜, 명작 컬렉션, 설화수 실란, 실란 명작컬렉션 | N43: 36 | O43: 실란 명작 컬렉션 | P43: 9 | R43: 0 | S43: 떨잠-옥공예 | T43: 6 | U43: 은은한 광택으로 피부톤을 밝혀주고 자연스러운 생기와 더불어 얼굴의 윤곽을 잡아주는 프리미엄 리미티드 컬러 팩트 | V43: 61 | Z43: https://www.sulwhasoo.com/kr/ko/misc/cover/shineclassic2020/shineclassic2020.html | AF43: 38303 | AG43: 9794 | AH43: 9794 | AI43: 3.8165553 | AK43: 197 | AL43: 51 | AM43: 3.8627451 | AN43: 100 | AO43: Very Easy | AP43: 2.7109859 | AQ43: 0 | AR43: 5 | AT43: 6 | AU43: 2 | AV43: 0 | AW43: 1.21 | AX43: 17 | AY43: 11 | AZ43: 0 | BA43: 2 | BB43: 2 | BC43: 0 | BH43: 5c04017612ee3fd9936716bd89c85b7a | BI43: 0.01 | BJ43: Mon, 12 Jan 2026 06:36:00 GMT | BN43: ko | BO43: 1.1 | BP43: 설화수 실란 - 명작 컬렉션 | 설화수 | BQ43: 설화수의 실란 명작컬렉션은 전통 장인의 기술을 향한 강한 집념과 열정을 바탕으로 한국 미의 본질을 한 단계 더 발전시켜 새로운 아름다움을 전달하는 컬렉션입니다. | Sulwhasoo | BR43: website | BS43: 설화수 | BT43: https://www.sulwhasoo.com/kr/ko/resource/img/sulwhasoo-og-img_250304.jpg | BU43: https://www.sulwhasoo.com/kr/ko/misc/cover/shineclassic2020/shineclassic2020.html | BV43: summary_large_image | BW43: 설화수 실란 - 명작 컬렉션 | 설화수 | BY43: https://www.sulwhasoo.com/kr/ko/misc/cover/shineclassic2020/shineclassic2020.html | CL43: https://www.sulwhasoo.com/kr/ko/misc/cover/shineclassic2020/shineclassic2020.html | CM43: 2026-02-05 15:34:40
A44: https://www.sulwhasoo.com/kr/ko/misc/cover/statevisitgift/statevisitgift.html | B44: text/html | C44: 200 | D44: OK | E44: Indexable | G44: 설화수 국빈세트 - 명작 컬렉션 | 설화수 | H44: 23 | I44: 176 | J44: 설화수 국빈세트는 설화수의 최고의 가치만을 엄선하여 정성과 예를 오롯이 담았습니다. 한국 전통장인과 함께 귀한 선물의 의미와 가치를 전달하는 설화수 국빈세트를 만나보세요. | Sulwhasoo | K44: 107 | L44: 584 | N44: 0 | O44: 2018 설화수 국빈세트 | P44: 13 | R44: 0 | S44: 전설의 새, 봉황이 깃드는 나무 | T44: 17 | U44: 전설의 새, 봉황이 깃드는 나무 | V44: 17 | Z44: https://www.sulwhasoo.com/kr/ko/misc/cover/statevisitgift/statevisitgift.html | AF44: 46494 | AG44: 11119 | AH44: 11119 | AI44: 4.3328853 | AK44: 317 | AL44: 74 | AM44: 4.2837838 | AN44: 100 | AO44: Very Easy | AP44: 3.401392 | AQ44: 0 | AR44: 5 | AT44: 5 | AU44: 2 | AV44: 0 | AW44: 1.21 | AX44: 16 | AY44: 11 | AZ44: 0 | BA44: 2 | BB44: 2 | BC44: 0 | BH44: 91f9fbedc7459d5cc1ea18d85b939d53 | BI44: 0.006 | BJ44: Mon, 12 Jan 2026 06:36:06 GMT | BN44: ko | BO44: 1.1 | BP44: 설화수 국빈세트 - 명작 컬렉션 | 설화수 | BQ44: 설화수 국빈세트는 설화수의 최고의 가치만을 엄선하여 정성과 예를 오롯이 담았습니다. 한국 전통장인과 함께 귀한 선물의 의미와 가치를 전달하는 설화수 국빈세트를 만나보세요. | Sulwhasoo | BR44: website | BS44: 설화수 | BT44: https://www.sulwhasoo.com/kr/ko/resource/img/sulwhasoo-og-img_250304.jpg | BU44: https://www.sulwhasoo.com/kr/ko/misc/cover/statevisitgift/statevisitgift.html | BV44: summary_large_image | BW44: 설화수 국빈세트 - 명작 컬렉션 | 설화수 | BY44: https://www.sulwhasoo.com/kr/ko/misc/cover/statevisitgift/statevisitgift.html | BZ44: schema.org | CD44: BreadcrumbList | CL44: https://www.sulwhasoo.com/kr/ko/misc/cover/statevisitgift/statevisitgift.html | CM44: 2026-02-05 15:35:27
A45: https://www.sulwhasoo.com/kr/ko/misc/login.html | B45: text/html | C45: 200 | D45: OK | E45: Indexable | G45: 로그인 | 설화수 | H45: 9 | I45: 69 | J45: 설화수 공식 홈페이지에 로그인 해보세요. 설화수와 아모레퍼시픽 사이트는 하나의 아이디와 비밀번호로 이용이 가능합니다. 지금 바로 회원가입 후 이용해보세요 | 설화수 한국 | K45: 94 | L45: 497 | N45: 0 | P45: 0 | R45: 0 | T45: 0 | V45: 0 | Z45: https://www.sulwhasoo.com/kr/ko/misc/login.html | AF45: 25725 | AG45: 6943 | AH45: 6943 | AI45: 2.7055691 | AK45: 47 | AL45: 22 | AM45: 2.1363636 | AN45: 100 | AO45: Very Easy | AP45: 1.314604 | AQ45: 0 | AR45: 3 | AT45: 4 | AU45: 1 | AV45: 0 | AW45: 0.61 | AX45: 16 | AY45: 11 | AZ45: 0 | BA45: 5 | BB45: 5 | BC45: 0 | BH45: ecfca2957de14824c7a19e57f23614d2 | BI45: 0.006 | BJ45: Mon, 12 Jan 2026 06:36:04 GMT | BN45: ko | BO45: 1.1 | BP45: 로그인 | 설화수 | BQ45: 설화수 공식 홈페이지에 로그인 해보세요. 설화수와 아모레퍼시픽 사이트는 하나의 아이디와 비밀번호로 이용이 가능합니다. 지금 바로 회원가입 후 이용해보세요 | 설화수 한국 | BR45: website | BS45: 설화수 | BT45: https://www.sulwhasoo.com/kr/ko/resource/img/sulwhasoo-og-img_250304.jpg | BU45: https://www.sulwhasoo.com/kr/ko/misc/login.html | BV45: summary_large_image | BW45: 로그인 | 설화수 | BY45: https://www.sulwhasoo.com/kr/ko/misc/login.html | CL45: https://www.sulwhasoo.com/kr/ko/misc/login.html | CM45: 2026-02-05 15:34:45
A46: https://www.sulwhasoo.com/kr/ko/misc/search/search.html | B46: text/html | C46: 200 | D46: OK | E46: Indexable | G46: 통합 검색 | 설화수 | H46: 11 | I46: 83 | J46: 설화수 통합 검색 | K46: 9 | L46: 48 | M46: 설화수, 설화수 통합 검색 | N46: 14 | O46: Search | P46: 6 | R46: 0 | T46: 0 | V46: 0 | Z46: https://www.sulwhasoo.com/kr/ko/misc/search/search.html | AF46: 36513 | AG46: 8789 | AH46: 8789 | AI46: 3.4249239 | AK46: 44 | AL46: 20 | AM46: 2.2 | AN46: 100 | AO46: Very Easy | AP46: 0.87997979 | AQ46: 0 | AR46: 4 | AT46: 4 | AU46: 1 | AV46: 0 | AW46: 0.61 | AX46: 16 | AY46: 11 | AZ46: 0 | BA46: 2 | BB46: 2 | BC46: 0 | BH46: aaa9962789caf847728d42091b11bbbf | BI46: 0.009 | BJ46: Mon, 12 Jan 2026 06:36:06 GMT | BN46: ko | BO46: 1.1 | BP46: 설화수 통합 검색 | BR46: website | BS46: 설화수 | BT46: https://www.sulwhasoo.com/kr/ko/resource/img/sulwhasoo-og-img_250304.jpg | BU46: https://www.sulwhasoo.com/kr/ko/misc/search/search.html | BV46: summary_large_image | BW46: 설화수 통합 검색 | BY46: https://www.sulwhasoo.com/kr/ko/misc/search/search.html | CL46: https://www.sulwhasoo.com/kr/ko/misc/search/search.html | CM46: 2026-02-05 15:35:08
A47: https://www.sulwhasoo.com/kr/ko/misc/sitemap/sitemap.html | B47: text/html | C47: 200 | D47: OK | E47: Indexable | G47: 사이트맵 | 설화수 | H47: 10 | I47: 78 | J47: 설화수 한국 공식 웹사이트의 사이트 맵입니다. | Sulwhasoo | K47: 38 | L47: 211 | M47: 설화수, 설화수 사이트 메뉴 | N47: 15 | O47: Sitemap | P47: 7 | R47: 0 | S47: Utility | T47: 7 | U47: Utility | V47: 7 | Z47: https://www.sulwhasoo.com/kr/ko/misc/sitemap/sitemap.html | AF47: 25474 | AG47: 6747 | AH47: 6747 | AI47: 2.6291912 | AK47: 49 | AL47: 25 | AM47: 1.96 | AN47: 100 | AO47: Very Easy | AP47: 1.3578535 | AQ47: 0 | AR47: 4 | AT47: 4 | AU47: 1 | AV47: 0 | AW47: 0.61 | AX47: 18 | AY47: 11 | AZ47: 0 | BA47: 4 | BB47: 2 | BC47: 0 | BH47: 124c50c2095fcab9e8cae0caa57d57ff | BI47: 0.006 | BJ47: Mon, 12 Jan 2026 06:36:00 GMT | BN47: ko | BO47: 1.1 | BP47: 사이트맵 | 설화수 | BQ47: 설화수 한국 공식 웹사이트의 사이트 맵입니다. | Sulwhasoo | BR47: website | BS47: 설화수 | BT47: https://www.sulwhasoo.com/kr/ko/resource/img/sulwhasoo-og-img_250304.jpg | BU47: https://www.sulwhasoo.com/kr/ko/misc/sitemap/sitemap.html | BV47: summary_large_image | BW47: 사이트맵 | 설화수 | BY47: https://www.sulwhasoo.com/kr/ko/misc/sitemap/sitemap.html | CL47: https://www.sulwhasoo.com/kr/ko/misc/sitemap/sitemap.html | CM47: 2026-02-05 15:35:55
A48: https://www.sulwhasoo.com/kr/ko/misc/store/store.html | B48: text/html | C48: 200 | D48: OK | E48: Indexable | G48: 매장찾기 | 설화수 | H48: 10 | I48: 78 | J48: 설화수 매장 찾기 페이지입니다. 가까운 매장 위치와 매장 정보를 확인해보세요. | Sulwhasoo | K48: 55 | L48: 305 | M48: 설화수, 설화수 매장 | N48: 11 | O48: Store Location | P48: 14 | R48: 0 | T48: 0 | V48: 0 | Z48: https://www.sulwhasoo.com/kr/ko/misc/store/store.html | AF48: 24410 | AG48: 6765 | AH48: 6765 | AI48: 2.6362055 | AK48: 53 | AL48: 20 | AM48: 2.65 | AN48: 100 | AO48: Very Easy | AP48: 1.484895 | AQ48: 0 | AR48: 4 | AT48: 237 | AU48: 164 | AV48: 0 | AW48: 99.39 | AX48: 17 | AY48: 10 | AZ48: 0 | BA48: 2 | BB48: 2 | BC48: 0 | BH48: 17d3867dbe3d6165637eee981cbbe495 | BI48: 0.006 | BJ48: Mon, 12 Jan 2026 06:35:58 GMT | BN48: ko | BO48: 1.1 | BP48: 매장찾기 | 설화수 | BQ48: 설화수 매장 찾기 페이지입니다. 가까운 매장 위치와 매장 정보를 확인해보세요. | Sulwhasoo | BR48: website | BS48: 설화수 | BT48: https://www.sulwhasoo.com/kr/ko/resource/img/sulwhasoo-og-img_250304.jpg | BU48: https://www.sulwhasoo.com/kr/ko/misc/store/store.html | BV48: summary_large_image | BW48: 매장찾기 | 설화수 | BY48: https://www.sulwhasoo.com/kr/ko/misc/store/store.html | CL48: https://www.sulwhasoo.com/kr/ko/misc/store/store.html | CM48: 2026-02-05 15:35:33
A49: https://www.sulwhasoo.com/kr/ko/products/2026-lunar-new-year-limited-edition.html | B49: text/html | C49: 200 | D49: OK | E49: Indexable | G49: 윤조에센스 6세대 120ML (말의 해 에디션) | 설화수 | H49: 32 | I49: 270 | J49: 설화수 윤조에센스 6세대 120ML (말의 해 에디션) 제품의 특징과 효능을 자세히 확인해보세요. 정체된 피부 흐름을 되살려, 다시 윤빛 도는 피부. #필수안티에이징에센스 #퍼스트에센스 | K49: 103 | L49: 568 | M49: 설화수, 아모레퍼시픽, 안티에이징, 안티에이징에센스, 부스팅에센스, 설화수 선물세트, 자생력 | N49: 51 | O49: 윤조에센스 6세대 120ML (말의 해 에디션) First Care Activating Serum VI | P49: 57 | R49: 0 | S49: 제품상세 닫기 | T49: 7 | U49: 윤조에센스 | V49: 5 | Z49: https://www.sulwhasoo.com/kr/ko/products/2026-lunar-new-year-limited-edition.html | AF49: 99649 | AG49: 20327 | AH49: 20327 | AI49: 7.9210863 | AK49: 715 | AL49: 207 | AM49: 3.4541063 | AN49: 100 | AO49: Very Easy | AP49: 3.6613638 | AQ49: 0 | AR49: 3 | AT49: 8 | AU49: 2 | AV49: 0 | AW49: 1.21 | AX49: 20 | AY49: 11 | AZ49: 0 | BA49: 2 | BB49: 2 | BC49: 0 | BH49: 835368593ce500f45fa7c488944a39df | BI49: 0.005 | BJ49: Thu, 05 Feb 2026 05:03:34 GMT | BN49: ko | BO49: 1.1 | BP49: 윤조에센스 6세대 120ML (말의 해 에디션) | 설화수 | BQ49: 설화수 윤조에센스 6세대 120ML (말의 해 에디션) 제품의 특징과 효능을 자세히 확인해보세요. 정체된 피부 흐름을 되살려, 다시 윤빛 도는 피부. #필수안티에이징에센스 #퍼스트에센스 | BR49: website | BS49: 설화수 | BT49: https://www.sulwhasoo.com/kr/ko/products/__icsFiles/afieldfile/2025/12/22/251222_final_KR_FCAS_LNY_BY26_PDP_thumbnail_640x640_01.jpg | BU49: https://www.sulwhasoo.com/kr/ko/products/2026-lunar-new-year-limited-edition.html | BV49: summary_large_image | BW49: 윤조에센스 6세대 120ML (말의 해 에디션) | 설화수 | BY49: https://www.sulwhasoo.com/kr/ko/products/2026-lunar-new-year-limited-edition.html | BZ49: schema.org | CA49: schema.org | CD49: BreadcrumbList | CE49: Product | CL49: https://www.sulwhasoo.com/kr/ko/products/2026-lunar-new-year-limited-edition.html | CM49: 2026-02-05 15:35:21
A50: https://www.sulwhasoo.com/kr/ko/products/clarifying-mask.html | B50: text/html | C50: 200 | D50: OK | E50: Indexable | G50: 옥용팩 | 설화수 | H50: 9 | I50: 69 | J50: 설화수 옥용팩 제품의 특징과 효능을 자세히 확인해보세요. 빈틈없이 밀착되어, 한번에 떼어내는 필-오프 마스크. #각질노폐물케어 #한방필오프팩 | K50: 78 | L50: 423 | M50: 마스크, 기타, 정화 & 각질케어, | N50: 19 | O50: 옥용팩 Clarifying Mask | P50: 19 | R50: 0 | S50: 제품상세 닫기 | T50: 7 | U50: 닫기 | V50: 2 | Z50: https://www.sulwhasoo.com/kr/ko/products/clarifying-mask.html | AF50: 90219 | AG50: 18891 | AH50: 18891 | AI50: 7.3615016 | AK50: 387 | AL50: 101 | AM50: 3.8316832 | AN50: 100 | AO50: Very Easy | AP50: 2.1495228 | AQ50: 0 | AR50: 3 | AT50: 8 | AU50: 2 | AV50: 0 | AW50: 1.21 | AX50: 23 | AY50: 14 | AZ50: 0 | BA50: 2 | BB50: 2 | BC50: 0 | BH50: fbd337671d47404aa247639584dae548 | BI50: 0.007 | BJ50: Thu, 05 Feb 2026 05:03:16 GMT | BN50: ko | BO50: 1.1 | BP50: 옥용팩 | 설화수 | BQ50: 설화수 옥용팩 제품의 특징과 효능을 자세히 확인해보세요. 빈틈없이 밀착되어, 한번에 떼어내는 필-오프 마스크. #각질노폐물케어 #한방필오프팩 | BR50: website | BS50: 설화수 | BT50: https://www.sulwhasoo.com/kr/ko/products/__icsFiles/afieldfile/2023/02/28/230228_final_Clarifying-Mask-120ml_thumbnail(640x640)_1.jpg | BU50: https://www.sulwhasoo.com/kr/ko/products/clarifying-mask.html | BV50: summary_large_image | BW50: 옥용팩 | 설화수 | BY50: https://www.sulwhasoo.com/kr/ko/products/clarifying-mask.html | BZ50: schema.org | CA50: schema.org | CB50: schema.org | CD50: BreadcrumbList | CE50: Product | CF50: HowTo | CL50: https://www.sulwhasoo.com/kr/ko/products/clarifying-mask.html | CM50: 2026-02-05 15:34:59
A51: https://www.sulwhasoo.com/kr/ko/products/concentrated-ginseng-brightening-serum.html | B51: text/html | C51: 200 | D51: OK | E51: Indexable | G51: 자음생세럼 브라이트닝 | 설화수 | H51: 17 | I51: 137 | J51: 설화수 자음생세럼 브라이트닝 제품의 특징과 효능을 자세히 확인해보세요. 피부 속부터 더 환하게, 더 빛나게. #토탈브라이트닝세럼 #탄력광채 #데일리저자극케어 | K51: 87 | L51: 476 | M51: 설화수, 미백, 브라이트닝, 광채, 잡티, 스팟, 탄력, 주름, 안티에이징 | N51: 41 | O51: 자음생세럼 브라이트닝 Concentrated Ginseng Brightening Serum | P51: 50 | R51: 0 | S51: 제품상세 닫기 | T51: 7 | U51: 닫기 | V51: 2 | Z51: https://www.sulwhasoo.com/kr/ko/products/concentrated-ginseng-brightening-serum.html | AF51: 88573 | AG51: 18986 | AH51: 18986 | AI51: 7.3985214 | AK51: 474 | AL51: 154 | AM51: 3.0779221 | AN51: 100 | AO51: Very Easy | AP51: 3.0459666 | AQ51: 0 | AR51: 3 | AT51: 8 | AU51: 2 | AV51: 0 | AW51: 1.21 | AX51: 21 | AY51: 12 | AZ51: 0 | BA51: 2 | BB51: 2 | BC51: 0 | BH51: 831419a29e32a76954bffffdcc90608c | BI51: 0.01 | BJ51: Thu, 05 Feb 2026 05:03:18 GMT | BN51: ko | BO51: 1.1 | BP51: 자음생세럼 브라이트닝 | 설화수 | BQ51: 설화수 자음생세럼 브라이트닝 제품의 특징과 효능을 자세히 확인해보세요. 피부 속부터 더 환하게, 더 빛나게. #토탈브라이트닝세럼 #탄력광채 #데일리저자극케어 | BR51: website | BS51: 설화수 | BT51: https://www.sulwhasoo.com/kr/ko/products/__icsFiles/afieldfile/2022/08/29/CGR-Brightening-Serum-50ml_Thumb.jpg | BU51: https://www.sulwhasoo.com/kr/ko/products/concentrated-ginseng-brightening-serum.html | BV51: summary_large_image | BW51: 자음생세럼 브라이트닝 | 설화수 | BY51: https://www.sulwhasoo.com/kr/ko/products/concentrated-ginseng-brightening-serum.html | BZ51: schema.org | CA51: schema.org | CD51: BreadcrumbList | CE51: Product | CL51: https://www.sulwhasoo.com/kr/ko/products/concentrated-ginseng-brightening-serum.html | CM51: 2026-02-05 15:35:22
A52: https://www.sulwhasoo.com/kr/ko/products/concentrated-ginseng-brightening-spot-ampoule.html | B52: text/html | C52: 200 | D52: OK | E52: Indexable | G52: 자음생앰플 브라이트닝 | 설화수 | H52: 17 | I52: 137 | J52: 설화수 자음생앰플 브라이트닝 제품의 특징과 효능을 자세히 확인해보세요. 더 환하게, 더 빛나는 피부 변화를 단 2주만에. #기미잡티집중케어 #2주잡티앰플 | K52: 85 | L52: 462 | M52: 설화수, 미백, 브라이트닝, 광채, 잡티, 스팟, 탄력, 주름, 안티에이징 | N52: 41 | O52: 자음생앰플 브라이트닝 Concentrated Ginseng Brightening Spot Ampoule | P52: 57 | R52: 0 | S52: 제품상세 닫기 | T52: 7 | U52: 닫기 | V52: 2 | Z52: https://www.sulwhasoo.com/kr/ko/products/concentrated-ginseng-brightening-spot-ampoule.html | AF52: 91141 | AG52: 19324 | AH52: 19324 | AI52: 7.5302343 | AK52: 520 | AL52: 157 | AM52: 3.3121019 | AN52: 100 | AO52: Very Easy | AP52: 3.1769335 | AQ52: 0 | AR52: 3 | AT52: 8 | AU52: 2 | AV52: 0 | AW52: 1.21 | AX52: 21 | AY52: 12 | AZ52: 0 | BA52: 2 | BB52: 2 | BC52: 0 | BH52: 2bb27f7770f629173522d149fcc40a1d | BI52: 0.008 | BJ52: Thu, 05 Feb 2026 05:03:18 GMT | BN52: ko | BO52: 1.1 | BP52: 자음생앰플 브라이트닝 | 설화수 | BQ52: 설화수 자음생앰플 브라이트닝 제품의 특징과 효능을 자세히 확인해보세요. 더 환하게, 더 빛나는 피부 변화를 단 2주만에. #기미잡티집중케어 #2주잡티앰플 | BR52: website | BS52: 설화수 | BT52: https://www.sulwhasoo.com/kr/ko/products/__icsFiles/afieldfile/2022/08/29/CGR-Brightening-Serum-Ampoule-20g_Thumb.jpg | BU52: https://www.sulwhasoo.com/kr/ko/products/concentrated-ginseng-brightening-spot-ampoule.html | BV52: summary_large_image | BW52: 자음생앰플 브라이트닝 | 설화수 | BY52: https://www.sulwhasoo.com/kr/ko/products/concentrated-ginseng-brightening-spot-ampoule.html | BZ52: schema.org | CA52: schema.org | CD52: BreadcrumbList | CE52: Product | CL52: https://www.sulwhasoo.com/kr/ko/products/concentrated-ginseng-brightening-spot-ampoule.html | CM52: 2026-02-05 15:35:01
A53: https://www.sulwhasoo.com/kr/ko/products/concentrated-ginseng-rejuvenating-ampoule.html | B53: text/html | C53: 200 | D53: OK | E53: Indexable | G53: 자음생앰플 | 설화수 | H53: 11 | I53: 87 | J53: 설화수 자음생앰플 제품의 특징과 효능을 자세히 확인해보세요. 인삼 전초 에너지를 담아 데미지를 케어*하여 빠르게 되돌린 고밀도 피부*건조, 거칠어짐 등의 피부손상 개선. #3주앰플 #피부컨디션회복 | K53: 109 | L53: 589 | M53: 설화수, 아모레퍼시픽, 안티에이징, 안티에이징앰플, 설화수 앰플, 설화수 선물세트, 자생력, 앰플 | N53: 54 | O53: 자음생앰플 Concentrated Ginseng Rejuvenating Ampoule | P53: 47 | R53: 0 | S53: 제품상세 닫기 | T53: 7 | U53: 자음생앰플 소개 | V53: 8 | Z53: https://www.sulwhasoo.com/kr/ko/products/concentrated-ginseng-rejuvenating-ampoule.html | AF53: 140351 | AG53: 23092 | AH53: 23092 | AI53: 8.9985598 | AK53: 639 | AL53: 201 | AM53: 3.1791045 | AN53: 100 | AO53: Very Easy | AP53: 2.2842526 | AQ53: 0 | AR53: 3 | AT53: 16 | AU53: 9 | AV53: 0 | AW53: 5.45 | AX53: 26 | AY53: 17 | AZ53: 0 | BA53: 2 | BB53: 2 | BC53: 0 | BH53: c723d48f1b2803422adb37f0021c5a9c | BI53: 0.008 | BJ53: Thu, 05 Feb 2026 05:03:26 GMT | BN53: ko | BO53: 1.1 | BP53: 자음생앰플 | 설화수 | BQ53: 설화수 자음생앰플 제품의 특징과 효능을 자세히 확인해보세요. 인삼 전초 에너지를 담아 데미지를 케어*하여 빠르게 되돌린 고밀도 피부*건조, 거칠어짐 등의 피부손상 개선. #3주앰플 #피부컨디션회복 | BR53: website | BS53: 설화수 | BT53: https://www.sulwhasoo.com/kr/ko/products/__icsFiles/afieldfile/2024/07/02/240628_final_SWS_KR_CGR-Ampoule_thumbnail_Product_640.jpg | BU53: https://www.sulwhasoo.com/kr/ko/products/concentrated-ginseng-rejuvenating-ampoule.html | BV53: summary_large_image | BW53: 자음생앰플 | 설화수 | BY53: https://www.sulwhasoo.com/kr/ko/products/concentrated-ginseng-rejuvenating-ampoule.html | BZ53: schema.org | CA53: schema.org | CD53: BreadcrumbList | CE53: Product | CL53: https://www.sulwhasoo.com/kr/ko/products/concentrated-ginseng-rejuvenating-ampoule.html | CM53: 2026-02-05 15:35:44
A54: https://www.sulwhasoo.com/kr/ko/products/concentrated-ginseng-rejuvenating-cleansing-foam.html | B54: text/html | C54: 200 | D54: OK | E54: Indexable | G54: 자음생클렌징폼 | 설화수 | H54: 13 | I54: 105 | J54: 설화수 자음생클렌징폼 제품의 특징과 효능을 자세히 확인해보세요. 세안 단계부터 깨어나는 피부 자생력. #자생력 #진생아미노콤플렉스™ | K54: 73 | L54: 404 | M54: 설화수, 아모레퍼시픽, 자음생, 자음생크림, 자음생클렌징폼, 설화수클렌징폼, 설화수클렌징 | N54: 49 | O54: 자음생클렌징폼 Concentrated Ginseng Rejuvenating Cleansing Foam | P54: 56 | R54: 0 | S54: 제품상세 닫기 | T54: 7 | U54: 함께 쓰면 좋은 제품 닫기 | V54: 14 | Z54: https://www.sulwhasoo.com/kr/ko/products/concentrated-ginseng-rejuvenating-cleansing-foam.html | AF54: 94697 | AG54: 19137 | AH54: 19137 | AI54: 7.4573636 | AK54: 642 | AL54: 168 | AM54: 3.8214286 | AN54: 100 | AO54: Very Easy | AP54: 3.5777006 | AQ54: 0 | AR54: 3 | AT54: 7 | AU54: 1 | AV54: 0 | AW54: 0.61 | AX54: 23 | AY54: 14 | AZ54: 0 | BA54: 2 | BB54: 2 | BC54: 0 | BH54: 817385926aee950f20d644cc332d76b3 | BI54: 0.007 | BJ54: Thu, 05 Feb 2026 05:03:32 GMT | BN54: ko | BO54: 1.1 | BP54: 자음생클렌징폼 | 설화수 | BQ54: 설화수 자음생클렌징폼 제품의 특징과 효능을 자세히 확인해보세요. 세안 단계부터 깨어나는 피부 자생력. #자생력 #진생아미노콤플렉스™ | BR54: website | BS54: 설화수 | BT54: https://www.sulwhasoo.com/kr/ko/products/__icsFiles/afieldfile/2025/07/23/250723_final_KR_concentrated-ginseng-rejuvenating-cleansing-foam_pdp_Thumbnail_640x640.jpg | BU54: https://www.sulwhasoo.com/kr/ko/products/concentrated-ginseng-rejuvenating-cleansing-foam.html | BV54: summary_large_image | BW54: 자음생클렌징폼 | 설화수 | BY54: https://www.sulwhasoo.com/kr/ko/products/concentrated-ginseng-rejuvenating-cleansing-foam.html | BZ54: schema.org | CA54: schema.org | CD54: BreadcrumbList | CE54: Product | CL54: https://www.sulwhasoo.com/kr/ko/products/concentrated-ginseng-rejuvenating-cleansing-foam.html | CM54: 2026-02-05 15:34:44
A55: https://www.sulwhasoo.com/kr/ko/products/concentrated-ginseng-rejuvenating-cream.html | B55: text/html | C55: 200 | D55: OK | E55: Indexable | G55: 자음생크림 | 설화수 | H55: 11 | I55: 87 | J55: 설화수 자음생크림 제품의 특징과 효능을 자세히 확인해보세요. 60년 인삼과학의 정수, 자생력으로 차오른 고밀도 피부. #자생력 #고밀도피부 | K55: 77 | L55: 420 | M55: 설화수, 아모레퍼시픽, 안티에이징, 안티에이징크림, 설화수 크림, 설화수 선물세트, 자생력 | N55: 50 | O55: 자음생크림 Concentrated Ginseng Rejuvenating Cream | P55: 45 | R55: 0 | S55: 제품상세 닫기 | T55: 7 | U55: 닫기 | V55: 2 | Z55: https://www.sulwhasoo.com/kr/ko/products/concentrated-ginseng-rejuvenating-cream.html | AF55: 159574 | AG55: 24238 | AH55: 24238 | AI55: 9.4451366 | AK55: 879 | AL55: 250 | AM55: 3.516 | AN55: 100 | AO55: Very Easy | AP55: 2.6632693 | AQ55: 0 | AR55: 3 | AT55: 19 | AU55: 13 | AV55: 0 | AW55: 7.88 | AX55: 26 | AY55: 17 | AZ55: 0 | BA55: 2 | BB55: 2 | BC55: 0 | BH55: 723e1d8ff8424d029b92b97055062bd7 | BI55: 0.006 | BJ55: Thu, 05 Feb 2026 05:03:24 GMT | BN55: ko | BO55: 1.1 | BP55: 자음생크림 | 설화수 | BQ55: 설화수 자음생크림 제품의 특징과 효능을 자세히 확인해보세요. 60년 인삼과학의 정수, 자생력으로 차오른 고밀도 피부. #자생력 #고밀도피부 | BR55: website | BS55: 설화수 | BT55: https://www.sulwhasoo.com/kr/ko/products/__icsFiles/afieldfile/2024/08/12/240812_final_SWS_KR_CGR-Cream-50ml_thumbnail_Product_640.jpg | BU55: https://www.sulwhasoo.com/kr/ko/products/concentrated-ginseng-rejuvenating-cream.html | BV55: summary_large_image | BW55: 자음생크림 | 설화수 | BY55: https://www.sulwhasoo.com/kr/ko/products/concentrated-ginseng-rejuvenating-cream.html | BZ55: schema.org | CA55: schema.org | CD55: BreadcrumbList | CE55: Product | CL55: https://www.sulwhasoo.com/kr/ko/products/concentrated-ginseng-rejuvenating-cream.html | CM55: 2026-02-05 15:34:51
A56: https://www.sulwhasoo.com/kr/ko/products/concentrated-ginseng-rejuvenating-cream-perfecting-rich.html | B56: text/html | C56: 200 | D56: OK | E56: Indexable | G56: 자음생크림 퍼펙팅 리치 | 설화수 | H56: 18 | I56: 142 | J56: 설화수 자음생크림 퍼펙팅 리치 제품의 특징과 효능을 자세히 확인해보세요. [ 오프라인 판매 전용 상품입니다. ]60년 인삼과학의 정수, 더 강력해진 피부 자생력으로 고밀도 피부를 완성하는 자음생크림. #자생력 #고밀도피부 | K56: 123 | L56: 657 | M56: 설화수, 아모레퍼시픽, 안티에이징, 안티에이징크림, 설화수 크림, 설화수 선물세트, 자생력 | N56: 50 | O56: 자음생크림 퍼펙팅 리치 Concentrated Ginseng Rejuvenating Cream Perfecting Rich | P56: 68 | R56: 0 | S56: 제품상세 닫기 | T56: 7 | U56: NEW 자음생크림 퍼펙팅 리치 | V56: 16 | Z56: https://www.sulwhasoo.com/kr/ko/products/concentrated-ginseng-rejuvenating-cream-perfecting-rich.html | AF56: 135970 | AG56: 23026 | AH56: 23026 | AI56: 8.9728408 | AK56: 746 | AL56: 205 | AM56: 3.6390244 | AN56: 100 | AO56: Very Easy | AP56: 2.8657489 | AQ56: 0 | AR56: 3 | AT56: 6 | AU56: 1 | AV56: 0 | AW56: 0.61 | AX56: 25 | AY56: 17 | AZ56: 0 | BA56: 2 | BB56: 2 | BC56: 0 | BH56: 6ae591f9eb00affe1571878d3f0a2a84 | BI56: 0.007 | BJ56: Thu, 05 Feb 2026 05:03:28 GMT | BN56: ko | BO56: 1.1 | BP56: 자음생크림 퍼펙팅 리치 | 설화수 | BQ56: 설화수 자음생크림 퍼펙팅 리치 제품의 특징과 효능을 자세히 확인해보세요. [ 오프라인 판매 전용 상품입니다. ]60년 인삼과학의 정수, 더 강력해진 피부 자생력으로 고밀도 피부를 완성하는 자음생크림. #자생력 #고밀도피부 | BR56: website | BS56: 설화수 | BT56: https://www.sulwhasoo.com/kr/ko/products/__icsFiles/afieldfile/2024/12/20/241219_final_KR_NEW-CGR-Cream-Perfecting-Rich_Product_thumbnail_640.jpg | BU56: https://www.sulwhasoo.com/kr/ko/products/concentrated-ginseng-rejuvenating-cream-perfecting-rich.html | BV56: summary_large_image | BW56: 자음생크림 퍼펙팅 리치 | 설화수 | BY56: https://www.sulwhasoo.com/kr/ko/products/concentrated-ginseng-rejuvenating-cream-perfecting-rich.html | BZ56: schema.org | CA56: schema.org | CD56: BreadcrumbList | CE56: Product | CL56: https://www.sulwhasoo.com/kr/ko/products/concentrated-ginseng-rejuvenating-cream-perfecting-rich.html | CM56: 2026-02-05 15:35:29
A57: https://www.sulwhasoo.com/kr/ko/products/concentrated-ginseng-rejuvenating-cream-rich.html | B57: text/html | C57: 200 | D57: OK | E57: Indexable | G57: 자음생크림 리치 | 설화수 | H57: 14 | I57: 110 | J57: 설화수 자음생크림 리치 제품의 특징과 효능을 자세히 확인해보세요. 60년 인삼과학의 정수, 자생력으로 차오른 고밀도 피부. #자생력 #고밀도피부 | K57: 80 | L57: 435 | M57: 설화수, 아모레퍼시픽, 안티에이징, 안티에이징크림, 설화수 크림, 설화수 선물세트, 자생력 | N57: 50 | O57: 자음생크림 리치 Concentrated Ginseng Rejuvenating Cream Rich | P57: 53 | R57: 0 | S57: 제품상세 닫기 | T57: 7 | U57: 닫기 | V57: 2 | Z57: https://www.sulwhasoo.com/kr/ko/products/concentrated-ginseng-rejuvenating-cream-rich.html | AF57: 163330 | AG57: 24704 | AH57: 24704 | AI57: 9.6267288 | AK57: 807 | AL57: 231 | AM57: 3.4935065 | AN57: 100 | AO57: Very Easy | AP57: 2.5542901 | AQ57: 0 | AR57: 3 | AT57: 12 | AU57: 5 | AV57: 0 | AW57: 3.03 | AX57: 26 | AY57: 17 | AZ57: 0 | BA57: 2 | BB57: 2 | BC57: 0 | BH57: cdb9105b7d59517e2d809491d0ea7129 | BI57: 0.008 | BJ57: Thu, 05 Feb 2026 05:03:24 GMT | BN57: ko | BO57: 1.1 | BP57: 자음생크림 리치 | 설화수 | BQ57: 설화수 자음생크림 리치 제품의 특징과 효능을 자세히 확인해보세요. 60년 인삼과학의 정수, 자생력으로 차오른 고밀도 피부. #자생력 #고밀도피부 | BR57: website | BS57: 설화수 | BT57: https://www.sulwhasoo.com/kr/ko/products/__icsFiles/afieldfile/2024/08/12/240812_final_SWS_KR_CGR-Cream-Rich-50ml_thumbnail_Product_640.jpg | BU57: https://www.sulwhasoo.com/kr/ko/products/concentrated-ginseng-rejuvenating-cream-rich.html | BV57: summary_large_image | BW57: 자음생크림 리치 | 설화수 | BY57: https://www.sulwhasoo.com/kr/ko/products/concentrated-ginseng-rejuvenating-cream-rich.html | BZ57: schema.org | CA57: schema.org | CD57: BreadcrumbList | CE57: Product | CL57: https://www.sulwhasoo.com/kr/ko/products/concentrated-ginseng-rejuvenating-cream-rich.html | CM57: 2026-02-05 15:34:57
A58: https://www.sulwhasoo.com/kr/ko/products/concentrated-ginseng-rejuvenating-emulsion.html | B58: text/html | C58: 200 | D58: OK | E58: Indexable | G58: 자음생유액 | 설화수 | H58: 11 | I58: 87 | J58: 설화수 자음생유액 제품의 특징과 효능을 자세히 확인해보세요. 촘촘히 차오른 콜라겐으로 밀도 높게 탄탄해진 피부. #자생력 #고밀도피부 | K58: 74 | L58: 401 | M58: 설화수, 아모레퍼시픽, 안티에이징, 안티에이징 로션, 설화수 로션, 설화수 선물세트, 자생력, 로션 | N58: 55 | O58: 자음생유액 Concentrated Ginseng Rejuvenating Emulsion | P58: 48 | R58: 0 | S58: 제품상세 닫기 | T58: 7 | U58: 자음생유액 소개 | V58: 8 | Z58: https://www.sulwhasoo.com/kr/ko/products/concentrated-ginseng-rejuvenating-emulsion.html | AF58: 132583 | AG58: 22309 | AH58: 22309 | AI58: 8.693438 | AK58: 552 | AL58: 183 | AM58: 3.0163934 | AN58: 100 | AO58: Very Easy | AP58: 2.1579239 | AQ58: 0 | AR58: 3 | AT58: 17 | AU58: 11 | AV58: 0 | AW58: 6.67 | AX58: 26 | AY58: 17 | AZ58: 0 | BA58: 2 | BB58: 2 | BC58: 0 | BH58: 1e742e8032427f577aee946ad3a2ca84 | BI58: 0.007 | BJ58: Thu, 05 Feb 2026 05:03:28 GMT | BN58: ko | BO58: 1.1 | BP58: 자음생유액 | 설화수 | BQ58: 설화수 자음생유액 제품의 특징과 효능을 자세히 확인해보세요. 촘촘히 차오른 콜라겐으로 밀도 높게 탄탄해진 피부. #자생력 #고밀도피부 | BR58: website | BS58: 설화수 | BT58: https://www.sulwhasoo.com/kr/ko/products/__icsFiles/afieldfile/2024/07/02/240628_final_SWS_KR_CGR-Emulsion_thumbnail_Product_640.jpg | BU58: https://www.sulwhasoo.com/kr/ko/products/concentrated-ginseng-rejuvenating-emulsion.html | BV58: summary_large_image | BW58: 자음생유액 | 설화수 | BY58: https://www.sulwhasoo.com/kr/ko/products/concentrated-ginseng-rejuvenating-emulsion.html | BZ58: schema.org | CA58: schema.org | CD58: BreadcrumbList | CE58: Product | CL58: https://www.sulwhasoo.com/kr/ko/products/concentrated-ginseng-rejuvenating-emulsion.html | CM58: 2026-02-05 15:35:36
A59: https://www.sulwhasoo.com/kr/ko/products/concentrated-ginseng-rejuvenating-eye-cream.html | B59: text/html | C59: 200 | D59: OK | E59: Indexable | G59: 자음생아이크림 | 설화수 | H59: 13 | I59: 105 | J59: 설화수 자음생아이크림 제품의 특징과 효능을 자세히 확인해보세요. 60년 인삼과학의 정수, 자생력으로 차오른 고밀도 피부. #자생력 #고밀도눈가피부 | K59: 81 | L59: 444 | M59: 설화수, 아모레퍼시픽, 안티에이징, 안티에이징아이크림, 설화수 아이크림, 설화수 선물세트, 자생력, 아이크림 | N59: 60 | O59: 자음생아이크림 Concentrated Ginseng Rejuvenating Eye Cream | P59: 51 | R59: 0 | S59: 제품상세 닫기 | T59: 7 | U59: 자음생아이크림 소개 | V59: 10 | Z59: https://www.sulwhasoo.com/kr/ko/products/concentrated-ginseng-rejuvenating-eye-cream.html | AF59: 141953 | AG59: 22839 | AH59: 22839 | AI59: 8.89997 | AK59: 622 | AL59: 201 | AM59: 3.0945274 | AN59: 100 | AO59: Very Easy | AP59: 2.1972952 | AQ59: 0 | AR59: 3 | AT59: 16 | AU59: 10 | AV59: 0 | AW59: 6.06 | AX59: 26 | AY59: 17 | AZ59: 0 | BA59: 2 | BB59: 2 | BC59: 0 | BH59: d2d3df1db37e45ff4eb966a0e75e48e8 | BI59: 0.007 | BJ59: Thu, 05 Feb 2026 05:03:26 GMT | BN59: ko | BO59: 1.1 | BP59: 자음생아이크림 | 설화수 | BQ59: 설화수 자음생아이크림 제품의 특징과 효능을 자세히 확인해보세요. 60년 인삼과학의 정수, 자생력으로 차오른 고밀도 피부. #자생력 #고밀도눈가피부 | BR59: website | BS59: 설화수 | BT59: https://www.sulwhasoo.com/kr/ko/products/__icsFiles/afieldfile/2024/07/02/240628_final_SWS_KR_CGR-EyeCream_thumbnail_Product_640.jpg | BU59: https://www.sulwhasoo.com/kr/ko/products/concentrated-ginseng-rejuvenating-eye-cream.html | BV59: summary_large_image | BW59: 자음생아이크림 | 설화수 | BY59: https://www.sulwhasoo.com/kr/ko/products/concentrated-ginseng-rejuvenating-eye-cream.html | BZ59: schema.org | CA59: schema.org | CD59: BreadcrumbList | CE59: Product | CL59: https://www.sulwhasoo.com/kr/ko/products/concentrated-ginseng-rejuvenating-eye-cream.html | CM59: 2026-02-05 15:35:45
A60: https://www.sulwhasoo.com/kr/ko/products/concentrated-ginseng-rejuvenating-serum.html | B60: text/html | C60: 200 | D60: OK | E60: Indexable | G60: 자음생캡슐세럼 | 설화수 | H60: 13 | I60: 105 | J60: 설화수 자음생캡슐세럼 제품의 특징과 효능을 자세히 확인해보세요. 10만* 인삼 캡슐을 담아 5가지 어린 피부 존을 세우다*본품 30ml 기준. #자생력 #인삼캡슐세럼 | K60: 92 | L60: 510 | M60: 설화수, 아모레퍼시픽, 안티에이징, 안티에이징세럼, 설화수 세럼, 설화수 선물세트, 자생력 | N60: 50 | O60: 자음생캡슐세럼 Concentrated Ginseng Rejuvenating Serum | P60: 47 | R60: 0 | S60: 제품상세 닫기 | T60: 7 | U60: 자음생캡슐세럼 소개 | V60: 10 | Z60: https://www.sulwhasoo.com/kr/ko/products/concentrated-ginseng-rejuvenating-serum.html | AF60: 142601 | AG60: 23102 | AH60: 23102 | AI60: 9.0024567 | AK60: 672 | AL60: 221 | AM60: 3.040724 | AN60: 100 | AO60: Very Easy | AP60: 2.3584597 | AQ60: 0 | AR60: 3 | AT60: 18 | AU60: 12 | AV60: 0 | AW60: 7.27 | AX60: 26 | AY60: 17 | AZ60: 0 | BA60: 2 | BB60: 2 | BC60: 0 | BH60: 3c50466bbe965d4f61683231d1389792 | BI60: 0.005 | BJ60: Thu, 05 Feb 2026 05:03:26 GMT | BN60: ko | BO60: 1.1 | BP60: 자음생캡슐세럼 | 설화수 | BQ60: 설화수 자음생캡슐세럼 제품의 특징과 효능을 자세히 확인해보세요. 10만* 인삼 캡슐을 담아 5가지 어린 피부 존을 세우다*본품 30ml 기준. #자생력 #인삼캡슐세럼 | BR60: website | BS60: 설화수 | BT60: https://www.sulwhasoo.com/kr/ko/products/__icsFiles/afieldfile/2024/07/02/240628_final_SWS_KR_CGRS_thumbnail_Product_640.jpg | BU60: https://www.sulwhasoo.com/kr/ko/products/concentrated-ginseng-rejuvenating-serum.html | BV60: summary_large_image | BW60: 자음생캡슐세럼 | 설화수 | BY60: https://www.sulwhasoo.com/kr/ko/products/concentrated-ginseng-rejuvenating-serum.html | BZ60: schema.org | CA60: schema.org | CD60: BreadcrumbList | CE60: Product | CL60: https://www.sulwhasoo.com/kr/ko/products/concentrated-ginseng-rejuvenating-serum.html | CM60: 2026-02-05 15:35:19
A61: https://www.sulwhasoo.com/kr/ko/products/concentrated-ginseng-rejuvenating-water.html | B61: text/html | C61: 200 | D61: OK | E61: Indexable | G61: 자음생수 | 설화수 | H61: 10 | I61: 78 | J61: 설화수 자음생수 제품의 특징과 효능을 자세히 확인해보세요. 촘촘히 차오른 콜라겐으로 밀도 높게 탄탄해진 피부. #자생력 #고밀도피부 | K61: 73 | L61: 395 | M61: 설화수, 아모레퍼시픽, 안티에이징, 안티에이징 토너, 설화수 스킨, 설화수 선물세트, 자생력, 토너, 스킨 | N61: 59 | O61: 자음생수 Concentrated Ginseng Rejuvenating Water | P61: 44 | R61: 0 | S61: 제품상세 닫기 | T61: 7 | U61: 자음생수 소개 | V61: 7 | Z61: https://www.sulwhasoo.com/kr/ko/products/concentrated-ginseng-rejuvenating-water.html | AF61: 133262 | AG61: 22310 | AH61: 22310 | AI61: 8.6938277 | AK61: 538 | AL61: 178 | AM61: 3.0224719 | AN61: 100 | AO61: Very Easy | AP61: 1.9985391 | AQ61: 0 | AR61: 3 | AT61: 17 | AU61: 11 | AV61: 0 | AW61: 6.67 | AX61: 26 | AY61: 17 | AZ61: 0 | BA61: 2 | BB61: 2 | BC61: 0 | BH61: 6c247b24c68d9e2ac57d7c274a7ecfaa | BI61: 0.006 | BJ61: Thu, 05 Feb 2026 05:03:28 GMT | BN61: ko | BO61: 1.1 | BP61: 자음생수 | 설화수 | BQ61: 설화수 자음생수 제품의 특징과 효능을 자세히 확인해보세요. 촘촘히 차오른 콜라겐으로 밀도 높게 탄탄해진 피부. #자생력 #고밀도피부 | BR61: website | BS61: 설화수 | BT61: https://www.sulwhasoo.com/kr/ko/products/__icsFiles/afieldfile/2024/07/02/240628_final_SWS_KR_CGR-Water_thumbnail_Product_640.jpg | BU61: https://www.sulwhasoo.com/kr/ko/products/concentrated-ginseng-rejuvenating-water.html | BV61: summary_large_image | BW61: 자음생수 | 설화수 | BY61: https://www.sulwhasoo.com/kr/ko/products/concentrated-ginseng-rejuvenating-water.html | BZ61: schema.org | CA61: schema.org | CD61: BreadcrumbList | CE61: Product | CL61: https://www.sulwhasoo.com/kr/ko/products/concentrated-ginseng-rejuvenating-water.html | CM61: 2026-02-05 15:34:50
A62: https://www.sulwhasoo.com/kr/ko/products/concentrated-ginseng-renewing-creamy-mask-EX.html | B62: text/html | C62: 200 | D62: OK | E62: Indexable | G62: 자음생마스크EX | 설화수 | H62: 14 | I62: 120 | J62: 설화수 자음생마스크EX 제품의 특징과 효능을 자세히 확인해보세요. 자음생크림 한 통*의 힘으로 하루 종일 힘있게 차오른 피부* 자음생마스크EX 5장 기준. #3중탄력마스크 #더블랩핑시트 | K62: 103 | L62: 574 | M62: 탄력개선, 주름개선, 3중탄력, 자음생, 안티에이징, 마스크, 자음생마스크, 탄력주름, 홈케어, 선물추천 | N62: 58 | O62: 자음생마스크EX Concentrated Ginseng Renewing Creamy Mask EX | P62: 53 | R62: 0 | S62: 제품상세 닫기 | T62: 7 | U62: 닫기 | V62: 2 | Z62: https://www.sulwhasoo.com/kr/ko/products/concentrated-ginseng-renewing-creamy-mask-EX.html | AF62: 84318 | AG62: 18589 | AH62: 18589 | AI62: 7.2438173 | AK62: 437 | AL62: 117 | AM62: 3.7350427 | AN62: 100 | AO62: Very Easy | AP62: 3.0008738 | AQ62: 0 | AR62: 3 | AT62: 7 | AU62: 1 | AV62: 0 | AW62: 0.61 | AX62: 21 | AY62: 12 | AZ62: 0 | BA62: 2 | BB62: 2 | BC62: 0 | BH62: 30e0367abdb81b539a599131996edf00 | BI62: 0.012 | BJ62: Thu, 05 Feb 2026 05:03:18 GMT | BN62: ko | BO62: 1.1 | BP62: 자음생마스크EX | 설화수 | BQ62: 설화수 자음생마스크EX 제품의 특징과 효능을 자세히 확인해보세요. 자음생크림 한 통*의 힘으로 하루 종일 힘있게 차오른 피부* 자음생마스크EX 5장 기준. #3중탄력마스크 #더블랩핑시트 | BR62: website | BS62: 설화수 | BT62: https://www.sulwhasoo.com/kr/ko/products/__icsFiles/afieldfile/2022/08/29/CGR-Creamy-Mask-EX-1ea_Thumb.jpg | BU62: https://www.sulwhasoo.com/kr/ko/products/concentrated-ginseng-renewing-creamy-mask-EX.html | BV62: summary_large_image | BW62: 자음생마스크EX | 설화수 | BY62: https://www.sulwhasoo.com/kr/ko/products/concentrated-ginseng-renewing-creamy-mask-EX.html | BZ62: schema.org | CA62: schema.org | CD62: BreadcrumbList | CE62: Product | CL62: https://www.sulwhasoo.com/kr/ko/products/concentrated-ginseng-renewing-creamy-mask-EX.html | CM62: 2026-02-05 15:35:28
... A74: https://www.sulwhasoo.com/kr/ko/products/first-care-activating-serum-vi.html | B74: text/html | C74: 200 | D74: OK | E74: Indexable | G74: 윤조에센스 6세대 | 설화수 | H74: 15 | I74: 121 | J74: 설화수 윤조에센스 6세대 제품의 특징과 효능을 자세히 확인해보세요. 정체된 피부 흐름을 되살려, 다시 윤빛 도는 피부. #필수안티에이징에센스 #퍼스트에센스 | K74: 86 | L74: 466 | M74: 설화수, 아모레퍼시픽, 안티에이징, 안티에이징에센스, 부스팅에센스, 설화수 선물세트, 필수안티에이징에센스 , 윤아 | N74: 63 | O74: 윤조에센스 6세대 First Care Activating Serum VI | P74: 40 | R74: 0 | S74: 제품상세 닫기 | T74: 7 | U74: 윤조에센스 | V74: 5 | Z74: https://www.sulwhasoo.com/kr/ko/products/first-care-activating-serum-vi.html | AF74: 103749 | AG74: 20808 | AH74: 20808 | AI74: 8.1085239 | AK74: 711 | AL74: 216 | AM74: 3.2916667 | AN74: 100 | AO74: Very Easy | AP74: 3.4588714 | AQ74: 0 | AR74: 3 | AT74: 38 | AU74: 31 | AV74: 0 | AW74: 18.79 | AX74: 23 | AY74: 14 | AZ74: 0 | BA74: 2 | BB74: 2 | BC74: 0 | BH74: a482d79854b361879e3d65ee1d2aba6a | BI74: 0.006 | BJ74: Thu, 05 Feb 2026 05:03:20 GMT | BN74: ko | BO74: 1.1 | BP74: 윤조에센스 6세대 | 설화수 | BQ74: 설화수 윤조에센스 6세대 제품의 특징과 효능을 자세히 확인해보세요. 정체된 피부 흐름을 되살려, 다시 윤빛 도는 피부. #필수안티에이징에센스 #퍼스트에센스 | BR74: website | BS74: 설화수 | BT74: https://www.sulwhasoo.com/kr/ko/products/__icsFiles/afieldfile/2025/02/17/250217_final_KR_FCAS-6th-Generation_90ml_Thmbnail_640x640_2.jpg | BU74: https://www.sulwhasoo.com/kr/ko/products/first-care-activating-serum-vi.html | BV74: summary_large_image | BW74: 윤조에센스 6세대 | 설화수 | BY74: https://www.sulwhasoo.com/kr/ko/products/first-care-activating-serum-vi.html | BZ74: schema.org | CA74: schema.org | CD74: BreadcrumbList | CE74: Product | CL74: https://www.sulwhasoo.com/kr/ko/products/first-care-activating-serum-vi.html | CM74: 2026-02-05 15:35:53
A75: https://www.sulwhasoo.com/kr/ko/products/gentle-cleansing-foam-ex.html | B75: text/html | C75: 200 | D75: OK | E75: Indexable | G75: 순행클렌징폼 | 설화수 | H75: 12 | I75: 96 | J75: 설화수 순행클렌징폼 제품의 특징과 효능을 자세히 확인해보세요. 수분 가득 풍성한 거품으로 모공 속까지 딥 클렌징 폼. #백화점No.1 #마일드클렌징 | K75: 82 | L75: 449 | M75: 설화수, 아모레퍼시픽, 어버이날선물, 설화수 순행, 설화수 클렌징폼, 순행, 순행클렌징폼, 설화수 화장품 | N75: 58 | O75: 순행클렌징폼 Gentle Cleansing Foam | P75: 28 | R75: 0 | S75: 제품상세 닫기 | T75: 7 | U75: 닫기 | V75: 2 | Z75: https://www.sulwhasoo.com/kr/ko/products/gentle-cleansing-foam-ex.html | AF75: 95522 | AG75: 19342 | AH75: 19342 | AI75: 7.5372486 | AK75: 381 | AL75: 104 | AM75: 3.6634615 | AN75: 100 | AO75: Very Easy | AP75: 2.1084437 | AQ75: 0 | AR75: 3 | AT75: 16 | AU75: 10 | AV75: 0 | AW75: 6.06 | AX75: 21 | AY75: 12 | AZ75: 0 | BA75: 2 | BB75: 2 | BC75: 0 | BH75: 7435af0035ba3ffad1bd250bce3f947c | BI75: 0.007 | BJ75: Thu, 05 Feb 2026 05:03:16 GMT | BN75: ko | BO75: 1.1 | BP75: 순행클렌징폼 | 설화수 | BQ75: 설화수 순행클렌징폼 제품의 특징과 효능을 자세히 확인해보세요. 수분 가득 풍성한 거품으로 모공 속까지 딥 클렌징 폼. #백화점No.1 #마일드클렌징 | BR75: website | BS75: 설화수 | BT75: https://www.sulwhasoo.com/kr/ko/products/__icsFiles/afieldfile/2023/05/30/230531_Gentle-Cleansing-Foam-400ml_thumb_640.jpg | BU75: https://www.sulwhasoo.com/kr/ko/products/gentle-cleansing-foam-ex.html | BV75: summary_large_image | BW75: 순행클렌징폼 | 설화수 | BY75: https://www.sulwhasoo.com/kr/ko/products/gentle-cleansing-foam-ex.html | BZ75: schema.org | CA75: schema.org | CB75: schema.org | CD75: BreadcrumbList | CE75: Product | CF75: HowTo | CL75: https://www.sulwhasoo.com/kr/ko/products/gentle-cleansing-foam-ex.html | CM75: 2026-02-05 15:35:30
A76: https://www.sulwhasoo.com/kr/ko/products/gentle-cleansing-oil.html | B76: text/html | C76: 200 | D76: OK | E76: Indexable | G76: 순행클렌징오일 | 설화수 | H76: 13 | I76: 105 | J76: 설화수 순행클렌징오일 제품의 특징과 효능을 자세히 확인해보세요. 잔여물 없이 모공 속까지 산뜻한 딥 클렌징 오일. #딥클렌징 #탄력모공케어 | K76: 77 | L76: 416 | M76: 클렌징, 기타, 정화 & 각질케어, | N76: 19 | O76: 순행클렌징오일 Gentle Cleansing Oil | P76: 28 | R76: 0 | S76: 제품상세 닫기 | T76: 7 | U76: 닫기 | V76: 2 | Z76: https://www.sulwhasoo.com/kr/ko/products/gentle-cleansing-oil.html | AF76: 94405 | AG76: 18700 | AH76: 18700 | AI76: 7.2870721 | AK76: 357 | AL76: 98 | AM76: 3.6428571 | AN76: 100 | AO76: Very Easy | AP76: 1.9716438 | AQ76: 0 | AR76: 3 | AT76: 11 | AU76: 4 | AV76: 0 | AW76: 2.42 | AX76: 21 | AY76: 12 | AZ76: 0 | BA76: 2 | BB76: 2 | BC76: 0 | BH76: af6b0998e7030e91e4cf945dfe675651 | BI76: 0.006 | BJ76: Thu, 05 Feb 2026 05:03:16 GMT | BN76: ko | BO76: 1.1 | BP76: 순행클렌징오일 | 설화수 | BQ76: 설화수 순행클렌징오일 제품의 특징과 효능을 자세히 확인해보세요. 잔여물 없이 모공 속까지 산뜻한 딥 클렌징 오일. #딥클렌징 #탄력모공케어 | BR76: website | BS76: 설화수 | BT76: https://www.sulwhasoo.com/kr/ko/products/__icsFiles/afieldfile/2023/05/30/230531_Gentle-Cleansing-Oil-400ml_thumb_640.jpg | BU76: https://www.sulwhasoo.com/kr/ko/products/gentle-cleansing-oil.html | BV76: summary_large_image | BW76: 순행클렌징오일 | 설화수 | BY76: https://www.sulwhasoo.com/kr/ko/products/gentle-cleansing-oil.html | BZ76: schema.org | CA76: schema.org | CD76: BreadcrumbList | CE76: Product | CL76: https://www.sulwhasoo.com/kr/ko/products/gentle-cleansing-oil.html | CM76: 2026-02-05 15:35:17
A77: https://www.sulwhasoo.com/kr/ko/products/glowing-lip-balm.html | B77: text/html | C77: 200 | D77: OK | E77: Indexable | G77: 윤조립밤 | 설화수 | H77: 10 | I77: 78 | J77: 설화수 윤조립밤 제품의 특징과 효능을 자세히 확인해보세요. 보이지 않는 주름까지 잡는 수분 볼륨 립케어. #주름개선기능성 #24시간보습지속 | K77: 77 | L77: 423 | M77: 설화수, 설화수윤조립밤, 윤조립밤, 립케어, 백화점립밤, 입술보습 | N77: 36 | O77: 윤조립밤 Glowing Lip Balm | P77: 21 | R77: 0 | S77: 제품상세 닫기 | T77: 7 | U77: 설화수 윤조립밤 | V77: 8 | Z77: https://www.sulwhasoo.com/kr/ko/products/glowing-lip-balm.html | AF77: 103547 | AG77: 21439 | AH77: 21439 | AI77: 8.3544138 | AK77: 629 | AL77: 189 | AM77: 3.3280423 | AN77: 100 | AO77: Very Easy | AP77: 3.4283772 | AQ77: 0 | AR77: 3 | AT77: 11 | AU77: 3 | AV77: 0 | AW77: 1.82 | AX77: 23 | AY77: 12 | AZ77: 0 | BA77: 2 | BB77: 2 | BC77: 0 | BH77: d210891057b3cf0f301d45bea76491c | BI77: 0.009 | BJ77: Thu, 05 Feb 2026 05:03:24 GMT | BN77: ko | BO77: 1.1 | BP77: 윤조립밤 | 설화수 | BQ77: 설화수 윤조립밤 제품의 특징과 효능을 자세히 확인해보세요. 보이지 않는 주름까지 잡는 수분 볼륨 립케어. #주름개선기능성 #24시간보습지속 | BR77: website | BS77: 설화수 | BT77: https://www.sulwhasoo.com/kr/ko/products/__icsFiles/afieldfile/2024/02/05/20240118_final_Glowing-Lip-Balm_pdp_Thumbnail_000-1.jpg | BU77: https://www.sulwhasoo.com/kr/ko/products/glowing-lip-balm.html | BV77: summary_large_image | BW77: 윤조립밤 | 설화수 | BY77: https://www.sulwhasoo.com/kr/ko/products/glowing-lip-balm.html | BZ77: schema.org | CA77: schema.org | CD77: BreadcrumbList | CE77: Product | CL77: https://www.sulwhasoo.com/kr/ko/products/glowing-lip-balm.html | CM77: 2026-02-05 15:35:39
A78: https://www.sulwhasoo.com/kr/ko/products/lumiwise-brightening-ampoule-serum.html | B78: text/html | C78: 200 | D78: OK | E78: Indexable | G78: 자정앰플세럼 | 설화수 | H78: 12 | I78: 96 | J78: 설화수 자정앰플세럼 제품의 특징과 효능을 자세히 확인해보세요. [오프라인 선런칭 *아모레몰 2/19]다시 짙어지지 않고 맑게 이어지는 피부. #브라이트닝 #맑고투명한피부 | K78: 95 | L78: 517 | M78: 아모레퍼시픽, 설화수, 설화수 스킨케어, 브라이트닝, 색소침착, 미백에센스 | N78: 41 | O78: 자정앰플세럼 Lumiwise Brightening Ampoule Serum | P78: 41 | R78: 0 | S78: 제품상세 닫기 | T78: 7 | U78: 함께 쓰면 좋은 제품 닫기 | V78: 14 | Z78: https://www.sulwhasoo.com/kr/ko/products/lumiwise-brightening-ampoule-serum.html | AF78: 140844 | AG78: 21803 | AH78: 21803 | AI78: 8.4962584 | AK78: 733 | AL78: 195 | AM78: 3.7589744 | AN78: 100 | AO78: Very Easy | AP78: 2.315357 | AQ78: 0 | AR78: 3 | AT78: 10 | AU78: 5 | AV78: 0 | AW78: 3.03 | AX78: 22 | AY78: 14 | AZ78: 0 | BA78: 2 | BB78: 2 | BC78: 0 | BH78: b9814d3c8c3c14f5eee3f1840bab926 | BI78: 0.012 | BJ78: Thu, 05 Feb 2026 05:03:34 GMT | BN78: ko | BO78: 1.1 | BP78: 자정앰플세럼 | 설화수 | BQ78: 설화수 자정앰플세럼 제품의 특징과 효능을 자세히 확인해보세요. [오프라인 선런칭 *아모레몰 2/19]다시 짙어지지 않고 맑게 이어지는 피부. #브라이트닝 #맑고투명한피부 | BR78: website | BS78: 설화수 | BT78: https://www.sulwhasoo.com/kr/ko/products/__icsFiles/afieldfile/2026/01/13/260112_final_KR_LUMIWISE_Brightening_Ampoule_Serum_PDP_thumbnail_640x640_01.jpg | BU78: https://www.sulwhasoo.com/kr/ko/products/lumiwise-brightening-ampoule-serum.html | BV78: summary_large_image | BW78: 자정앰플세럼 | 설화수 | BY78: https://www.sulwhasoo.com/kr/ko/products/lumiwise-brightening-ampoule-serum.html | BZ78: schema.org | CA78: schema.org | CD78: BreadcrumbList | CE78: Product | CL78: https://www.sulwhasoo.com/kr/ko/products/lumiwise-brightening-ampoule-serum.html | CM78: 2026-02-05 15:34:42
A79: https://www.sulwhasoo.com/kr/ko/products/lumiwise-brightening-emulsion.html | B79: text/html | C79: 200 | D79: OK | E79: Indexable | G79: 자정유액 | 설화수 | H79: 10 | I79: 78 | J79: 설화수 자정유액 제품의 특징과 효능을 자세히 확인해보세요. [오프라인 선런칭 *아모레몰 2/19]다시 짙어지지 않고 맑게 이어지는 피부. #브라이트닝 #맑고투명한피부 | K79: 93 | L79: 505 | M79: 아모레퍼시픽, 설화수, 설화수 스킨케어, 브라이트닝, 색소침착, 미백로션, 여드름피부 | N79: 47 | O79: 자정유액 Lumiwise Brightening Emulsion | P79: 34 | R79: 0 | S79: 제품상세 닫기 | T79: 7 | U79: 함께 쓰면 좋은 제품 닫기 | V79: 14 | Z79: https://www.sulwhasoo.com/kr/ko/products/lumiwise-brightening-emulsion.html | AF79: 139770 | AG79: 21826 | AH79: 21826 | AI79: 8.5052212 | AK79: 640 | AL79: 175 | AM79: 3.6571429 | AN79: 100 | AO79: Very Easy | AP79: 2.0617182 | AQ79: 0 | AR79: 3 | AT79: 7 | AU79: 2 | AV79: 0 | AW79: 1.21 | AX79: 22 | AY79: 14 | AZ79: 0 | BA79: 2 | BB79: 2 | BC79: 0 | BH79: f8a561fac9e2840104b85b0bd47d37b6 | BI79: 0.006 | BJ79: Thu, 05 Feb 2026 05:03:34 GMT | BN79: ko | BO79: 1.1 | BP79: 자정유액 | 설화수 | BQ79: 설화수 자정유액 제품의 특징과 효능을 자세히 확인해보세요. [오프라인 선런칭 *아모레몰 2/19]다시 짙어지지 않고 맑게 이어지는 피부. #브라이트닝 #맑고투명한피부 | BR79: website | BS79: 설화수 | BT79: https://www.sulwhasoo.com/kr/ko/products/__icsFiles/afieldfile/2026/01/23/260116_final_KR_LUMIWISE_Brightening_Emulsion_PDP_thumbnail_640x640_01.jpg | BU79: https://www.sulwhasoo.com/kr/ko/products/lumiwise-brightening-emulsion.html | BV79: summary_large_image | BW79: 자정유액 | 설화수 | BY79: https://www.sulwhasoo.com/kr/ko/products/lumiwise-brightening-emulsion.html | BZ79: schema.org | CA79: schema.org | CD79: BreadcrumbList | CE79: Product | CL79: https://www.sulwhasoo.com/kr/ko/products/lumiwise-brightening-emulsion.html | CM79: 2026-02-05 15:35:12
A80: https://www.sulwhasoo.com/kr/ko/products/lumiwise-brightening-essence-water.html | B80: text/html | C80: 200 | D80: OK | E80: Indexable | G80: 자정수 | 설화수 | H80: 9 | I80: 69 | J80: 설화수 자정수 제품의 특징과 효능을 자세히 확인해보세요. [오프라인 선런칭 *아모레몰 2/19]다시 짙어지지 않고 맑게 이어지는 피부. #브라이트닝 #맑고투명한피부 | K80: 92 | L80: 499 | M80: 아모레퍼시픽, 설화수, 설화수 스킨케어, 브라이트닝, 색소침착, 피부결, 각질케어 | N80: 45 | O80: 자정수 Lumiwise Brightening Essence Water | P80: 38 | R80: 0 | S80: 제품상세 닫기 | T80: 7 | U80: 함께 쓰면 좋은 제품 닫기 | V80: 14 | Z80: https://www.sulwhasoo.com/kr/ko/products/lumiwise-brightening-essence-water.html | AF80: 115586 | AG80: 19682 | AH80: 19682 | AI80: 7.6697408 | AK80: 500 | AL80: 136 | AM80: 3.6764706 | AN80: 100 | AO80: Very Easy | AP80: 1.9665411 | AQ80: 0 | AR80: 3 | AT80: 10 | AU80: 5 | AV80: 0 | AW80: 3.03 | AX80: 22 | AY80: 14 | AZ80: 0 | BA80: 2 | BB80: 2 | BC80: 0 | BH80: 45e0d9c9622ae1e1abcaff9ab4ec5c41 | BI80: 0.008 | BJ80: Thu, 05 Feb 2026 05:03:34 GMT | BN80: ko | BO80: 1.1 | BP80: 자정수 | 설화수 | BQ80: 설화수 자정수 제품의 특징과 효능을 자세히 확인해보세요. [오프라인 선런칭 *아모레몰 2/19]다시 짙어지지 않고 맑게 이어지는 피부. #브라이트닝 #맑고투명한피부 | BR80: website | BS80: 설화수 | BT80: https://www.sulwhasoo.com/kr/ko/products/__icsFiles/afieldfile/2026/01/14/260112_final_KR_LUMIWISE_Brightening_Essence_Water_PDP_thumbnail_640x640_01.jpg | BU80: https://www.sulwhasoo.com/kr/ko/products/lumiwise-brightening-essence-water.html | BV80: summary_large_image | BW80: 자정수 | 설화수 | BY80: https://www.sulwhasoo.com/kr/ko/products/lumiwise-brightening-essence-water.html | BZ80: schema.org | CA80: schema.org | CD80: BreadcrumbList | CE80: Product | CL80: https://www.sulwhasoo.com/kr/ko/products/lumiwise-brightening-essence-water.html | CM80: 2026-02-05 15:35:20
A81: https://www.sulwhasoo.com/kr/ko/products/lumiwise-discoloration-corrector.html | B81: text/html | C81: 200 | D81: OK | E81: Indexable | G81: 자정기미코렉터 | 설화수 | H81: 13 | I81: 105 | J81: 설화수 자정기미코렉터 제품의 특징과 효능을 자세히 확인해보세요. [오프라인 선런칭 *아모레몰 2/19]다시 짙어지지 않고 맑게 이어지는 피부. #브라이트닝 #맑고투명한피부 | K81: 96 | L81: 523 | M81: 아모레퍼시픽, 설화수, 설화수 스킨케어, 브라이트닝, 색소침착, 기미케어, 미백크림 | N81: 46 | O81: 자정기미코렉터 Lumiwise Discoloration Corrector | P81: 40 | R81: 0 | S81: 제품상세 닫기 | T81: 7 | U81: 함께 쓰면 좋은 제품 닫기 | V81: 14 | Z81: https://www.sulwhasoo.com/kr/ko/products/lumiwise-discoloration-corrector.html | AF81: 134916 | AG81: 21166 | AH81: 21166 | AI81: 8.2480304 | AK81: 780 | AL81: 246 | AM81: 3.1707317 | AN81: 100 | AO81: Very Easy | AP81: 2.8849726 | AQ81: 0 | AR81: 3 | AT81: 10 | AU81: 5 | AV81: 0 | AW81: 3.03 | AX81: 22 | AY81: 14 | AZ81: 0 | BA81: 2 | BB81: 2 | BC81: 0 | BH81: cea34c007165b92a466a1dfdb2d3f267 | BI81: 0.006 | BJ81: Thu, 05 Feb 2026 05:03:34 GMT | BN81: ko | BO81: 1.1 | BP81: 자정기미코렉터 | 설화수 | BQ81: 설화수 자정기미코렉터 제품의 특징과 효능을 자세히 확인해보세요. [오프라인 선런칭 *아모레몰 2/19]다시 짙어지지 않고 맑게 이어지는 피부. #브라이트닝 #맑고투명한피부 | BR81: website | BS81: 설화수 | BT81: https://www.sulwhasoo.com/kr/ko/products/__icsFiles/afieldfile/2026/01/27/260126_final_KR_LUMIWISE_Corrector_PDP_thumbnail_640x640_01.jpg | BU81: https://www.sulwhasoo.com/kr/ko/products/lumiwise-discoloration-corrector.html | BV81: summary_large_image | BW81: 자정기미코렉터 | 설화수 | BY81: https://www.sulwhasoo.com/kr/ko/products/lumiwise-discoloration-corrector.html | BZ81: schema.org | CA81: schema.org | CD81: BreadcrumbList | CE81: Product | CL81: https://www.sulwhasoo.com/kr/ko/products/lumiwise-discoloration-corrector.html | CM81: 2026-02-05 15:35:40
A82: https://www.sulwhasoo.com/kr/ko/products/makeup/category/base/index.html | B82: text/html | C82: 200 | D82: OK | E82: Indexable | G82: 설화수 베이스 (메이크업) | 설화수 | H82: 20 | I82: 156 | J82: 메이크업 베이스 전체 제품 목록입니다. 베이스부터 포인트까지 다양한 제품을 한눈에 확인하고, 원하는 무드로 나만의 메이크업을 손쉽게 완성해보세요. | K82: 81 | L82: 431 | N82: 0 | O82: 베이스 | P82: 3 | R82: 0 | T82: 0 | V82: 0 | Z82: https://www.sulwhasoo.com/kr/ko/products/makeup/category/base/index.html | AF82: 38737 | AG82: 10579 | AH82: 10579 | AI82: 4.1224565 | AK82: 61 | AL82: 28 | AM82: 2.1785714 | AN82: 100 | AO82: Very Easy | AP82: 0.93776184 | AQ82: 0 | AR82: 6 | AT82: 14 | AU82: 7 | AV82: 0 | AW82: 4.24 | AX82: 25 | AY82: 16 | AZ82: 0 | BA82: 2 | BB82: 2 | BC82: 0 | BH82: e8af6da9e18bbb3d5b2c44b2e994d392 | BI82: 0.008 | BJ82: Mon, 12 Jan 2026 06:36:00 GMT | BN82: ko | BO82: 1.1 | BP82: 설화수 베이스 (메이크업) | 설화수 | BQ82: 메이크업 베이스 전체 제품 목록입니다. 베이스부터 포인트까지 다양한 제품을 한눈에 확인하고, 원하는 무드로 나만의 메이크업을 손쉽게 완성해보세요. | BR82: website | BS82: 설화수 | BT82: https://www.sulwhasoo.com/kr/ko/resource/img/sulwhasoo-og-img_250304.jpg | BU82: https://www.sulwhasoo.com/kr/ko/products/makeup/category/base/index.html | BV82: summary_large_image | BW82: 설화수 베이스 (메이크업) | 설화수 | BY82: https://www.sulwhasoo.com/kr/ko/products/makeup/category/base/index.html | BZ82: schema.org | CD82: BreadcrumbList | CL82: https://www.sulwhasoo.com/kr/ko/products/makeup/category/base/index.html | CM82: 2026-02-05 15:35:31
A83: https://www.sulwhasoo.com/kr/ko/products/makeup/category/cushion/index.html | B83: text/html | C83: 200 | D83: OK | E83: Indexable | G83: 설화수 쿠션 (메이크업) | 설화수 | H83: 19 | I83: 147 | J83: 메이크업 쿠션 전체 제품 목록입니다. 베이스부터 포인트까지 다양한 제품을 한눈에 확인하고, 원하는 무드로 나만의 메이크업을 손쉽게 완성해보세요. | K83: 80 | L83: 425 | N83: 0 | O83: 쿠션 | P83: 2 | R83: 0 | T83: 0 | V83: 0 | Z83: https://www.sulwhasoo.com/kr/ko/products/makeup/category/cushion/index.html | AF83: 38719 | AG83: 10584 | AH83: 10584 | AI83: 4.1244049 | AK83: 61 | AL83: 28 | AM83: 2.1785714 | AN83: 100 | AO83: Very Easy | AP83: 0.93500876 | AQ83: 0 | AR83: 6 | AT83: 14 | AU83: 7 | AV83: 0 | AW83: 4.24 | AX83: 25 | AY83: 16 | AZ83: 0 | BA83: 2 | BB83: 2 | BC83: 0 | BH83: 81758fbf520408dbd232ed43004076e6 | BI83: 0.007 | BJ83: Mon, 12 Jan 2026 06:36:00 GMT | BN83: ko | BO83: 1.1 | BP83: 설화수 쿠션 (메이크업) | 설화수 | BQ83: 메이크업 쿠션 전체 제품 목록입니다. 베이스부터 포인트까지 다양한 제품을 한눈에 확인하고, 원하는 무드로 나만의 메이크업을 손쉽게 완성해보세요. | BR83: website | BS83: 설화수 | BT83: https://www.sulwhasoo.com/kr/ko/resource/img/sulwhasoo-og-img_250304.jpg | BU83: https://www.sulwhasoo.com/kr/ko/products/makeup/category/cushion/index.html | BV83: summary_large_image | BW83: 설화수 쿠션 (메이크업) | 설화수 | BY83: https://www.sulwhasoo.com/kr/ko/products/makeup/category/cushion/index.html | BZ83: schema.org | CD83: BreadcrumbList | CL83: https://www.sulwhasoo.com/kr/ko/products/makeup/category/cushion/index.html | CM83: 2026-02-05 15:35:58
A84: https://www.sulwhasoo.com/kr/ko/products/makeup/category/foundation/index.html | B84: text/html | C84: 200 | D84: OK | E84: Indexable | G84: 설화수 파운데이션 (메이크업) | 설화수 | H84: 22 | I84: 174 | J84: 메이크업 파운데이션 전체 제품 목록입니다. 베이스부터 포인트까지 다양한 제품을 한눈에 확인하고, 원하는 무드로 나만의 메이크업을 손쉽게 완성해보세요. | K84: 83 | L84: 443 | N84: 0 | O84: 파운데이션 | P84: 5 | R84: 0 | T84: 0 | V84: 0 | Z84: https://www.sulwhasoo.com/kr/ko/products/makeup/category/foundation/index.html | AF84: 38821 | AG84: 10587 | AH84: 10587 | AI84: 4.1255739 | AK84: 61 | AL84: 28 | AM84: 2.1785714 | AN84: 100 | AO84: Very Easy | AP84: 0.94204658 | AQ84: 0 | AR84: 6 | AT84: 14 | AU84: 7 | AV84: 0 | AW84: 4.24 | AX84: 25 | AY84: 16 | AZ84: 0 | BA84: 2 | BB84: 2 | BC84: 0 | BH84: f186093cdb9092e767fda96a6ea1269e | BI84: 0.011 | BJ84: Mon, 12 Jan 2026 06:36:02 GMT | BN84: ko | BO84: 1.1 | BP84: 설화수 파운데이션 (메이크업) | 설화수 | BQ84: 메이크업 파운데이션 전체 제품 목록입니다. 베이스부터 포인트까지 다양한 제품을 한눈에 확인하고, 원하는 무드로 나만의 메이크업을 손쉽게 완성해보세요. | BR84: website | BS84: 설화수 | BT84: https://www.sulwhasoo.com/kr/ko/resource/img/sulwhasoo-og-img_250304.jpg | BU84: https://www.sulwhasoo.com/kr/ko/products/makeup/category/foundation/index.html | BV84: summary_large_image | BW84: 설화수 파운데이션 (메이크업) | 설화수 | BY84: https://www.sulwhasoo.com/kr/ko/products/makeup/category/foundation/index.html | BZ84: schema.org | CD84: BreadcrumbList | CL84: https://www.sulwhasoo.com/kr/ko/products/makeup/category/foundation/index.html | CM84: 2026-02-05 15:35:09
A85: https://www.sulwhasoo.com/kr/ko/products/makeup/category/index.html | B85: text/html | C85: 200 | D85: OK | E85: Indexable | G85: 설화수 유형별 전체 (메이크업) | 설화수 | H85: 23 | I85: 179 | J85: 메이크업 유형별 전체 제품 목록입니다. 베이스부터 포인트까지 다양한 제품을 한눈에 확인하고, 원하는 무드로 나만의 메이크업을 손쉽게 완성해보세요. | K85: 81 | L85: 431 | N85: 0 | O85: 제품 유형별 | P85: 6 | R85: 0 | T85: 0 | V85: 0 | Z85: https://www.sulwhasoo.com/kr/ko/products/makeup/category/index.html | AF85: 38650 | AG85: 10598 | AH85: 10598 | AI85: 4.1298604 | AK85: 62 | AL85: 28 | AM85: 2.2142857 | AN85: 100 | AO85: Very Easy | AP85: 0.94938427 | AQ85: 0 | AR85: 5 | AT85: 14 | AU85: 7 | AV85: 0 | AW85: 4.24 | AX85: 25 | AY85: 16 | AZ85: 0 | BA85: 2 | BB85: 2 | BC85: 0 | BH85: 19a9754d46b10284c6631311a85a3c7b | BI85: 0.006 | BJ85: Mon, 12 Jan 2026 06:36:02 GMT | BN85: ko | BO85: 1.1 | BP85: 설화수 유형별 전체 (메이크업) | 설화수 | BQ85: 메이크업 유형별 전체 제품 목록입니다. 베이스부터 포인트까지 다양한 제품을 한눈에 확인하고, 원하는 무드로 나만의 메이크업을 손쉽게 완성해보세요. | BR85: website | BS85: 설화수 | BT85: https://www.sulwhasoo.com/kr/ko/resource/img/sulwhasoo-og-img_250304.jpg | BU85: https://www.sulwhasoo.com/kr/ko/products/makeup/category/index.html | BV85: summary_large_image | BW85: 설화수 유형별 전체 (메이크업) | 설화수 | BY85: https://www.sulwhasoo.com/kr/ko/products/makeup/category/index.html | BZ85: schema.org | CD85: BreadcrumbList | CL85: https://www.sulwhasoo.com/kr/ko/products/makeup/category/index.html | CM85: 2026-02-05 15:35:11
